Workbook

Sheet 특이사항
A2: 2023.05 특이사항
A4: (1) 하나은행 KRW 거래내역 질문
B5: 은행 조회 자료 | G5: Weekly Cash Closing Package 자료 발췌 | I5: KPMG 질문 | J5: EQUIS 답변
B6: No | C6: 거래일시 | D6: 적요 | E6: 의뢰인/수취인 | F6: 입금 | G6: Description | H6: Concur Invoice Name (Racquel)
B7: 1 | C7: 2023-02-23 09:48:37 | D7: 삼성화재입금 | E7: 삼성화재해상보험(주 | F7: 736480 | H7: no supporting documents | J7: >>(구)금명에게 지급하여야 함.
B8: 2 | C8: 2023-02-23 10:50:17 | D8: 삼성화재입금 | E8: 삼성화재해상보험(주 | F8: 707420 | H8: no supporting documents | J8: >>(구)금명에게 지급하여야 함.
B9: 3 | C9: 2023-02-23 14:41:15 | D9: 산재반환금 | E9: 근로복지공단 | F9: 476370 | H9: no supporting documents | J9: >>(구)금명에게 지급하여야 함.
B10: 4 | C10: 2023-02-23 14:41:17 | D10: 석면반환금 | E10: 근로복지공단 | F10: 1420 | H10: no supporting documents | J10: >>(구)금명에게 지급하여야 함.
B11: 5 | C11: 2023-02-23 14:41:25 | D11: 임채반환금 | E11: 근로복지공단 | F11: 28580 | H11: no supporting documents | J11: >>(구)금명에게 지급하여야 함.
B12: 6 | C12: 2023-02-28 17:08:22 | D12: 과오납연금 | E12: 국민연금 | F12: 216230 | H12: Overpayment | J12: >>(구)금명에게 지급하여야 함.
B13: 7 | C13: 2023-03-13 17:07:55 | D13: 과오납연금 | E13: 국민연금 | F13: 440450 | J13: >>(구)금명에게 지급하여야 함.
B14: 8 | C14: 2023-03-14 16:15:19 | D14: 한전남전주지사 | E14: 한국전력공사 | F14: 592060 | J14: >>(구)금명에게 지급하여야 함.
A16: (2) 하나은행 USD 거래내역 질문
B17: 은행 조회 자료 | G17: Weekly Cash Closing Package 자료 발췌 | I17: KPMG 질문 | J17: EQUIS 답변
B18: No | C18: 거래일시 | D18: 적요 | E18: 통화 | F18: 입금 | G18: Description | H18: Concur Invoice Name (Racquel)
B19: 1 | C19: 2023-01-13 14:51:59 | D19: 에퀴스에너지코리아2유한회사 | E19: USD | F19: 5360000 | G19: 에퀴스에너지코리아2유한회사 | H19: no supporting documents | I19: 계약서 요청_기간, 이자율 확인 필요 | J19: 계약서 수령, 14%, 원화금액으로 인식
A21: (3) 신협 거래내역 질문
B22: 은행 조회 자료 | G22: Weekly Cash Closing Package 자료 발췌 | I22: KPMG 질문 | J22: EQUIS 답변
B23: 순번 | C23: 거래일자 | D23: 출금금액 | E23: 입금금액 | F23: 거래기록사항 | G23: Description | H23: Concur Invoice Name (Racquel)
B24: 1 | C24: 2023-03-30 | D24: 0 | E24: 63040 | F24: 건강보험환급 | G24: 전자금융 | H24: no supporting documents | J24: >>(구)금명에게 지급하여야 함.
B25: 2 | C25: 2023-03-30 | D25: 0 | E25: 11200 | F25: 장기요양환급 | G25: 전자금융 | H25: no supporting documents | J25: >>(구)금명에게 지급하여야 함.
B26: 3 | C26: 2023-04-07 | D26: 0 | E26: 358440 | F26: 건강보험환급 | G26: 전자금융 | H26: no supporting documents | J26: >>(구)금명에게 지급하여야 함.
B27: 4 | C27: 2023-04-07 | D27: 0 | E27: 46210 | F27: 장기요양환급 | G27: 전자금융 | H27: no supporting documents | J27: >>(구)금명에게 지급하여야 함.
B28: 5 | C28: 2023-04-20 | D28: 0 | E28: 112840 | F28: 장기요양환급 | G28: 전자금융 | H28: no supporting documents | J28: >>(구)금명에게 지급하여야 함.
B29: 6 | C29: 2023-04-20 | D29: 0 | E29: 881040 | F29: 건강보험환급 | G29: 전자금융 | H29: no supporting documents | J29: >>(구)금명에게 지급하여야 함.
B30: 7 | C30: 2023-05-02 | D30: 8712328 | E30: 0 | F30: 210059099464 | G30: Local office mainten | H30: no supporting documents | I30: 출금사유 및 증빙 요청 | J30: 대출금 계약서 제공해주심
B31: 8 | C31: 2023-05-31 | D31: 9002739 | E31: 0 | F31: 210059099464 | G31: 210059099464 | H31: no supporting documents | I31: 출금사유 및 증빙 요청 | J31: 대출금 계약서 제공해주심
A33: (4) 기타
B34: NO | C34: 내용 | I34: KPMG 질문 | J34: EQUIS 답변
B35: 1 | C35: 통장출금_토지 매매대금 | I35: 통장 출금내역 중 토지 매매대금, 취득세 등은 토지 계정으로 반영 예정입니다. | J35: ok 유선확인
B36: 2 | C36: 통장출금_취득세 납부
B37: 3 | C37: 매입세금계산서_법무사수수료 (등기) | I37: 매입세금계산서중 법무사비용은 토지 취득의 부대비용으로, 매입세액 불공제 하고 토지 계정으로 반영 예정입니다. | J37: ok 유선확인
A39: (5) 매입세금계산서 및 계산서
B40: 구분 | C40: 작성일자 | D40: 상호 | E40: 합계금액 | F40: 공급가액 | G40: 세액 | H40: 품목명 | I40: KPMG 질문 | J40: EQUIS 답변
B41: 세금계산서 | C41: 2023-02-07 | D41: 주식회사 케이티 | E41: 54516 | F41: 49560 | G41: 4956 | H41: 일반전화 (006103335896) | I41: 대금납부_금명? Or 금명건설? | J41: 금명건설이 납부해야 함, 장부반영x / 부가세 수정 필요함
B42: 세금계산서 | C42: 2023-02-07 | D42: 주식회사 케이티 | E42: 39600 | F42: 36000 | G42: 3600 | H42: 인터넷 베이직 (z!67151690062) | I42: 대금납부_금명? Or 금명건설? | J42: 금명건설이 납부해야 함, 장부반영x / 부가세 수정 필요함
B43: 세금계산서 | C43: 2023-02-09 | D43: 한국전력공사 | E43: 334749 | F43: 304317 | G43: 30432 | H43: 전기요금(1228771682) | I43: 대금납부_금명? Or 금명건설? | J43: 금명건설이 납부해야 함, 장부반영x / 부가세 수정 필요함
B44: 세금계산서 | C44: 2023-02-09 | D44: 한국전력공사 | E44: 77123 | F44: 70112 | G44: 7011 | H44: 전기요금(0341826108) | I44: 대금납부_금명? Or 금명건설? | J44: 금명건설이 납부해야 함, 장부반영x / 부가세 수정 필요함
B45: 세금계산서 | C45: 2023-03-09 | D45: 한국전력공사 | E45: 278388 | F45: 253080 | G45: 25308 | H45: 전기요금(1228771682) | I45: 대금납부_금명? Or 금명건설? | J45: 금명건설이 납부해야 함, 장부반영x / 부가세 수정 필요함
B46: 세금계산서 | C46: 2023-05-07 | D46: 주식회사 케이티 | E46: 97572 | F46: 88702 | G46: 8870 | H46: 일반전화 (006102434885) | I46: 대금납부_금명
B47: 계산서 | C47: 2023-02-15 | D47: 폭스바겐파이낸셜서비스코리아주식회사 | E47: 602500 | F47: 602500 | H47: 리스료 | I47: 대금납부_금명? Or 금명건설? | J47: 금명건설이 납부해야 함, 장부반영x / 부가세 수정 필요함
B48: 세금계산서 | C48: 411-08-77777 | D48: 신안사무용가구 | E48: 2115300 | F48: 1923000 | G48: 192300 | H48: 일자형책상1600 외 9건 | I48: 비품(가구)_감가상각자산 or 소모품비 | J48: 일시 비용 처리 (사무용품비 계정 사용)
B49: 세금계산서 | C49: 411-08-69961 | D49: 하나로열쇠 | E49: 187000 | F49: 170000 | G49: 17000 | H49: 디지털도어락 | I49: 비품(가구)_감가상각자산 or 소모품비 | J49: 일시 비용 처리 (사무용품비 계정 사용)
B50: 세금계산서 | C50: 411-09-38015 | D50: 준디자인 | E50: 275000 | F50: 250000 | G50: 25000 | H50: 사무실 에칭시트 썬팅 | I50: 비품(가구)_감가상각자산 or 소모품비 | J50: 일시 비용 처리 (사무용품비 계정 사용)
B51: 세금계산서 | C51: 214-86-43198 | D51: 이노컴퍼니 주식회사 | E51: 1914000 | F51: 1740000 | G51: 174000 | H51: Lenovo ThinkPad T14 G3 1EA | I51: 비품(가구)_감가상각자산 or 소모품비 | J51: 일시 비용 처리 (사무용품비 계정 사용)
B52: 세금계산서 | C52: 411-08-77777 | D52: 신안사무용가구 | E52: 542300 | F52: 493000 | G52: 49300 | H52: 파티션1600*1200 외 3건 | I52: 비품(가구)_감가상각자산 or 소모품비 | J52: 일시 비용 처리 (사무용품비 계정 사용)
B53: 세금계산서 | C53: 104-81-16860 | D53: 롯데하이마트(주) | E53: 226000 | F53: 205454 | G53: 20546 | H53: 가전,통신,컴퓨터 등 | I53: 비품(가구)_감가상각자산 or 소모품비 | J53: 일시 비용 처리 (사무용품비 계정 사용)
B54: 세금계산서 | C54: 2023-02-16 | D54: (주)삼정개발 | E54: 38280000 | F54: 34800000 | G54: 3480000 | H54: 부동산중개 용역수수료 | I54: 토지 취득 부대비용으로 확인해주심 (1Q 부가세) | J54: 토지 취득 부대비용 OK
B55: 세금계산서 | C55: 2023-04-03 | D55: (주)삼정개발 | E55: -1600 | F55: -1460 | G55: -140 | H55: 용역비 (Land Commission) | I55: 토지 취득 부대비용 or 수수료 | J55: 토지 취득 부대비용 OK
B56: 세금계산서 | C56: 2023-04-03 | D56: (주)삼정개발 | E56: 34374400 | F56: 31249460 | G56: 3124940 | H56: 용역비 (Land Commission) | I56: 토지 취득 부대비용 or 수수료 | J56: 토지 취득 부대비용 OK
B57: 세금계산서 | C57: 2023-05-09 | D57: (주)삼정개발 | E57: 18238000 | F57: 16580000 | G57: 1658000 | H57: 용역비 (Land Commission) | I57: 토지 취득 부대비용 or 수수료 | J57: 토지 취득 부대비용 OK
B58: 세금계산서 | C58: 2023-05-30 | D58: (주)삼정개발 | E58: 23975600 | F58: 21796000 | G58: 2179600 | H58: 용역비 (Land Commission) | I58: 토지 취득 부대비용 or 수수료 | J58: 토지 취득 부대비용 OK
A60: (6) 분할 등기 비용 관련 문의
B61: 회사분할 [설립]에 해당하는 비용은 [금명건설]에서 인식하고 부담해야 할 비용이 맞을까요?
B62: 전액 금명에서 지급한 것으로 보이는데, 통장에서 출금되는 시점에는 이미 분할전표로 인해 반제할 미지급금이 남아있지 않은 상태입니다.
B63: 아래 금액의 처리 방법 관련하여 문의드립니다.
B64: EQUIS 답변 => 해당금액은 전액 금명의 비용으로 처리 부탁드리겠습니다(금명건설로부터 받을 금액이 아닌).
A66: Date | B66: Vendor Name | C66: Total Amount | D66: Base Amount | E66: VAT | F66: 품목명 | G66: 제비용 | H66: 총 지급액 | I66: 확인사항
A67: 2023-01-16 | B67: 법무법인(유한) 광장 | C67: 2420000 | D67: 2200000 | E67: 220000 | F67: E517F20 등기 | G67: =+G70+G71 -> 1678560 | H67: =C67+G67 -> 4098560 | I67: . 1/16일 더존자료 (분할전 재무제표에 이미 반영) . 분할전표로 미지급금 삭제 되었으나, . 전액 EQUIS에서 2/9일 지급
B69: 세부내역 | C69: Total Amount | D69: Base Amount | E69: VAT | F69: 품목명 | G69: 제비용 | H69: 총 지급액 | I69: 질문사항 | J69: EQUIS 답변
B70: EQUIS 부담금 | C70: =+D70+E70 -> 1100000 | D70: 1000000 | E70: =D70/10 -> 100000 | F70: 회사분할_변경 | G70: 132480 | H70: =C70+G70 -> 1232480
B71: 금명건설 부담금 | C71: =+D71+E71 -> 1320000 | D71: 1200000 | E71: =D71/10 -> 120000 | F71: 회사분할_설립 | G71: 1546080 | H71: =C71+G71 -> 2866080 | I71: 금명건설로부터 받을 돈으로 인식하면 될까요? | J71: EQUIS 답변 => 해당금액은 전액 금명의 비용으로 처리 부탁드리겠습니다(금명건설로부터 받을 금액이 아닌).
B73: 구분(1) | C73: 구분(2) | D73: 금액 | E73: As-is | F73: should be
B74: 금명(EQUIS) 부담금 | C74: =D69 -> Base Amount | D74: =D70 -> 1000000 | E74: 수수료 | F74: =E74 -> 수수료 | I74: 8/31일자 수수료 -> 감자차손 변경
B75: 금명(EQUIS) 부담금 | C75: =E69 -> VAT | D75: =E70 -> 100000 | E75: 부가세대급금 | F75: =E75 -> 부가세대급금
B76: 금명(EQUIS) 부담금 | C76: =G69 -> 제비용 | D76: =G70 -> 132480 | E76: 반영x | F76: 수수료
B77: 금명건설 부담금 | C77: =C74 -> Base Amount | D77: =D71 -> 1200000 | E77: 수수료 | F77: 잡손실
B78: 금명건설 부담금 | C78: =C75 -> VAT | D78: =E71 -> 120000 | E78: 부가세대급금 | F78: 잡손실
B79: 금명건설 부담금 | C79: =C76 -> 제비용 | D79: =G71 -> 1546080 | E79: 반영x | F79: 잡손실
D80: =SUM(D74:D79) -> 4098560
B82: 1/16 매입전표 | C82: 수수료 | D82: 2200000 | E82: 미지급비용 | F82: 2420000
C83: 부가세대급금 | D83: 220000
B85: 1/16 분할전표 | C85: 미지급비용 | D85: 2420000 | E85: 미처분 이익잉여금 | F85: 2200000
E86: 부가세대급금 | F86: 220000
B88: 2/9 지급전표 | C88: 수수료 | D88: -1200000 | E88: 통장 | F88: 4098560 | G88: 금명건설 설립 비용 (1/16 비용 일부 조정 효과)
C89: 잡손실 | D89: 1200000 | G89: 금명건설 설립 비용
C90: 잡손실 | D90: 1546080 | G90: 금명건설 설립 제비용
C91: 수수료 | D91: 132480 | G91: 금명 변경등기 제비용 | I91: 8/31일자 수수료 -> 감자차손 변경
C92: 잡손실 | D92: 2420000 | G92: 금명에서 지급하기로 약정한 수수료 및 부가세
B95: 부가세 수정신고시 | C95: 잡손실 | D95: 120000 | E95: 통장(부가세납부) | F95: 120000 | G95: 금명은 공제한다고 했으나 실제로는 불공제
B98: check | C98: 잡손실 | D98: =SUMIFS($D$82:$D$92,$C$82:$C$92,C98) -> 5166080 | E98: ok (금명건설의 입장에서, 부담하지 않은 비용 (1,200,000+1,546,080) + 미지급금 안갚아도 되니까 언젠간 영업외이익이 될 금액 (2,420,000))
C99: 수수료 | D99: =SUMIFS($D$82:$D$92,$C$82:$C$92,C99) -> 1132480 | E99: ok (금명의 실제 분할등기 수수료 1,000,000 + 제비용 132,480)
A101: (7) 토지 매입을 위한 대출금 차입원가 자본화
A102: 아래 이자 비용중 토지 매입에 사용된 금액에 대한 이자부분은 자본화대상입니다. 다만, 월결산시에는 전액 토지로 인식하고, 토지 매입완료시점 또는 기말 시점에 기간 안분 계산 예정 입니다.
B103: 일(월) | C103: 구분 | D103: 대출금 입금 | E103: 출금 (토지 매매) | F103: EEK2 이자 | G103: 신협 이자
B104: 01월 13일 | C104: EEK2 | D104: 6661408000
B105: 1월 | E105: 3141377260 | F105: 48546151
B106: 2월 | E106: 283910376 | F106: 71541697
B107: 3월 | E107: 571378100 | F107: 79206879 | G107: -
B108: 03월 31일 | C108: 신협 | D108: 2000000000
B109: 4월 | E109: 509874200 | F109: 76651818 | G109: 8712328
B110: 5월 | E110: 1150460860 | F110: 79206879 | G110: 9002739
B112: 누계 | D112: 8661408000 | E112: 5657000796 | F112: 355153424 | G112: 17715067
A115: 2023.07 특이사항
A117: @Hwajin Kim 차장님,
A118: 금명 차입금 이자지급 관련하여 질의 드립니다. 계약서상 이자지급일이 지난 것으로 보여, 이자 상환계획에 변동이 있으면 알려주시면 감사하겠습니다.
A120: [EQUIS 회신]
A121: 문의주신 금명 차입금 이자지급은 관련하여 이자지급일을 만기에 상환하는 것으로 약정서를 수정하였고, 이자상환은 이에 따라 만기에 진행할 예정입니다.
A122: 업무에 참고 부탁드리며, 변경된 agreement 별도의 메일로 공유 드리도록 하겠습니다.
A124: @Jiyu Lee 대리님
...

Sheet FS →

Sheet CONTENTS
C2: 46112
D5: Kummyung Ltd.
D6: MONTHLY REPORTING CONTENTS
B11: FINANCIAL STATEMENTS
B12: - | C12: BALANCE SHEET
B13: - | C13: INCOME STATEMENT
B14: - | C14: TRIAL BALANCE
B15: - | C15: JOURNAL ENTRY
B16: - | C16: GENERAL LEDGER
B17: - | C17: GENERAL LEDGER(Up to reported month)
B19: DETAIL FOR BS RECONCILIATION
B20: - | C20: SUMMARY BANK
B21: - | C21: PREPAID TAX
B22: - | C22: Loan receivables
B23: - | C23: Intercompany loans
B24: - | C24: FX - realized / unrealized gains & losses
B25: - | C25: VAT payable
B26: - | C26: GST/VAT receivable
B27: - | C27: CAPITAL

Sheet journal 2025_KPMG
B1: ※ 조회기간 : 2025/01/01 ~ 2025/02/28
A2: 전표월 | B2: 전표번호 | C2: 현재상태 | D2: 전표일자 | E2: 제목 | F2: 기표일 | G2: 이체일 | H2: 계정 | I2: 계정명 | J2: 차변(FC) | K2: 대변(FC) | L2: 통화 | M2: 환율 | N2: 차변(TC) | O2: 대변(TC) | P2: 거래처코드 | R2: 거래처명 | S2: 은행명 | T2: 은행계좌 | U2: 예금주 | V2: 증빙종류 | W2: 적요 | X2: 보조계정 | Y2: 보조계정명 | Z2: 반제여부 | AA2: 반제일자 | AB2: 반제 계정코드 | AC2: 반제-계정명 | AD2: 반제-은행 | AE2: 반제-계좌 | AF2: 반제-예금주 | AG2: 확장코드 | AH2: 확장코드명
A3: =MID(D3,1,6) -> 202501 | B3: 250100001UP | C3: 승인 | D3: 20250102 | E3: (HTX)_공인인증서(은행/보험용) | H3: 5301-00-000 | I3: 은행 수수료 | J3: 4000 | K3: 0 | L3: KRW | M3: 1 | N3: 4000 | P3: 2028114695 | R3: HANA BANK (주)하나은행 | W3: 공인인증서(은행/보험용)_HANA BANK (주)하나은행 | Z3: OFF | AG3: PTI | AH3: 매입세금계산서
A4: =MID(D4,1,6) -> 202501 | B4: 250100001UP | C4: 승인 | D4: 20250102 | E4: (HTX)_공인인증서(은행/보험용) | H4: 2407-00-000 | I4: 부가세대급금 | J4: 400 | K4: 0 | L4: KRW | M4: 1 | N4: 400 | P4: 2028114695 | R4: HANA BANK (주)하나은행 | W4: VAT_공인인증서(은행/보험용)_HANA BANK (주)하나은행 | Z4: OFF | AG4: PTI | AH4: 매입세금계산서
A5: =MID(D5,1,6) -> 202501 | B5: 250100001UP | C5: 승인 | D5: 20250102 | E5: (HTX)_공인인증서(은행/보험용) | H5: 2202-00-001 | I5: 기타미지급금 | J5: 0 | K5: 4400 | L5: KRW | M5: 1 | O5: 4400 | P5: 2028114695 | R5: HANA BANK (주)하나은행 | W5: 공인인증서(은행/보험용)_HANA BANK (주)하나은행 | Z5: OFF | AG5: PTI | AH5: 매입세금계산서
A6: =MID(D6,1,6) -> 202501 | B6: 250100006UP | C6: 승인 | D6: 20250102 | E6: [KR Inv_202412] VJIPYON02_Kummyung_Registration fee for debt to equity_KRW 23487000 | H6: 1112-KR-001 | I6: 현금 - 원 (HANA) | J6: 0 | K6: 23487500 | L6: KRW | M6: 1 | O6: 23487500 | P6: 201-910031-85704 | R6: HANA_Bank 하나은행(85704) | W6: [KR Inv_202412] VJIPYON02_Kummyung_Registration fee for debt to equity_KRW 23487000 | Z6: OFF | AG6: BANK | AH6: 통장
A7: =MID(D7,1,6) -> 202501 | B7: 250100006UP | C7: 승인 | D7: 20250102 | E7: [KR Inv_202412] VJIPYON02_Kummyung_Registration fee for debt to equity_KRW 23487000 | H7: 2202-00-001 | I7: 기타미지급금 | J7: 23487000 | K7: 0 | L7: KRW | M7: 1 | N7: 23487000 | P7: 1048617068 | R7: JIPYONG LLC.법무법인(유한) 지평 | W7: [KR Inv_202412] VJIPYON02_Kummyung_Registration fee for debt to equity_KRW 23487000 | Z7: OFF | AG7: BANK | AH7: 통장
A8: =MID(D8,1,6) -> 202501 | B8: 250100006UP | C8: 승인 | D8: 20250102 | E8: [KR Inv_202412] VJIPYON02_Kummyung_Registration fee for debt to equity_KRW 23487000 | H8: 5301-00-000 | I8: 은행 수수료 | J8: 500 | K8: 0 | L8: KRW | M8: 1 | N8: 500 | P8: 201-910031-85704 | R8: HANA_Bank 하나은행(85704) | W8: Bank charge | Z8: OFF | AG8: BANK | AH8: 통장
A9: =MID(D9,1,6) -> 202501 | B9: 250100007UP | C9: 승인 | D9: 20250102 | E9: [KR Inv_202411] VNEULSA01_Kummyung_Real estate transaction amount_KRW 12000000 | H9: 1112-KR-001 | I9: 현금 - 원 (HANA) | J9: 0 | K9: 12000500 | L9: KRW | M9: 1 | O9: 12000500 | P9: 201-910031-85704 | R9: HANA_Bank 하나은행(85704) | W9: [KR Inv_202411] VNEULSA01_Kummyung_Real estate transaction amount_KRW 12000000 | Z9: OFF | AG9: BANK | AH9: 통장
A10: =MID(D10,1,6) -> 202501 | B10: 250100007UP | C10: 승인 | D10: 20250102 | E10: [KR Inv_202411] VNEULSA01_Kummyung_Real estate transaction amount_KRW 12000000 | H10: 2202-00-001 | I10: 기타미지급금 | J10: 12000000 | K10: 0 | L10: KRW | M10: 1 | N10: 12000000 | P10: 4118183990 | R10: (유)늘샘쏠라에너지 | W10: [KR Inv_202411] VNEULSA01_Kummyung_Real estate transaction amount_KRW 12000000 | Z10: OFF | AG10: BANK | AH10: 통장
A11: =MID(D11,1,6) -> 202501 | B11: 250100007UP | C11: 승인 | D11: 20250102 | E11: [KR Inv_202411] VNEULSA01_Kummyung_Real estate transaction amount_KRW 12000000 | H11: 5301-00-000 | I11: 은행 수수료 | J11: 500 | K11: 0 | L11: KRW | M11: 1 | N11: 500 | P11: 201-910031-85704 | R11: HANA_Bank 하나은행(85704) | W11: Bank charge | Z11: OFF | AG11: BANK | AH11: 통장
A12: =MID(D12,1,6) -> 202501 | B12: 250100008UP | C12: 승인 | D12: 20250102 | E12: Issuance Fee payment | H12: 1112-KR-001 | I12: 현금 - 원 (HANA) | J12: 0 | K12: 4400 | L12: KRW | M12: 1 | O12: 4400 | P12: 201-910031-85704 | R12: HANA_Bank 하나은행(85704) | W12: Issuance Fee payment | Z12: OFF | AG12: BANK | AH12: 통장
A13: =MID(D13,1,6) -> 202501 | B13: 250100008UP | C13: 승인 | D13: 20250102 | E13: Issuance Fee payment | H13: 2202-00-001 | I13: 기타미지급금 | J13: 4400 | K13: 0 | L13: KRW | M13: 1 | N13: 4400 | P13: 2028114695 | R13: HANA BANK (주)하나은행 | W13: Issuance Fee payment | Z13: OFF | AG13: BANK | AH13: 통장
A14: =MID(D14,1,6) -> 202501 | B14: 250100009UP | C14: 승인 | D14: 20250108 | E14: [KR Inv_202501] VCOMNAM01_Project Phantom - Jeju Air Passenger Plane Crash Victim Charity_KRW 20000000 | H14: 1112-KR-001 | I14: 현금 - 원 (HANA) | J14: 0 | K14: 20000000 | L14: KRW | M14: 1 | O14: 20000000 | P14: 201-910031-85704 | R14: HANA_Bank 하나은행(85704) | W14: [KR Inv_202501] VCOMNAM01_Project Phantom - Jeju Air Passenger Plane Crash Victim Charity_KRW 20000000 | Z14: OFF | AG14: BANK | AH14: 통장
A15: =MID(D15,1,6) -> 202501 | B15: 250100009UP | C15: 승인 | D15: 20250108 | E15: [KR Inv_202501] VCOMNAM01_Project Phantom - Jeju Air Passenger Plane Crash Victim Charity_KRW 20000000 | H15: 5319-00-000 | I15: 기부금 | J15: 20000000 | K15: 0 | L15: KRW | M15: 1 | N15: 20000000 | P15: 4098209674 | R15: 사회복지법인 사회복지공동모금회 전라남도지회 | W15: [KR Inv_202501] VCOMNAM01_Project Phantom - Jeju Air Passenger Plane Crash Victim Charity_KRW 20000000 | Z15: OFF | AG15: BANK | AH15: 통장
A16: =MID(D16,1,6) -> 202501 | B16: 250100002UP | C16: 승인 | D16: 20250110 | E16: (HTX)_12월 관리비 | H16: 5101-00-000 | I16: 관리 수수료 비용 | J16: 333100 | K16: 0 | L16: KRW | M16: 1 | N16: 333100 | P16: 1168268413 | R16: 세정아울렛 관리단 | W16: 12월 관리비_세정아울렛 관리단 | Z16: OFF | AG16: PTI | AH16: 매입세금계산서
A17: =MID(D17,1,6) -> 202501 | B17: 250100002UP | C17: 승인 | D17: 20250110 | E17: (HTX)_12월 관리비 | H17: 2407-00-000 | I17: 부가세대급금 | J17: 33310 | K17: 0 | L17: KRW | M17: 1 | N17: 33310 | P17: 1168268413 | R17: 세정아울렛 관리단 | W17: VAT_12월 관리비_세정아울렛 관리단 | Z17: OFF | AG17: PTI | AH17: 매입세금계산서
A18: =MID(D18,1,6) -> 202501 | B18: 250100002UP | C18: 승인 | D18: 20250110 | E18: (HTX)_12월 관리비 | H18: 2202-00-001 | I18: 기타미지급금 | J18: 0 | K18: 366410 | L18: KRW | M18: 1 | O18: 366410 | P18: 1168268413 | R18: 세정아울렛 관리단 | W18: 12월 관리비_세정아울렛 관리단 | Z18: OFF | AG18: PTI | AH18: 매입세금계산서
A19: =MID(D19,1,6) -> 202501 | B19: 250100010UP | C19: 승인 | D19: 20250117 | E19: [KR Inv_202501] VSEJUNG01_Kummyung office maintenance fee_KRW 366,410 | H19: 1112-KR-001 | I19: 현금 - 원 (HANA) | J19: 0 | K19: 366410 | L19: KRW | M19: 1 | O19: 366410 | P19: 201-910031-85704 | R19: HANA_Bank 하나은행(85704) | W19: [KR Inv_202501] VSEJUNG01_Kummyung office maintenance fee_KRW 366,410 | Z19: OFF | AG19: BANK | AH19: 통장
A20: =MID(D20,1,6) -> 202501 | B20: 250100010UP | C20: 승인 | D20: 20250117 | E20: [KR Inv_202501] VSEJUNG01_Kummyung office maintenance fee_KRW 366,410 | H20: 2202-00-001 | I20: 기타미지급금 | J20: 366410 | K20: 0 | L20: KRW | M20: 1 | N20: 366410 | P20: 1168268413 | R20: 세정아울렛 관리단 | W20: [KR Inv_202501] VSEJUNG01_Kummyung office maintenance fee_KRW 366,410 | Z20: OFF | AG20: BANK | AH20: 통장
A21: =MID(D21,1,6) -> 202501 | B21: 250100003UP | C21: 승인 | D21: 20250131 | E21: (HTX)_용역보수 | H21: 5249-00-000 | I21: 기타 법률 및 전문 수수료 | J21: 1400000 | K21: 0 | L21: KRW | M21: 1 | N21: 1400000 | P21: 1028134334 | R21: KPMG 삼정회계법인 | W21: 용역보수_KPMG 삼정회계법인 | Z21: OFF | AG21: PTI | AH21: 매입세금계산서
A22: =MID(D22,1,6) -> 202501 | B22: 250100003UP | C22: 승인 | D22: 20250131 | E22: (HTX)_용역보수 | H22: 2407-00-000 | I22: 부가세대급금 | J22: 140000 | K22: 0 | L22: KRW | M22: 1 | N22: 140000 | P22: 1028134334 | R22: KPMG 삼정회계법인 | W22: VAT_용역보수_KPMG 삼정회계법인 | Z22: OFF | AG22: PTI | AH22: 매입세금계산서
A23: =MID(D23,1,6) -> 202501 | B23: 250100003UP | C23: 승인 | D23: 20250131 | E23: (HTX)_용역보수 | H23: 2202-00-001 | I23: 기타미지급금 | J23: 0 | K23: 1540000 | L23: KRW | M23: 1 | O23: 1540000 | P23: 1028134334 | R23: KPMG 삼정회계법인 | W23: 용역보수_KPMG 삼정회계법인 | Z23: OFF | AG23: PTI | AH23: 매입세금계산서
A24: =MID(D24,1,6) -> 202501 | B24: 250100004UP | C24: 승인 | D24: 20250131 | E24: (HTX)_FY2024 Q4 MSA Chargeback | H24: 2203-00-000 | I24: 관계사미지급금 | J24: 147977176 | K24: 0 | L24: KRW | M24: 1 | N24: 147977176 | P24: 5028400374 | R24: ECSK BO 에퀴스센트럴서비스코리아피티이엘티디 (영업소) | W24: FY2024 Q4 MSA Chargeback_ECSK BO 에퀴스센트럴서비스코리아피티이엘티디 (영업소) | Z24: OFF | AG24: PTI | AH24: 매입세금계산서
A25: =MID(D25,1,6) -> 202501 | B25: 250100004UP | C25: 승인 | D25: 20250131 | E25: (HTX)_FY2024 Q4 MSA Chargeback | H25: 2407-00-000 | I25: 부가세대급금 | J25: 14797717 | K25: 0 | L25: KRW | M25: 1 | N25: 14797717 | P25: 5028400374 | R25: ECSK BO 에퀴스센트럴서비스코리아피티이엘티디 (영업소) | W25: VAT_FY2024 Q4 MSA Chargeback_ECSK BO 에퀴스센트럴서비스코리아피티이엘티디 (영업소) | Z25: OFF | AG25: PTI | AH25: 매입세금계산서
A26: =MID(D26,1,6) -> 202501 | B26: 250100004UP | C26: 승인 | D26: 20250131 | E26: (HTX)_FY2024 Q4 MSA Chargeback | H26: 2203-00-000 | I26: 관계사미지급금 | J26: 0 | K26: 162774893 | L26: KRW | M26: 1 | O26: 162774893 | P26: 5028400374 | R26: ECSK BO 에퀴스센트럴서비스코리아피티이엘티디 (영업소) | W26: FY2024 Q4 MSA Chargeback_ECSK BO 에퀴스센트럴서비스코리아피티이엘티디 (영업소) | Z26: OFF | AG26: PTI | AH26: 매입세금계산서
A27: =MID(D27,1,6) -> 202501 | B27: 250100005UP | C27: 승인 | D27: 20250131 | E27: VAT Return for 2024.4Q | H27: 2407-00-000 | I27: 부가세대급금 | J27: 0 | K27: 445000 | L27: KRW | M27: 1 | O27: 445000 | P27: 1028134334 | R27: KPMG 삼정회계법인 | W27: VAT Return for 2024.4Q | Z27: OFF | AG27: ETC | AH27: 수기입력
A28: =MID(D28,1,6) -> 202501 | B28: 250100005UP | C28: 승인 | D28: 20250131 | E28: VAT Return for 2024.4Q | H28: 2407-00-000 | I28: 부가세대급금 | J28: 0 | K28: 350000 | L28: KRW | M28: 1 | O28: 350000 | P28: 1048617068 | R28: JIPYONG LLC.법무법인(유한) 지평 | W28: VAT Return for 2024.4Q | Z28: OFF | AG28: ETC | AH28: 수기입력
A29: =MID(D29,1,6) -> 202501 | B29: 250100005UP | C29: 승인 | D29: 20250131 | E29: VAT Return for 2024.4Q | H29: 2407-00-000 | I29: 부가세대급금 | J29: 0 | K29: 1200000 | L29: KRW | M29: 1 | O29: 1200000 | P29: 1608101862 | R29: 유한회사 삼형 | W29: VAT Return for 2024.4Q | Z29: OFF | AG29: ETC | AH29: 수기입력
A30: =MID(D30,1,6) -> 202501 | B30: 250100005UP | C30: 승인 | D30: 20250131 | E30: VAT Return for 2024.4Q | H30: 2407-00-000 | I30: 부가세대급금 | J30: 0 | K30: 115000 | L30: KRW | M30: 1 | O30: 115000 | P30: 2018112563 | R30: Lee&Ko 법무법인(유한) 광장 | W30: VAT Return for 2024.4Q | Z30: OFF | AG30: ETC | AH30: 수기입력
A31: =MID(D31,1,6) -> 202501 | B31: 250100005UP | C31: 승인 | D31: 20250131 | E31: VAT Return for 2024.4Q | H31: 2407-00-000 | I31: 부가세대급금 | J31: 0 | K31: 800 | L31: KRW | M31: 1 | O31: 800 | P31: 2028114695 | R31: HANA BANK (주)하나은행 | W31: VAT Return for 2024.4Q | Z31: OFF | AG31: ETC | AH31: 수기입력
A32: =MID(D32,1,6) -> 202501 | B32: 250100005UP | C32: 승인 | D32: 20250131 | E32: VAT Return for 2024.4Q | H32: 2407-00-000 | I32: 부가세대급금 | J32: 0 | K32: 19627885 | L32: KRW | M32: 1 | O32: 19627885 | P32: 5028400374 | R32: ECSK BO 에퀴스센트럴서비스코리아피티이엘티디 (영업소) | W32: VAT Return for 2024.4Q | Z32: OFF | AG32: ETC | AH32: 수기입력
A33: =MID(D33,1,6) -> 202501 | B33: 250100005UP | C33: 승인 | D33: 20250131 | E33: VAT Return for 2024.4Q | H33: 2407-00-000 | I33: 부가세대급금 | J33: 0 | K33: 200000 | L33: KRW | M33: 1 | O33: 200000 | P33: 6768103123 | R33: 유한회사 대연애드 | W33: VAT Return for 2024.4Q | Z33: OFF | AG33: ETC | AH33: 수기입력
A34: =MID(D34,1,6) -> 202501 | B34: 250100005UP | C34: 승인 | D34: 20250131 | E34: VAT Return for 2024.4Q | H34: 2407-00-000 | I34: 부가세대급금 | J34: 0 | K34: 108000 | L34: KRW | M34: 1 | O34: 108000 | P34: 7121001566 | R34: 이솝부동산중개사무소 | W34: VAT Return for 2024.4Q | Z34: OFF | AG34: ETC | AH34: 수기입력
A35: =MID(D35,1,6) -> 202501 | B35: 250100005UP | C35: 승인 | D35: 20250131 | E35: VAT Return for 2024.4Q | H35: 1214-00-000 | I35: 기타미수금 | J35: 22046685 | K35: 0 | L35: KRW | M35: 1 | N35: 22046685 | P35: TAX412 | R35: Naju Tax Office 나주세무서 | W35: VAT Return for 2024.4Q | Z35: OFF | AG35: ETC | AH35: 수기입력
A36: =MID(D36,1,6) -> 202501 | B36: 250100011UP | C36: 승인 | D36: 20250131 | E36: 이자지급 (20억, 23.03.31-26.03.31, 변동금리) | H36: 1112-KR-005 | I36: 현금 - 원 (신협) | J36: 0 | K36: 8662250 | L36: KRW | M36: 1 | O36: 8662250 | P36: 131-022-007238 | R36: 신협 (007238) | W36: 이자지급 (20억, 23.03.31-26.03.31, 변동금리) | Z36: OFF | AG36: BANK | AH36: 통장
A37: =MID(D37,1,6) -> 202501 | B37: 250100011UP | C37: 승인 | D37: 20250131 | E37: 이자지급 (20억, 23.03.31-26.03.31, 변동금리) | H37: 2204-00-002 | I37: 미지급이자비용 - 일반 대출 - 단기 | J37: 8662250 | K37: 0 | L37: KRW | M37: 1 | N37: 8662250 | P37: 4118202510 | R37: 목포신용협동조합 | W37: 이자지급 (20억, 23.03.31-26.03.31, 변동금리) | Z37: OFF | AG37: BANK | AH37: 통장
A38: =MID(D38,1,6) -> 202501 | B38: 250100012UP | C38: 승인 | D38: 20250131 | E38: Loan Interest_목포신협 to 금명 (KRW 2,000,000,000_5.1% 변동금리) | H38: 2204-00-002 | I38: 미지급이자비용 - 일반 대출 - 단기 | J38: 0 | K38: 8662250 | L38: KRW | M38: 1 | O38: 8662250 | P38: 4118202510 | R38: 목포신용협동조합 | W38: Loan Interest_목포신협 to 금명 (KRW 2,000,000,000_5.1% 변동금리) | Z38: OFF | AG38: ETC | AH38: 수기입력
A39: =MID(D39,1,6) -> 202501 | B39: 250100012UP | C39: 승인 | D39: 20250131 | E39: Loan Interest_목포신협 to 금명 (KRW 2,000,000,000_5.1% 변동금리) | H39: 5719-00-000 | I39: 이자비용 - 일반 | J39: 8662250 | K39: 0 | L39: KRW | M39: 1 | N39: 8662250 | P39: 4118202510 | R39: 목포신용협동조합 | W39: Loan Interest_목포신협 to 금명 (KRW 2,000,000,000_5.1% 변동금리) | Z39: OFF | AG39: ETC | AH39: 수기입력
A40: =MID(D40,1,6) -> 202501 | B40: 250100013UP | C40: 승인 | D40: 20250131 | E40: Office rent | H40: 5281-00-000 | I40: 지급임차료 | J40: 1000000 | K40: 0 | L40: KRW | M40: 1 | N40: 1000000 | P40: 1608101862 | R40: 유한회사 삼형 | W40: Office rent | Z40: OFF | AG40: ETC | AH40: 수기입력
A41: =MID(D41,1,6) -> 202501 | B41: 250100013UP | C41: 승인 | D41: 20250131 | E41: Office rent | H41: 1232-00-000 | I41: 선급비용 | J41: 0 | K41: 1000000 | L41: KRW | M41: 1 | O41: 1000000 | P41: 1608101862 | R41: 유한회사 삼형 | W41: Office rent | Z41: OFF | AG41: ETC | AH41: 수기입력
A42: =MID(D42,1,6) -> 202501 | B42: 250100014UP | C42: 승인 | D42: 20250131 | E42: Loan Interest_EEK2 to 금명 (KRW 1,321,408,000_14%) | H42: 5717-00-000 | I42: 이자비용 - 회사 간 대출 | J42: 15712084 | K42: 0 | L42: KRW | M42: 1 | N42: 15712084 | P42: 8258101824 | R42: EEK 2 에퀴스에너지코리아2 유한회사 | W42: Loan Interest_EEK2 to 금명 (KRW 1,321,408,000_14%) | Z42: OFF | AG42: ETC | AH42: 수기입력
A43: =MID(D43,1,6) -> 202501 | B43: 250100014UP | C43: 승인 | D43: 20250131 | E43: Loan Interest_EEK2 to 금명 (KRW 1,321,408,000_14%) | H43: 2204-00-001 | I43: 미지급이자비용 - 관계사 대출 - 장기 | J43: 0 | K43: 15712084 | L43: KRW | M43: 1 | O43: 15712084 | P43: 8258101824 | R43: EEK 2 에퀴스에너지코리아2 유한회사 | W43: Loan Interest_EEK2 to 금명 (KRW 1,321,408,000_14%) | Z43: OFF | AG43: ETC | AH43: 수기입력
A44: =MID(D44,1,6) -> 202502 | B44: 250200027UP | C44: 승인 | D44: 20250203 | E44: EQUIS InterCo Billings_ECSSPL | H44: 5106-00-000 | I44: 공유 서비스 비용 | J44: 2590672 | K44: 0 | L44: KRW | M44: 1 | N44: 2590672 | P44: 201726513C | R44: ECSS PL Equis Central Service Singapore Pte. Ltd. | W44: Mgmt & Shared Service Fee Q4 2024-Keummyeong Co. Ltd | Z44: OFF | AG44: Interco Invoices | AH44: 관계사 인보이스
A45: =MID(D45,1,6) -> 202502 | B45: 250200027UP | C45: 승인 | D45: 20250203 | E45: EQUIS InterCo Billings_ECSSPL | H45: 2203-00-000 | I45: 관계사미지급금 | J45: 0 | K45: 2590672 | L45: SGD | M45: 1073.6 | O45: 2413.07 | P45: 201726513C | R45: ECSS PL Equis Central Service Singapore Pte. Ltd. | W45: IECSG001-INV25-0041(SGD 2413.07*@ 1,073.60) | Z45: OFF | AG45: Interco Invoices | AH45: 관계사 인보이스
A46: =MID(D46,1,6) -> 202502 | B46: 250200006UP | C46: 승인 | D46: 20250206 | E46: (HTX)_공인인증서(은행/보험용) | H46: 5301-00-000 | I46: 은행 수수료 | J46: 4000 | K46: 0 | L46: KRW | M46: 1 | N46: 4000 | P46: 2028114695 | R46: HANA BANK (주)하나은행 | W46: 공인인증서(은행/보험용)_HANA BANK (주)하나은행 | Z46: OFF | AG46: PTI | AH46: 매입세금계산서
A47: =MID(D47,1,6) -> 202502 | B47: 250200006UP | C47: 승인 | D47: 20250206 | E47: (HTX)_공인인증서(은행/보험용) | H47: 2407-00-000 | I47: 부가세대급금 | J47: 400 | K47: 0 | L47: KRW | M47: 1 | N47: 400 | P47: 2028114695 | R47: HANA BANK (주)하나은행 | W47: VAT_공인인증서(은행/보험용)_HANA BANK (주)하나은행 | Z47: OFF | AG47: PTI | AH47: 매입세금계산서
A48: =MID(D48,1,6) -> 202502 | B48: 250200006UP | C48: 승인 | D48: 20250206 | E48: (HTX)_공인인증서(은행/보험용) | H48: 2202-00-001 | I48: 기타미지급금 | J48: 0 | K48: 4400 | L48: KRW | M48: 1 | O48: 4400 | P48: 2028114695 | R48: HANA BANK (주)하나은행 | W48: 공인인증서(은행/보험용)_HANA BANK (주)하나은행 | Z48: OFF | AG48: PTI | AH48: 매입세금계산서
A49: =MID(D49,1,6) -> 202502 | B49: 250200008UP | C49: 승인 | D49: 20250206 | E49: Issuance Fee payment | H49: 1112-KR-001 | I49: 현금 - 원 (HANA) | J49: 0 | K49: 4400 | L49: KRW | M49: 1 | O49: 4400 | P49: 201-910031-85704 | R49: HANA_Bank 하나은행(85704) | W49: Issuance Fee payment | Z49: OFF | AG49: BANK | AH49: 통장
A50: =MID(D50,1,6) -> 202502 | B50: 250200008UP | C50: 승인 | D50: 20250206 | E50: Issuance Fee payment | H50: 2202-00-001 | I50: 기타미지급금 | J50: 4400 | K50: 0 | L50: KRW | M50: 1 | N50: 4400 | P50: 2028114695 | R50: HANA BANK (주)하나은행 | W50: Issuance Fee payment | Z50: OFF | AG50: BANK | AH50: 통장
A51: =MID(D51,1,6) -> 202502 | B51: 250200005UP | C51: 승인 | D51: 20250210 | E51: (HTX)_관리비 | H51: 5101-00-000 | I51: 관리 수수료 비용 | J51: 332530 | K51: 0 | L51: KRW | M51: 1 | N51: 332530 | P51: 1168268413 | R51: 세정아울렛 관리단 | W51: 관리비_세정아울렛 관리단 | Z51: OFF | AG51: PTI | AH51: 매입세금계산서
A52: =MID(D52,1,6) -> 202502 | B52: 250200005UP | C52: 승인 | D52: 20250210 | E52: (HTX)_관리비 | H52: 2407-00-000 | I52: 부가세대급금 | J52: 33250 | K52: 0 | L52: KRW | M52: 1 | N52: 33250 | P52: 1168268413 | R52: 세정아울렛 관리단 | W52: VAT_관리비_세정아울렛 관리단 | Z52: OFF | AG52: PTI | AH52: 매입세금계산서
A53: =MID(D53,1,6) -> 202502 | B53: 250200005UP | C53: 승인 | D53: 20250210 | E53: (HTX)_관리비 | H53: 2202-00-001 | I53: 기타미지급금 | J53: 0 | K53: 365780 | L53: KRW | M53: 1 | O53: 365780 | P53: 1168268413 | R53: 세정아울렛 관리단 | W53: 관리비_세정아울렛 관리단 | Z53: OFF | AG53: PTI | AH53: 매입세금계산서
A54: =MID(D54,1,6) -> 202502 | B54: 250200009UP | C54: 승인 | D54: 20250212 | E54: MSA2405 | H54: 1112-KR-001 | I54: 현금 - 원 (HANA) | J54: 0 | K54: 60000000 | L54: KRW | M54: 1 | O54: 60000000 | P54: 201-910031-85704 | R54: HANA_Bank 하나은행(85704) | W54: MSA2405 | Z54: OFF | AG54: BANK | AH54: 통장
A55: =MID(D55,1,6) -> 202502 | B55: 250200009UP | C55: 승인 | D55: 20250212 | E55: MSA2405 | H55: 2203-00-000 | I55: 관계사미지급금 | J55: 60000000 | K55: 0 | L55: KRW | M55: 1 | N55: 60000000 | P55: 5028400374 | R55: ECSK BO 에퀴스센트럴서비스코리아피티이엘티디 (영업소) | W55: MSA2405 | Z55: OFF | AG55: BANK | AH55: 통장
A56: =MID(D56,1,6) -> 202502 | B56: 250200004UP | C56: 승인 | D56: 20250214 | E56: (HTX)_공인인증서(은행/보험용) | H56: 5301-00-000 | I56: 은행 수수료 | J56: 4000 | K56: 0 | L56: KRW | M56: 1 | N56: 4000 | P56: 2028114695 | R56: HANA BANK (주)하나은행 | W56: 공인인증서(은행/보험용)_HANA BANK (주)하나은행 | Z56: OFF | AG56: PTI | AH56: 매입세금계산서
A57: =MID(D57,1,6) -> 202502 | B57: 250200004UP | C57: 승인 | D57: 20250214 | E57: (HTX)_공인인증서(은행/보험용) | H57: 2407-00-000 | I57: 부가세대급금 | J57: 400 | K57: 0 | L57: KRW | M57: 1 | N57: 400 | P57: 2028114695 | R57: HANA BANK (주)하나은행 | W57: VAT_공인인증서(은행/보험용)_HANA BANK (주)하나은행 | Z57: OFF | AG57: PTI | AH57: 매입세금계산서
A58: =MID(D58,1,6) -> 202502 | B58: 250200004UP | C58: 승인 | D58: 20250214 | E58: (HTX)_공인인증서(은행/보험용) | H58: 2202-00-001 | I58: 기타미지급금 | J58: 0 | K58: 4400 | L58: KRW | M58: 1 | O58: 4400 | P58: 2028114695 | R58: HANA BANK (주)하나은행 | W58: 공인인증서(은행/보험용)_HANA BANK (주)하나은행 | Z58: OFF | AG58: PTI | AH58: 매입세금계산서
A59: =MID(D59,1,6) -> 202502 | B59: 250200010UP | C59: 승인 | D59: 20250214 | E59: Issuance Fee payment | H59: 1112-KR-001 | I59: 현금 - 원 (HANA) | J59: 0 | K59: 4400 | L59: KRW | M59: 1 | O59: 4400 | P59: 201-910031-85704 | R59: HANA_Bank 하나은행(85704) | W59: Issuance Fee payment | Z59: OFF | AG59: BANK | AH59: 통장
A60: =MID(D60,1,6) -> 202502 | B60: 250200010UP | C60: 승인 | D60: 20250214 | E60: Issuance Fee payment | H60: 2202-00-001 | I60: 기타미지급금 | J60: 4400 | K60: 0 | L60: KRW | M60: 1 | N60: 4400 | P60: 2028114695 | R60: HANA BANK (주)하나은행 | W60: Issuance Fee payment | Z60: OFF | AG60: BANK | AH60: 통장
A61: =MID(D61,1,6) -> 202502 | B61: 250200021UP | C61: 승인 | D61: 20250218 | E61: 230 EEKHPL_Unsecured Loan Agreement(USD 1,500,000) | H61: 2102-00-000 | I61: 관계사 대출 - 장기 | J61: 0 | K61: 2168985000 | L61: KRW | M61: 1 | O61: 2168985000 | P61: 201907742E | R61: EEKH PL Equis Energy (Korea) Holdings Pte. Ltd. | W61: 230 EEKHPL_Unsecured Loan Agreement(USD 1,500,000) | Z61: OFF | AG61: BANK | AH61: 통장
A62: =MID(D62,1,6) -> 202502 | B62: 250200021UP | C62: 승인 | D62: 20250218 | E62: 230 EEKHPL_Unsecured Loan Agreement(USD 1,500,000) | H62: 1108-KR-001 | I62: 현금 - USD (HANA) | J62: 2168985000 | K62: 0 | L62: KRW | M62: 1 | N62: 2168985000 | P62: 201-910016-70638 | R62: HANA_Bank 하나은행(70638) | W62: 230 EEKHPL_Unsecured Loan Agreement(USD 1,500,000) | Z62: OFF | AG62: BANK | AH62: 통장
A63: =MID(D63,1,6) -> 202502 | B63: 250200022UP | C63: 승인 | D63: 20250218 | E63: 231 EEKHPL_Unsecured Loan Agreement(USD 260,000) | H63: 2102-00-000 | I63: 관계사 대출 - 장기 | J63: 0 | K63: 375957400 | L63: KRW | M63: 1 | O63: 375957400 | P63: 201907742E | R63: EEKH PL Equis Energy (Korea) Holdings Pte. Ltd. | W63: 231 EEKHPL_Unsecured Loan Agreement(USD 260,000) | Z63: OFF | AG63: BANK | AH63: 통장
A64: =MID(D64,1,6) -> 202502 | B64: 250200022UP | C64: 승인 | D64: 20250218 | E64: 231 EEKHPL_Unsecured Loan Agreement(USD 260,000) | H64: 1108-KR-001 | I64: 현금 - USD (HANA) | J64: 375957400 | K64: 0 | L64: KRW | M64: 1 | N64: 375957400 | P64: 201-910016-70638 | R64: HANA_Bank 하나은행(70638) | W64: 231 EEKHPL_Unsecured Loan Agreement(USD 260,000) | Z64: OFF | AG64: BANK | AH64: 통장
A65: =MID(D65,1,6) -> 202502 | B65: 250200002UP | C65: 승인 | D65: 20250219 | E65: (HTX)_공인인증서(은행/보험용) | H65: 5301-00-000 | I65: 은행 수수료 | J65: 4000 | K65: 0 | L65: KRW | M65: 1 | N65: 4000 | P65: 2028114695 | R65: HANA BANK (주)하나은행 | W65: 공인인증서(은행/보험용)_HANA BANK (주)하나은행 | Z65: OFF | AG65: PTI | AH65: 매입세금계산서
A66: =MID(D66,1,6) -> 202502 | B66: 250200002UP | C66: 승인 | D66: 20250219 | E66: (HTX)_공인인증서(은행/보험용) | H66: 2407-00-000 | I66: 부가세대급금 | J66: 400 | K66: 0 | L66: KRW | M66: 1 | N66: 400 | P66: 2028114695 | R66: HANA BANK (주)하나은행 | W66: VAT_공인인증서(은행/보험용)_HANA BANK (주)하나은행 | Z66: OFF | AG66: PTI | AH66: 매입세금계산서
A67: =MID(D67,1,6) -> 202502 | B67: 250200002UP | C67: 승인 | D67: 20250219 | E67: (HTX)_공인인증서(은행/보험용) | H67: 2202-00-001 | I67: 기타미지급금 | J67: 0 | K67: 4400 | L67: KRW | M67: 1 | O67: 4400 | P67: 2028114695 | R67: HANA BANK (주)하나은행 | W67: 공인인증서(은행/보험용)_HANA BANK (주)하나은행 | Z67: OFF | AG67: PTI | AH67: 매입세금계산서
A68: =MID(D68,1,6) -> 202502 | B68: 250200003UP | C68: 승인 | D68: 20250219 | E68: (HTX)_공인인증서(은행/보험용) | H68: 5301-00-000 | I68: 은행 수수료 | J68: 4000 | K68: 0 | L68: KRW | M68: 1 | N68: 4000 | P68: 2028114695 | R68: HANA BANK (주)하나은행 | W68: 공인인증서(은행/보험용)_HANA BANK (주)하나은행 | Z68: OFF | AG68: PTI | AH68: 매입세금계산서
A69: =MID(D69,1,6) -> 202502 | B69: 250200003UP | C69: 승인 | D69: 20250219 | E69: (HTX)_공인인증서(은행/보험용) | H69: 2407-00-000 | I69: 부가세대급금 | J69: 400 | K69: 0 | L69: KRW | M69: 1 | N69: 400 | P69: 2028114695 | R69: HANA BANK (주)하나은행 | W69: VAT_공인인증서(은행/보험용)_HANA BANK (주)하나은행 | Z69: OFF | AG69: PTI | AH69: 매입세금계산서
A70: =MID(D70,1,6) -> 202502 | B70: 250200003UP | C70: 승인 | D70: 20250219 | E70: (HTX)_공인인증서(은행/보험용) | H70: 2202-00-001 | I70: 기타미지급금 | J70: 0 | K70: 4400 | L70: KRW | M70: 1 | O70: 4400 | P70: 2028114695 | R70: HANA BANK (주)하나은행 | W70: 공인인증서(은행/보험용)_HANA BANK (주)하나은행 | Z70: OFF | AG70: PTI | AH70: 매입세금계산서
A71: =MID(D71,1,6) -> 202502 | B71: 250200011UP | C71: 승인 | D71: 20250219 | E71: Issuance Fee payment | H71: 1112-KR-001 | I71: 현금 - 원 (HANA) | J71: 0 | K71: 4400 | L71: KRW | M71: 1 | O71: 4400 | P71: 201-910031-85704 | R71: HANA_Bank 하나은행(85704) | W71: Issuance Fee payment | Z71: OFF | AG71: BANK | AH71: 통장
A72: =MID(D72,1,6) -> 202502 | B72: 250200011UP | C72: 승인 | D72: 20250219 | E72: Issuance Fee payment | H72: 2202-00-001 | I72: 기타미지급금 | J72: 4400 | K72: 0 | L72: KRW | M72: 1 | N72: 4400 | P72: 2028114695 | R72: HANA BANK (주)하나은행 | W72: Issuance Fee payment | Z72: OFF | AG72: BANK | AH72: 통장
A73: =MID(D73,1,6) -> 202502 | B73: 250200012UP | C73: 승인 | D73: 20250219 | E73: Issuance Fee payment | H73: 1112-KR-001 | I73: 현금 - 원 (HANA) | J73: 0 | K73: 4400 | L73: KRW | M73: 1 | O73: 4400 | P73: 201-910031-85704 | R73: HANA_Bank 하나은행(85704) | W73: Issuance Fee payment | Z73: OFF | AG73: BANK | AH73: 통장
A74: =MID(D74,1,6) -> 202502 | B74: 250200012UP | C74: 승인 | D74: 20250219 | E74: Issuance Fee payment | H74: 2202-00-001 | I74: 기타미지급금 | J74: 4400 | K74: 0 | L74: KRW | M74: 1 | N74: 4400 | P74: 2028114695 | R74: HANA BANK (주)하나은행 | W74: Issuance Fee payment | Z74: OFF | AG74: BANK | AH74: 통장
A75: =MID(D75,1,6) -> 202502 | B75: 250200013UP | C75: 승인 | D75: 20250219 | E75: no supporting documents | H75: 1112-KR-001 | I75: 현금 - 원 (HANA) | J75: 2158500000 | K75: 0 | L75: KRW | M75: 1 | N75: 2158500000 | P75: 201-910031-85704 | R75: HANA_Bank 하나은행(85704) | W75: 230 EEKHPL_Unsecured Loan Agreement(USD 1,500,000)_bank transfer | Z75: OFF | AG75: BANK | AH75: 통장
A76: =MID(D76,1,6) -> 202502 | B76: 250200013UP | C76: 승인 | D76: 20250219 | E76: no supporting documents | H76: 1108-KR-001 | I76: 현금 - USD (HANA) | J76: 0 | K76: 2168985000 | L76: KRW | M76: 1 | O76: 2168985000 | P76: 201-910016-70638 | R76: HANA_Bank 하나은행(70638) | W76: 230 EEKHPL_Unsecured Loan Agreement(USD 1,500,000)_bank transfer | Z76: OFF | AG76: BANK | AH76: 통장
A77: =MID(D77,1,6) -> 202502 | B77: 250200013UP | C77: 승인 | D77: 20250219 | E77: no supporting documents | H77: 5342-00-000 | I77: 외환차손 | J77: 10485000 | K77: 0 | L77: KRW | M77: 1 | N77: 10485000 | P77: 201-910016-70638 | R77: HANA_Bank 하나은행(70638) | W77: 230 EEKHPL_Unsecured Loan Agreement(USD 1,500,000)_bank transfer | Z77: OFF | AG77: BANK | AH77: 통장
A78: =MID(D78,1,6) -> 202502 | B78: 250200014UP | C78: 승인 | D78: 20250219 | E78: no supporting documents | H78: 1112-KR-001 | I78: 현금 - 원 (HANA) | J78: 374140000 | K78: 0 | L78: KRW | M78: 1 | N78: 374140000 | P78: 201-910031-85704 | R78: HANA_Bank 하나은행(85704) | W78: 231 EEKHPL_Unsecured Loan Agreement(USD 260,000)_bank transfer | Z78: OFF | AG78: BANK | AH78: 통장
A79: =MID(D79,1,6) -> 202502 | B79: 250200014UP | C79: 승인 | D79: 20250219 | E79: no supporting documents | H79: 1108-KR-001 | I79: 현금 - USD (HANA) | J79: 0 | K79: 375957400 | L79: KRW | M79: 1 | O79: 375957400 | P79: 201-910016-70638 | R79: HANA_Bank 하나은행(70638) | W79: 231 EEKHPL_Unsecured Loan Agreement(USD 260,000)_bank transfer | Z79: OFF | AG79: BANK | AH79: 통장
A80: =MID(D80,1,6) -> 202502 | B80: 250200014UP | C80: 승인 | D80: 20250219 | E80: no supporting documents | H80: 5342-00-000 | I80: 외환차손 | J80: 1817400 | K80: 0 | L80: KRW | M80: 1 | N80: 1817400 | P80: 201-910016-70638 | R80: HANA_Bank 하나은행(70638) | W80: 231 EEKHPL_Unsecured Loan Agreement(USD 260,000)_bank transfer | Z80: OFF | AG80: BANK | AH80: 통장
A81: =MID(D81,1,6) -> 202502 | B81: 250200015UP | C81: 승인 | D81: 20250219 | E81: MSA24Q1,Q2,Q3 | H81: 1112-KR-001 | I81: 현금 - 원 (HANA) | J81: 0 | K81: 297152365 | L81: KRW | M81: 1 | O81: 297152365 | P81: 201-910031-85704 | R81: HANA_Bank 하나은행(85704) | W81: MSA24Q1,Q2,Q3 | Z81: OFF | AG81: BANK | AH81: 통장
A82: =MID(D82,1,6) -> 202502 | B82: 250200015UP | C82: 승인 | D82: 20250219 | E82: MSA24Q1,Q2,Q3 | H82: 2203-00-000 | I82: 관계사미지급금 | J82: 297152364 | K82: 0 | L82: KRW | M82: 1 | N82: 297152364 | P82: 5028400374 | R82: ECSK BO 에퀴스센트럴서비스코리아피티이엘티디 (영업소) | W82: MSA24Q1,Q2,Q3 | Z82: OFF | AG82: BANK | AH82: 통장
A83: =MID(D83,1,6) -> 202502 | B83: 250200015UP | C83: 승인 | D83: 20250219 | E83: MSA24Q1,Q2,Q3 | H83: 5601-00-000 | I83: 잡손실 | J83: 1 | K83: 0 | L83: KRW | M83: 1 | N83: 1 | P83: 5028400374 | R83: ECSK BO 에퀴스센트럴서비스코리아피티이엘티디 (영업소) | W83: MSA24Q1,Q2,Q3 | Z83: OFF | AG83: BANK | AH83: 통장
A84: =MID(D84,1,6) -> 202502 | B84: 250200016UP | C84: 승인 | D84: 20250220 | E84: [KR Inv_202502] VSEJUNG01_Kummyung office maintenance fee_KRW 365,780 | H84: 1112-KR-001 | I84: 현금 - 원 (HANA) | J84: 0 | K84: 365780 | L84: KRW | M84: 1 | O84: 365780 | P84: 201-910031-85704 | R84: HANA_Bank 하나은행(85704) | W84: [KR Inv_202502] VSEJUNG01_Kummyung office maintenance fee_KRW 365,780 | Z84: OFF | AG84: BANK | AH84: 통장
A85: =MID(D85,1,6) -> 202502 | B85: 250200016UP | C85: 승인 | D85: 20250220 | E85: [KR Inv_202502] VSEJUNG01_Kummyung office maintenance fee_KRW 365,780 | H85: 2202-00-001 | I85: 기타미지급금 | J85: 365780 | K85: 0 | L85: KRW | M85: 1 | N85: 365780 | P85: 1168268413 | R85: 세정아울렛 관리단 | W85: [KR Inv_202502] VSEJUNG01_Kummyung office maintenance fee_KRW 365,780 | Z85: OFF | AG85: BANK | AH85: 통장
A86: =MID(D86,1,6) -> 202502 | B86: 250200017UP | C86: 승인 | D86: 20250220 | E86: [KR Inv_202410] VKPMCOR01_KPMG Acct Service for Sep'24_KRW 48669500 | H86: 1112-KR-001 | I86: 현금 - 원 (HANA) | J86: 0 | K86: 715000 | L86: KRW | M86: 1 | O86: 715000 | P86: 201-910031-85704 | R86: HANA_Bank 하나은행(85704) | W86: [KR Inv_202410] VKPMCOR01_KPMG Acct Service for Sep'24_KRW 48669500 | Z86: OFF | AG86: BANK | AH86: 통장
A87: =MID(D87,1,6) -> 202502 | B87: 250200017UP | C87: 승인 | D87: 20250220 | E87: [KR Inv_202410] VKPMCOR01_KPMG Acct Service for Sep'24_KRW 48669500 | H87: 2202-00-001 | I87: 기타미지급금 | J87: 715000 | K87: 0 | L87: KRW | M87: 1 | N87: 715000 | P87: 1028134334 | R87: KPMG 삼정회계법인 | W87: [KR Inv_202410] VKPMCOR01_KPMG Acct Service for Sep'24_KRW 48669500 | Z87: OFF | AG87: BANK | AH87: 통장
A88: =MID(D88,1,6) -> 202502 | B88: 250200018UP | C88: 승인 | D88: 20250220 | E88: [KR Inv_202501] VKPMCOR01_KPMG Acct Service for Dec'24_KRW 31141000 | H88: 1112-KR-001 | I88: 현금 - 원 (HANA) | J88: 0 | K88: 715000 | L88: KRW | M88: 1 | O88: 715000 | P88: 201-910031-85704 | R88: HANA_Bank 하나은행(85704) | W88: [KR Inv_202501] VKPMCOR01_KPMG Acct Service for Dec'24_KRW 31141000 | Z88: OFF | AG88: BANK | AH88: 통장
A89: =MID(D89,1,6) -> 202502 | B89: 250200018UP | C89: 승인 | D89: 20250220 | E89: [KR Inv_202501] VKPMCOR01_KPMG Acct Service for Dec'24_KRW 31141000 | H89: 2202-00-001 | I89: 기타미지급금 | J89: 715000 | K89: 0 | L89: KRW | M89: 1 | N89: 715000 | P89: 1028134334 | R89: KPMG 삼정회계법인 | W89: [KR Inv_202501] VKPMCOR01_KPMG Acct Service for Dec'24_KRW 31141000 | Z89: OFF | AG89: BANK | AH89: 통장
A90: =MID(D90,1,6) -> 202502 | B90: 250200007UP | C90: 승인 | D90: 20250226 | E90: VAT Return for 2024.4Q | H90: 1214-00-000 | I90: 기타미수금 | J90: 0 | K90: 22046685 | L90: KRW | M90: 1 | O90: 22046685 | P90: TAX412 | R90: Naju Tax Office 나주세무서 | W90: VAT Return for 2024.4Q | Z90: OFF | AG90: BANK | AH90: 통장
A91: =MID(D91,1,6) -> 202502 | B91: 250200007UP | C91: 승인 | D91: 20250226 | E91: VAT Return for 2024.4Q | H91: 1112-KR-001 | I91: 현금 - 원 (HANA) | J91: 22046680 | K91: 0 | L91: KRW | M91: 1 | N91: 22046680 | P91: 201-910031-85704 | R91: HANA_Bank 하나은행(85704) | W91: VAT Return for 2024.4Q | Z91: OFF | AG91: BANK | AH91: 통장
A92: =MID(D92,1,6) -> 202502 | B92: 250200007UP | C92: 승인 | D92: 20250226 | E92: VAT Return for 2024.4Q | H92: 5601-00-000 | I92: 잡손실 | J92: 5 | K92: 0 | L92: KRW | M92: 1 | N92: 5 | P92: TAX412 | R92: Naju Tax Office 나주세무서 | W92: VAT Return for 2024.4Q | Z92: OFF | AG92: BANK | AH92: 통장
A93: =MID(D93,1,6) -> 202502 | B93: 250200019UP | C93: 승인 | D93: 20250227 | E93: [KR Inv_202502] VNEULSA01_PJ Phantom Real Estate Sales Contract Payment_KRW 252000000 | H93: 1112-KR-001 | I93: 현금 - 원 (HANA) | J93: 0 | K93: 252000000 | L93: KRW | M93: 1 | O93: 252000000 | P93: 201-910031-85704 | R93: HANA_Bank 하나은행(85704) | W93: [KR Inv_202502] VNEULSA01_PJ Phantom Real Estate Sales Contract Payment_KRW 252000000 | Z93: OFF | AG93: BANK | AH93: 통장
A94: =MID(D94,1,6) -> 202502 | B94: 250200019UP | C94: 승인 | D94: 20250227 | E94: [KR Inv_202502] VNEULSA01_PJ Phantom Real Estate Sales Contract Payment_KRW 252000000 | H94: 1712-00-000 | I94: 토지 | J94: 252000000 | K94: 0 | L94: KRW | M94: 1 | N94: 252000000 | P94: 4118183990 | R94: (유)늘샘쏠라에너지 | W94: [KR Inv_202502] VNEULSA01_PJ Phantom Real Estate Sales Contract Payment_KRW 252000000 | Z94: OFF | AG94: BANK | AH94: 통장
A95: =MID(D95,1,6) -> 202502 | B95: 250200020UP | C95: 승인 | D95: 20250227 | E95: FY24 Q4 MSA | H95: 1112-KR-001 | I95: 현금 - 원 (HANA) | J95: 0 | K95: 162774893 | L95: KRW | M95: 1 | O95: 162774893 | P95: 201-910031-85704 | R95: HANA_Bank 하나은행(85704) | W95: FY24 Q4 MSA | Z95: OFF | AG95: BANK | AH95: 통장
A96: =MID(D96,1,6) -> 202502 | B96: 250200020UP | C96: 승인 | D96: 20250227 | E96: FY24 Q4 MSA | H96: 2203-00-000 | I96: 관계사미지급금 | J96: 162774893 | K96: 0 | L96: KRW | M96: 1 | N96: 162774893 | P96: 5028400374 | R96: ECSK BO 에퀴스센트럴서비스코리아피티이엘티디 (영업소) | W96: FY24 Q4 MSA | Z96: OFF | AG96: BANK | AH96: 통장
A97: =MID(D97,1,6) -> 202502 | B97: 250200001UP | C97: 승인 | D97: 20250228 | E97: (HTX)_용역보수 | H97: 5249-00-000 | I97: 기타 법률 및 전문 수수료 | J97: 650000 | K97: 0 | L97: KRW | M97: 1 | N97: 650000 | P97: 1028134334 | R97: KPMG 삼정회계법인 | W97: 용역보수_KPMG 삼정회계법인 | Z97: OFF | AG97: PTI | AH97: 매입세금계산서
A98: =MID(D98,1,6) -> 202502 | B98: 250200001UP | C98: 승인 | D98: 20250228 | E98: (HTX)_용역보수 | H98: 2407-00-000 | I98: 부가세대급금 | J98: 65000 | K98: 0 | L98: KRW | M98: 1 | N98: 65000 | P98: 1028134334 | R98: KPMG 삼정회계법인 | W98: VAT_용역보수_KPMG 삼정회계법인 | Z98: OFF | AG98: PTI | AH98: 매입세금계산서
A99: =MID(D99,1,6) -> 202502 | B99: 250200001UP | C99: 승인 | D99: 20250228 | E99: (HTX)_용역보수 | H99: 2202-00-001 | I99: 기타미지급금 | J99: 0 | K99: 715000 | L99: KRW | M99: 1 | O99: 715000 | P99: 1028134334 | R99: KPMG 삼정회계법인 | W99: 용역보수_KPMG 삼정회계법인 | Z99: OFF | AG99: PTI | AH99: 매입세금계산서
A100: =MID(D100,1,6) -> 202502 | B100: 250200023UP | C100: 승인 | D100: 20250228 | E100: 과다송금액 반환 | H100: 1112-KR-005 | I100: 현금 - 원 (신협) | J100: 43834 | K100: 0 | L100: KRW | M100: 1 | N100: 43834 | P100: 131-022-007238 | R100: 신협 (007238) | W100: 과다송금액 반환 | Z100: OFF | AG100: BANK | AH100: 통장
...

Sheet journal 2025_EY
A1: Posting Date | B1: Document No. | C1: G/L Account No. | D1: G/L Account Name | E1: Vendor Code | F1: Description | G1: Comment | H1: Debit Amount (LCY) | I1: Credit Amount (LCY) | J1: Amount (LCY) | K1: Bal. Account Type | L1: Bal. Account No. | M1: Currency Code | N1: Gen. Posting Type | O1: Gen. Bus. Posting Group | P1: Gen. Prod. Posting Group | Q1: Created At
A2: 45747 | B2: GJ25-0072 | C2: 6402-00-002 | D2: FX - unrealized gains - others / 외화환산손실 | E2: IEEKR001 | F2: 231 EEKHPL_Unsecured Loan Agreement(USD 260,000) | H2: 3231800 | I2: 0 | J2: 3231800 | K2: G/L Account | L2: 2102-00-000 | N2: Purchase | P2: GENERAL | Q2: 45763.167
A3: 45747 | B3: GJ25-0071 | C3: 6402-00-002 | D3: FX - unrealized gains - others / 외화환산손실 | E3: IEEKR001 | F3: 230 EEKHPL_Unsecured Loan Agreement(USD 1,500,000) | H3: 18645000 | I3: 0 | J3: 18645000 | K3: G/L Account | L3: 2102-00-000 | N3: Purchase | P3: GENERAL | Q3: 45763.167
A4: 45747 | B4: GJ25-0073 | C4: 6402-00-002 | D4: FX - unrealized gains - others / 외화환산손실 | E4: IECSG001 | F4: EQUIS InterCo Billings_ECSSPL | H4: 41674 | I4: 0 | J4: 41674 | K4: Vendor | L4: IECSG001 | N4: Purchase | P4: GENERAL | Q4: 45763.167
A5: 45747 | B5: GJ25-0063 | C5: 5719-00-000 | D5: Interest expense - External / 이자비용 - 일반 | E5: VMOKPOC01 | F5: Loan Interest_목포신협 to 금명 (KRW 2,000,000,000_5.1% 변동금리) | H5: 8663013 | I5: 0 | J5: 8663013 | K5: G/L Account | L5: 2204-00-002 | N5: Purchase | P5: GENERAL | Q5: 45762.889
A6: 45747 | B6: GJ25-0068 | C6: 5717-00-000 | D6: Interest expense - InterCo / 이자비용 - 회사 간 대출 | E6: IEEKR005 | F6: Loan Interest_EEK2 to 금명 (KRW 1,321,408,000_14%) | H6: 15712084 | I6: 0 | J6: 15712084 | K6: G/L Account | L6: 2204-00-001 | N6: Purchase | P6: GENERAL | Q6: 45763.117
A7: 45747 | B7: GJ25-0067 | C7: 5717-00-000 | D7: Interest expense - InterCo / 이자비용 - 회사 간 대출 | E7: IEEKR005 | F7: 수정분개 Loan Interest_EEK2 to 금명 (KRW 1,321,408,000_14%) | H7: 0 | I7: 14191560 | J7: -14191560 | K7: G/L Account | L7: 2204-00-001 | N7: Purchase | P7: GENERAL | Q7: 45763.117
A8: 45747 | B8: GJ25-0065 | C8: 5717-00-000 | D8: Interest expense - InterCo / 이자비용 - 회사 간 대출 | E8: IEEKR005 | F8: Loan Interest_EEK2 to 금명 (KRW 1,321,408,000_14%) | H8: 14191560 | I8: 0 | J8: 14191560 | K8: G/L Account | L8: 2204-00-001 | N8: Purchase | P8: GENERAL | Q8: 45762.889
A9: 45747 | B9: GJ25-0066 | C9: 5281-00-000 | D9: Rent / 지급임차료 | E9: VSAMHYO01 | F9: Office rent | H9: 1000000 | I9: 0 | J9: 1000000 | K9: G/L Account | L9: 1232-00-000 | N9: Purchase | P9: GENERAL | Q9: 45762.889
A10: 45747 | B10: GJ25-0064 | C10: 2204-00-002 | D10: Accrued interest expense - General Loan - Short term / 미지급이자비용 - 일반 대출 - 단기 | E10: VMOKPOC01 | F10: 이자지급 (20억, 23.03.31-26.03.31, 변동금리) | H10: 8663013 | I10: 0 | J10: 8663013 | K10: Bank Account | L10: SHINHYUP-KRW | M10: KRW | N10: Purchase | P10: GENERAL | Q10: 45762.889
A11: 45747 | B11: GJ25-0063 | C11: 2204-00-002 | D11: Accrued interest expense - General Loan - Short term / 미지급이자비용 - 일반 대출 - 단기 | E11: VMOKPOC01 | F11: Loan Interest_목포신협 to 금명 (KRW 2,000,000,000_5.1% 변동금리) | H11: 0 | I11: 8663013 | J11: -8663013 | K11: G/L Account | L11: 5719-00-000 | N11: Purchase | P11: GENERAL | Q11: 45762.889
A12: 45747 | B12: GJ25-0068 | C12: 2204-00-001 | D12: Accrued interest expense - Loan - Long term / 미지급이자비용 - 관계사 대출 - 장기 | E12: IEEKR005 | F12: Loan Interest_EEK2 to 금명 (KRW 1,321,408,000_14%) | H12: 0 | I12: 15712084 | J12: -15712084 | K12: G/L Account | L12: 5717-00-000 | N12: Purchase | P12: GENERAL | Q12: 45763.117
A13: 45747 | B13: GJ25-0067 | C13: 2204-00-001 | D13: Accrued interest expense - Loan - Long term / 미지급이자비용 - 관계사 대출 - 장기 | E13: IEEKR005 | F13: 수정분개 Loan Interest_EEK2 to 금명 (KRW 1,321,408,000_14%) | H13: 14191560 | I13: 0 | J13: 14191560 | K13: G/L Account | L13: 5717-00-000 | N13: Purchase | P13: GENERAL | Q13: 45763.117
A14: 45747 | B14: GJ25-0065 | C14: 2204-00-001 | D14: Accrued interest expense - Loan - Long term / 미지급이자비용 - 관계사 대출 - 장기 | E14: IEEKR005 | F14: Loan Interest_EEK2 to 금명 (KRW 1,321,408,000_14%) | H14: 0 | I14: 14191560 | J14: -14191560 | K14: G/L Account | L14: 5717-00-000 | N14: Purchase | P14: GENERAL | Q14: 45762.889
A15: 45747 | B15: GJ25-0073 | C15: 2203-00-000 | D15: Intercompany Payable / 관계사미지급금 | E15: IECSG001 | F15: EQUIS InterCo Billings_ECSSPL | H15: 0 | I15: 41674 | J15: -41674 | K15: G/L Account | L15: 6402-00-002 | Q15: 45763.167
A16: 45747 | B16: GJ25-0072 | C16: 2102-00-000 | D16: Intercompany loans / 관계사 대출 - 장기 | E16: IEEKR001 | F16: 231 EEKHPL_Unsecured Loan Agreement(USD 260,000) | H16: 0 | I16: 3231800 | J16: -3231800 | K16: G/L Account | L16: 6402-00-002 | N16: Purchase | P16: GENERAL | Q16: 45763.167
A17: 45747 | B17: GJ25-0071 | C17: 2102-00-000 | D17: Intercompany loans / 관계사 대출 - 장기 | E17: IEEKR001 | F17: 230 EEKHPL_Unsecured Loan Agreement(USD 1,500,000) | H17: 0 | I17: 18645000 | J17: -18645000 | K17: G/L Account | L17: 6402-00-002 | N17: Purchase | P17: GENERAL | Q17: 45763.167
A18: 45747 | B18: GJ25-0066 | C18: 1232-00-000 | D18: Prepaid expenses / 선급비용 | E18: VSAMHYO01 | F18: Office rent | H18: 0 | I18: 1000000 | J18: -1000000 | K18: G/L Account | L18: 5281-00-000 | N18: Purchase | P18: GENERAL | Q18: 45762.889
A19: 45747 | B19: GJ25-0064 | C19: 1112-KR-005 | D19: Cash - KRW (SHINHYUP) / 현금 - 원 (신협) | E19: VMOKPOC01 | F19: 이자지급 (20억, 23.03.31-26.03.31, 변동금리) | H19: 0 | I19: 8663013 | J19: -8663013 | K19: G/L Account | L19: 2204-00-002 | M19: KRW | Q19: 45762.889
A20: 45743 | B20: GJ25-0062 | C20: 2202-00-001 | D20: Other payable / 기타미지급금 | E20: VHYCHNG01 | F20: [KR Inv_202504] VHYCHNG01_PJ PhantomKummyung CSR - 2025 Dialogue with Citizens Event Support (Sinan | H20: 905000 | I20: 0 | J20: 905000 | K20: Bank Account | L20: HANA-KRW | M20: KRW | Q20: 45762.889
A21: 45743 | B21: GJ25-0061 | C21: 2202-00-001 | D21: Other payable / 기타미지급금 | E21: VPRDLTD01 | F21: [KR Inv_202504] VHYCHNG01_PJ Phantom_Kummyung CSR - 2025 Dialogue with Citizens Event Support (Sinan | H21: 3000000 | I21: 0 | J21: 3000000 | K21: Bank Account | L21: HANA-KRW | M21: KRW | Q21: 45762.889
A22: 45743 | B22: GJ25-0062 | C22: 1112-KR-001 | D22: Cash - KRW (HANA) / 현금 - 원 (HANA) | E22: VHYCHNG01 | F22: [KR Inv_202504] VHYCHNG01_PJ PhantomKummyung CSR - 2025 Dialogue with Citizens Event Support (Sinan | H22: 0 | I22: 905000 | J22: -905000 | K22: G/L Account | L22: 2202-00-001 | M22: KRW | Q22: 45762.889
A23: 45743 | B23: GJ25-0061 | C23: 1112-KR-001 | D23: Cash - KRW (HANA) / 현금 - 원 (HANA) | E23: VPRDLTD01 | F23: [KR Inv_202504] VHYCHNG01_PJ Phantom_Kummyung CSR - 2025 Dialogue with Citizens Event Support (Sinan | H23: 0 | I23: 3000000 | J23: -3000000 | K23: G/L Account | L23: 2202-00-001 | M23: KRW | Q23: 45762.889
A24: 45737 | B24: GJ25-0054 | C24: 5249-00-000 | D24: Other legal and professional fees / 기타 법률 및 전문 수수료 | E24: VKPMCOR01 | F24: 용역보수_KPMG 삼정회계법인 | H24: 850000 | I24: 0 | J24: 850000 | K24: Vendor | L24: VKPMCOR01 | N24: Purchase | P24: GENERAL | Q24: 45762.889
A25: 45737 | B25: GJ25-0054 | C25: 2407-00-000 | D25: GST/VAT receivable / 부가세대급금 | E25: VKPMCOR01 | F25: 용역보수_KPMG 삼정회계법인 | H25: 85000 | I25: 0 | J25: 85000 | K25: G/L Account | Q25: 45762.889
A26: 45737 | B26: GJ25-0053 | C26: 2202-00-001 | D26: Other payable / 기타미지급금 | E26: VKIMYUN01 | F26: 소유권이전 (분매리134-249외 4필지, 총 2100평)_김윤석 법무사 | H26: 0 | I26: 330000 | J26: -330000 | K26: G/L Account | Q26: 45762.889
A27: 45737 | B27: GJ25-0054 | C27: 2202-00-001 | D27: Other payable / 기타미지급금 | E27: VKPMCOR01 | F27: 용역보수_KPMG 삼정회계법인 | H27: 0 | I27: 935000 | J27: -935000 | K27: G/L Account | L27: 5249-00-000 | Q27: 45762.889
A28: 45737 | B28: GJ25-0060 | C28: 1712-00-000 | D28: Leasehold land / 토지 | E28: VSACGOO01 | F28: [KR Inv_202503] VTAXLOC01_Project Phantom_Kummyung Land Acquisition Tax Payment_KRW 11592000 | H28: 11592000 | I28: 0 | J28: 11592000 | K28: Bank Account | L28: HANA-KRW | M28: KRW | N28: Purchase | P28: GENERAL | Q28: 45762.889
A29: 45737 | B29: GJ25-0053 | C29: 1712-00-000 | D29: Leasehold land / 토지 | E29: VKIMYUN01 | F29: VAT_소유권이전 (분매리134-249외 4필지, 총 2100평)_김윤석 법무사 | H29: 30000 | I29: 0 | J29: 30000 | K29: G/L Account | N29: Purchase | P29: GENERAL | Q29: 45762.889
A30: 45737 | B30: GJ25-0053 | C30: 1712-00-000 | D30: Leasehold land / 토지 | E30: VKIMYUN01 | F30: 소유권이전 (분매리134-249외 4필지, 총 2100평)_김윤석 법무사 | H30: 300000 | I30: 0 | J30: 300000 | K30: G/L Account | N30: Purchase | P30: GENERAL | Q30: 45762.889
A31: 45737 | B31: GJ25-0060 | C31: 1112-KR-001 | D31: Cash - KRW (HANA) / 현금 - 원 (HANA) | E31: VSACGOO01 | F31: [KR Inv_202503] VTAXLOC01_Project Phantom_Kummyung Land Acquisition Tax Payment_KRW 11592000 | H31: 0 | I31: 11592000 | J31: -11592000 | K31: G/L Account | L31: 1712-00-000 | M31: KRW | Q31: 45762.889
A32: 45736 | B32: GJ25-0059 | C32: 2202-00-001 | D32: Other payable / 기타미지급금 | E32: VSEJUNG01 | F32: [KR Inv_202503] VSEJUNG01_Kummyung office maintenance fee_KRW 439,610 | H32: 439610 | I32: 0 | J32: 439610 | K32: Bank Account | L32: HANA-KRW | M32: KRW | Q32: 45762.889
A33: 45736 | B33: GJ25-0058 | C33: 2202-00-001 | D33: Other payable / 기타미지급금 | E33: VKPMCOR01 | F33: [KR Inv_202503] VKPMCOR01_KPMG Acct Service for Jan'24_KRW 73372750 | H33: 1540000 | I33: 0 | J33: 1540000 | K33: Bank Account | L33: HANA-KRW | M33: KRW | Q33: 45762.889
A34: 45736 | B34: GJ25-0057 | C34: 2202-00-001 | D34: Other payable / 기타미지급금 | E34: VKPMCOR01 | F34: [KR Inv_202501] VKPMCOR01_KPMG Acct Service for Dec'24_KRW 31141000 | H34: 715000 | I34: 0 | J34: 715000 | K34: Bank Account | L34: HANA-KRW | M34: KRW | Q34: 45762.889
A35: 45736 | B35: GJ25-0059 | C35: 1112-KR-001 | D35: Cash - KRW (HANA) / 현금 - 원 (HANA) | E35: VSEJUNG01 | F35: [KR Inv_202503] VSEJUNG01_Kummyung office maintenance fee_KRW 439,610 | H35: 0 | I35: 439610 | J35: -439610 | K35: Vendor | L35: VSEJUNG01 | M35: KRW | Q35: 45762.889
A36: 45736 | B36: GJ25-0058 | C36: 1112-KR-001 | D36: Cash - KRW (HANA) / 현금 - 원 (HANA) | E36: VKPMCOR01 | F36: [KR Inv_202503] VKPMCOR01_KPMG Acct Service for Jan'24_KRW 73372750 | H36: 0 | I36: 1540000 | J36: -1540000 | K36: Vendor | L36: VKPMCOR01 | M36: KRW | Q36: 45762.889
A37: 45736 | B37: GJ25-0057 | C37: 1112-KR-001 | D37: Cash - KRW (HANA) / 현금 - 원 (HANA) | E37: VKPMCOR01 | F37: [KR Inv_202501] VKPMCOR01_KPMG Acct Service for Dec'24_KRW 31141000 | H37: 0 | I37: 715000 | J37: -715000 | K37: Vendor | L37: VKPMCOR01 | M37: KRW | Q37: 45762.889
A38: 45733 | B38: GJ25-0052 | C38: 5263-00-000 | D38: Advertising / 광고비용 | E38: VHYCHNG01 | F38: 떡류_현창떡집 | H38: 822727 | I38: 0 | J38: 822727 | K38: G/L Account | L38: 2202-00-001 | N38: Purchase | P38: GENERAL | Q38: 45762.889
A39: 45733 | B39: GJ25-0052 | C39: 2407-00-000 | D39: GST/VAT receivable / 부가세대급금 | E39: VHYCHNG01 | F39: 떡류_현창떡집 | H39: 82273 | I39: 0 | J39: 82273 | K39: G/L Account | Q39: 45762.889
A40: 45733 | B40: GJ25-0052 | C40: 2202-00-001 | D40: Other payable / 기타미지급금 | E40: VHYCHNG01 | F40: 떡류_현창떡집 | H40: 0 | I40: 905000 | J40: -905000 | K40: G/L Account | L40: 5263-00-000 | Q40: 45762.889
A41: 45731 | B41: GJ25-0056 | C41: 5612-00-000 | D41: Interest income - bank / 이자수익 - 은행 | E41: VHANABA01 | F41: bank interest income(예금이자 201,741 소득세 28,240 지방소득세 2,820) | H41: 0 | I41: 201741 | J41: -201741 | K41: G/L Account | M41: KRW | N41: Purchase | P41: GENERAL | Q41: 45762.889
A42: 45731 | B42: GJ25-0056 | C42: 1212-00-000 | D42: Income tax receivables / 선납세금 | F42: bank interest income(예금이자 201,741 소득세 28,240 지방소득세 2,820) | H42: 2820 | I42: 0 | J42: 2820 | K42: G/L Account | M42: KRW | N42: Purchase | P42: GENERAL | Q42: 45762.889
A43: 45731 | B43: GJ25-0056 | C43: 1212-00-000 | D43: Income tax receivables / 선납세금 | F43: bank interest income(예금이자 201,741 소득세 28,240 지방소득세 2,820) | H43: 28240 | I43: 0 | J43: 28240 | K43: G/L Account | M43: KRW | N43: Purchase | P43: GENERAL | Q43: 45762.889
A44: 45731 | B44: GJ25-0056 | C44: 1112-KR-001 | D44: Cash - KRW (HANA) / 현금 - 원 (HANA) | E44: VHANABA01 | F44: bank interest income(예금이자 201,741 소득세 28,240 지방소득세 2,820) | H44: 170681 | I44: 0 | J44: 170681 | K44: G/L Account | M44: KRW | Q44: 45762.889
A45: 45729 | B45: GJ25-0051 | C45: 5263-00-000 | D45: Advertising / 광고비용 | E45: VPRDLTD01 | F45: 신안군기념품(타올)구입_유한회사 파란디 | H45: 2727273 | I45: 0 | J45: 2727273 | K45: G/L Account | L45: 2202-00-001 | N45: Purchase | P45: GENERAL | Q45: 45762.889
A46: 45729 | B46: GJ25-0051 | C46: 2407-00-000 | D46: GST/VAT receivable / 부가세대급금 | E46: VPRDLTD01 | F46: 신안군기념품(타올)구입_유한회사 파란디 | H46: 272727 | I46: 0 | J46: 272727 | K46: G/L Account | Q46: 45762.889
A47: 45729 | B47: GJ25-0051 | C47: 2202-00-001 | D47: Other payable / 기타미지급금 | E47: VPRDLTD01 | F47: 신안군기념품(타올)구입_유한회사 파란디 | H47: 0 | I47: 3000000 | J47: -3000000 | K47: G/L Account | L47: 5263-00-000 | Q47: 45762.889
A48: 45726 | B48: GJ25-0070 | C48: 5101-00-000 | D48: Management fee expense / 관리 수수료 비용 | E48: VSEJUNG01 | F48: 관리비_세정아울렛 관리단 | H48: 383020 | I48: 0 | J48: 383020 | K48: Vendor | L48: VSEJUNG01 | N48: Purchase | P48: GENERAL | Q48: 45763.167
A49: 45726 | B49: GJ25-0069 | C49: 5101-00-000 | D49: Management fee expense / 관리 수수료 비용 | E49: VSEJUNG01 | F49: 수정분개 | H49: 0 | I49: 383018 | J49: -383018 | K49: Vendor | L49: VSEJUNG01 | N49: Purchase | P49: GENERAL | Q49: 45763.167
A50: 45726 | B50: GJ25-0050 | C50: 5101-00-000 | D50: Management fee expense / 관리 수수료 비용 | F50: 관리비_세정아울렛 관리단 | H50: 383018 | I50: 0 | J50: 383018 | K50: Vendor | L50: VSEJUNG01 | N50: Purchase | P50: GENERAL | Q50: 45762.889
A51: 45726 | B51: GJ25-0070 | C51: 2407-00-000 | D51: GST/VAT receivable / 부가세대급금 | E51: VSEJUNG01 | F51: 관리비_세정아울렛 관리단 | H51: 38300 | I51: 0 | J51: 38300 | K51: G/L Account | Q51: 45763.167
A52: 45726 | B52: GJ25-0069 | C52: 2407-00-000 | D52: GST/VAT receivable / 부가세대급금 | E52: VSEJUNG01 | F52: 수정분개 | H52: 0 | I52: 38302 | J52: -38302 | K52: G/L Account | Q52: 45763.167
A53: 45726 | B53: GJ25-0050 | C53: 2407-00-000 | D53: GST/VAT receivable / 부가세대급금 | F53: 관리비_세정아울렛 관리단 | H53: 38302 | I53: 0 | J53: 38302 | K53: G/L Account | Q53: 45762.889
A54: 45726 | B54: GJ25-0070 | C54: 2202-00-001 | D54: Other payable / 기타미지급금 | E54: VSEJUNG01 | F54: 관리비_세정아울렛 관리단 | H54: 0 | I54: 421320 | J54: -421320 | K54: G/L Account | L54: 5101-00-000 | Q54: 45763.167
A55: 45726 | B55: GJ25-0069 | C55: 2202-00-001 | D55: Other payable / 기타미지급금 | E55: VSEJUNG01 | F55: 수정분개 | H55: 421320 | I55: 0 | J55: 421320 | K55: G/L Account | L55: 5101-00-000 | Q55: 45763.167
A56: 45726 | B56: GJ25-0050 | C56: 2202-00-001 | D56: Other payable / 기타미지급금 | F56: 관리비_세정아울렛 관리단 | H56: 0 | I56: 421320 | J56: -421320 | K56: G/L Account | L56: 5101-00-000 | Q56: 45762.889
A57: 45722 | B57: GJ25-0049 | C57: 5301-00-000 | D57: Bank charges / 은행 수수료 | F57: 공인인증서(은행/보험용)_HANA BANK (주)하나은행 | H57: 4000 | I57: 0 | J57: 4000 | K57: Vendor | L57: VHANABA01 | N57: Purchase | P57: GENERAL | Q57: 45762.889
A58: 45722 | B58: GJ25-0049 | C58: 2407-00-000 | D58: GST/VAT receivable / 부가세대급금 | F58: 공인인증서(은행/보험용)_HANA BANK (주)하나은행 | H58: 400 | I58: 0 | J58: 400 | K58: G/L Account | Q58: 45762.889
A59: 45722 | B59: GJ25-0055 | C59: 2202-00-001 | D59: Other payable / 기타미지급금 | E59: VHANABA01 | F59: Issuance Fee payment | H59: 4400 | I59: 0 | J59: 4400 | K59: Bank Account | L59: HANA-KRW | M59: KRW | Q59: 45762.889
A60: 45722 | B60: GJ25-0049 | C60: 2202-00-001 | D60: Other payable / 기타미지급금 | F60: 공인인증서(은행/보험용)_HANA BANK (주)하나은행 | H60: 0 | I60: 4400 | J60: -4400 | K60: G/L Account | L60: 5301-00-000 | Q60: 45762.889
A61: 45722 | B61: GJ25-0055 | C61: 1112-KR-001 | D61: Cash - KRW (HANA) / 현금 - 원 (HANA) | E61: VHANABA01 | F61: Issuance Fee payment | H61: 0 | I61: 4400 | J61: -4400 | K61: Vendor | L61: VHANABA01 | M61: KRW | Q61: 45762.889
A62: 45716 | B62: GJ25-0045 | C62: 5719-00-000 | D62: Interest expense - External / 이자비용 - 일반 | E62: VMOKPOC01 | F62: Loan Interest_목포신협 to 금명 (KRW 2,000,000,000_5.1% 변동금리)_목포신용협동조합 | H62: 7824657 | I62: 0 | J62: 7824657 | K62: G/L Account | L62: 2204-00-002 | N62: Purchase | P62: GENERAL | Q62: 45753.834
A63: 45716 | B63: GJ25-0044 | C63: 5717-00-000 | D63: Interest expense - InterCo / 이자비용 - 회사 간 대출 | E63: IEEKR005 | F63: Loan Interest_EEK2 to 금명 (KRW 1,321,408,000_14%)_EEK 2 에퀴스에너지코리아2 유한회사 | H63: 14191560 | I63: 0 | J63: 14191560 | K63: G/L Account | L63: 2204-00-001 | N63: Purchase | P63: GENERAL | Q63: 45753.834
A64: 45716 | B64: GJ25-0046 | C64: 5281-00-000 | D64: Rent / 지급임차료 | E64: VSAMHYO01 | F64: Office rent_유한회사 삼형 | H64: 1000000 | I64: 0 | J64: 1000000 | K64: G/L Account | L64: 1232-00-000 | N64: Purchase | P64: GENERAL | Q64: 45753.834
A65: 45716 | B65: GJ25-0041 | C65: 5249-00-000 | D65: Other legal and professional fees / 기타 법률 및 전문 수수료 | E65: VKPMCOR01 | F65: 용역보수_KPMG 삼정회계법인_KPMG 삼정회계법인 | H65: 650000 | I65: 0 | J65: 650000 | K65: Vendor | L65: VKPMCOR01 | N65: Purchase | P65: GENERAL | Q65: 45753.834
A66: 45716 | B66: GJ25-0041 | C66: 2407-00-000 | D66: GST/VAT receivable / 부가세대급금 | E66: VKPMCOR01 | F66: 용역보수_KPMG 삼정회계법인_KPMG 삼정회계법인 | H66: 65000 | I66: 0 | J66: 65000 | K66: G/L Account | Q66: 45753.834
A67: 45716 | B67: GJ25-0045 | C67: 2204-00-002 | D67: Accrued interest expense - General Loan - Short term / 미지급이자비용 - 일반 대출 - 단기 | E67: VMOKPOC01 | F67: Loan Interest_목포신협 to 금명 (KRW 2,000,000,000_5.1% 변동금리)_목포신용협동조합 | H67: 0 | I67: 7824657 | J67: -7824657 | K67: G/L Account | L67: 5719-00-000 | N67: Purchase | P67: GENERAL | Q67: 45753.834
A68: 45716 | B68: GJ25-0043 | C68: 2204-00-002 | D68: Accrued interest expense - General Loan - Short term / 미지급이자비용 - 일반 대출 - 단기 | E68: VMOKPOC01 | F68: 이자지급 (20억, 23.03.31-26.03.31, 변동금리)_목포신용협동조합 | H68: 7824657 | I68: 0 | J68: 7824657 | K68: Bank Account | L68: SHINHYUP-KRW | M68: KRW | N68: Purchase | P68: GENERAL | Q68: 45753.834
A69: 45716 | B69: GJ25-0044 | C69: 2204-00-001 | D69: Accrued interest expense - Loan - Long term / 미지급이자비용 - 관계사 대출 - 장기 | E69: IEEKR005 | F69: Loan Interest_EEK2 to 금명 (KRW 1,321,408,000_14%)_EEK 2 에퀴스에너지코리아2 유한회사 | H69: 0 | I69: 14191560 | J69: -14191560 | K69: G/L Account | L69: 5717-00-000 | N69: Purchase | P69: GENERAL | Q69: 45753.834
A70: 45716 | B70: GJ25-0041 | C70: 2202-00-001 | D70: Other payable / 기타미지급금 | E70: VKPMCOR01 | F70: 용역보수_KPMG 삼정회계법인_KPMG 삼정회계법인 | H70: 0 | I70: 715000 | J70: -715000 | K70: G/L Account | L70: 5249-00-000 | Q70: 45753.834
A71: 45716 | B71: GJ25-0042 | C71: 1233-00-000 | D71: Other prepaid and advances / 선급금 (유동) | E71: VKPMCOR01 | F71: 과다송금액 반환_삼정 KPMG AAS (proxy payment) | H71: 0 | I71: 43834 | J71: -43834 | K71: Bank Account | L71: SHINHYUP-KRW | M71: KRW | N71: Purchase | P71: GENERAL | Q71: 45753.834
A72: 45716 | B72: GJ25-0046 | C72: 1232-00-000 | D72: Prepaid expenses / 선급비용 | E72: VSAMHYO01 | F72: Office rent_유한회사 삼형 | H72: 0 | I72: 1000000 | J72: -1000000 | K72: G/L Account | L72: 5281-00-000 | N72: Purchase | P72: GENERAL | Q72: 45753.834
A73: 45716 | B73: GJ25-0043 | C73: 1112-KR-005 | D73: Cash - KRW (SHINHYUP) / 현금 - 원 (신협) | E73: VMOKPOC01 | F73: 이자지급 (20억, 23.03.31-26.03.31, 변동금리)_목포신용협동조합 | H73: 0 | I73: 7824657 | J73: -7824657 | K73: G/L Account | L73: 2204-00-002 | M73: KRW | Q73: 45753.834
A74: 45716 | B74: GJ25-0042 | C74: 1112-KR-005 | D74: Cash - KRW (SHINHYUP) / 현금 - 원 (신협) | E74: VKPMCOR01 | F74: 과다송금액 반환_삼정 KPMG AAS (proxy payment) | H74: 43834 | I74: 0 | J74: 43834 | K74: G/L Account | L74: 1233-00-000 | M74: KRW | Q74: 45753.834
A75: 45715 | B75: GJ25-0040 | C75: 2203-00-000 | D75: Intercompany Payable / 관계사미지급금 | E75: IECKR001 | F75: FY24 Q4 MSA_ECSK BO 에퀴스센트럴서비스코리아피티이엘티디 (영업소) | H75: 162774893 | I75: 0 | J75: 162774893 | K75: Bank Account | L75: HANA-KRW | M75: KRW | Q75: 45753.834
A76: 45715 | B76: GJ25-0039 | C76: 1712-00-000 | D76: Leasehold land / 토지 | E76: VNEULSA01 | F76: [KR Inv_202502] VNEULSA01_PJ Phantom Real Estate Sales Contract Payment_KRW 252000000_HANA_Bank 하나은행 | H76: 252000000 | I76: 0 | J76: 252000000 | K76: Bank Account | L76: HANA-KRW | M76: KRW | N76: Purchase | P76: GENERAL | Q76: 45753.834
A77: 45715 | B77: GJ25-0039 | C77: 1112-KR-001 | D77: Cash - KRW (HANA) / 현금 - 원 (HANA) | E77: VNEULSA01 | F77: [KR Inv_202502] VNEULSA01_PJ Phantom Real Estate Sales Contract Payment_KRW 252000000_HANA_Bank 하나은행 | H77: 0 | I77: 252000000 | J77: -252000000 | K77: G/L Account | L77: 1712-00-000 | M77: KRW | Q77: 45753.834
A78: 45715 | B78: GJ25-0040 | C78: 1112-KR-001 | D78: Cash - KRW (HANA) / 현금 - 원 (HANA) | E78: IECKR001 | F78: FY24 Q4 MSA_ECSK BO 에퀴스센트럴서비스코리아피티이엘티디 (영업소) | H78: 0 | I78: 162774893 | J78: -162774893 | K78: Vendor | L78: IECKR001 | M78: KRW | Q78: 45753.834
A79: 45714 | B79: GJ25-0038 | C79: 5601-00-000 | D79: Other expenses / 잡손실 | E79: TAX412 | F79: VAT Return for 2024.4Q_Naju Tax Office 나주세무서 | H79: 5 | I79: 0 | J79: 5 | K79: G/L Account | M79: KRW | N79: Purchase | P79: GENERAL | Q79: 45753.834
A80: 45714 | B80: GJ25-0038 | C80: 1214-00-000 | D80: Other receivables / 기타미수금 | E80: TAX412 | F80: VAT Return for 2024.4Q_Naju Tax Office 나주세무서 | H80: 0 | I80: 22046685 | J80: -22046685 | K80: G/L Account | M80: KRW | N80: Purchase | P80: GENERAL | Q80: 45753.834
A81: 45714 | B81: GJ25-0038 | C81: 1112-KR-001 | D81: Cash - KRW (HANA) / 현금 - 원 (HANA) | E81: VHANABA01 | F81: VAT Return for 2024.4Q_HANA_Bank 하나은행(85704) | H81: 22046680 | I81: 0 | J81: 22046680 | K81: G/L Account | M81: KRW | Q81: 45753.834
A82: 45708 | B82: GJ25-0035 | C82: 2202-00-001 | D82: Other payable / 기타미지급금 | E82: VSEJUNG01 | F82: [KR Inv_202502] VSEJUNG01_Kummyung office maintenance fee_KRW 365,780_HANA_Bank 하나은행(85704) | H82: 365780 | I82: 0 | J82: 365780 | K82: Bank Account | L82: HANA-KRW | M82: KRW | Q82: 45753.834
A83: 45708 | B83: GJ25-0037 | C83: 2202-00-001 | D83: Other payable / 기타미지급금 | E83: VKPMCOR01 | F83: [KR Inv_202501] VKPMCOR01_KPMG Acct Service for Dec'24_KRW 31141000_HANA_Bank 하나은행(85704) | H83: 715000 | I83: 0 | J83: 715000 | K83: Bank Account | L83: HANA-KRW | M83: KRW | Q83: 45753.834
A84: 45708 | B84: GJ25-0036 | C84: 2202-00-001 | D84: Other payable / 기타미지급금 | E84: VKPMCOR01 | F84: [KR Inv_202410] VKPMCOR01_KPMG Acct Service for Sep'24_KRW 48669500_HANA_Bank 하나은행(85704) | H84: 715000 | I84: 0 | J84: 715000 | K84: Bank Account | L84: HANA-KRW | M84: KRW | Q84: 45753.834
A85: 45708 | B85: GJ25-0035 | C85: 1112-KR-001 | D85: Cash - KRW (HANA) / 현금 - 원 (HANA) | E85: VSEJUNG01 | F85: [KR Inv_202502] VSEJUNG01_Kummyung office maintenance fee_KRW 365,780_HANA_Bank 하나은행(85704) | H85: 0 | I85: 365780 | J85: -365780 | K85: Vendor | L85: VSEJUNG01 | M85: KRW | Q85: 45753.834
A86: 45708 | B86: GJ25-0037 | C86: 1112-KR-001 | D86: Cash - KRW (HANA) / 현금 - 원 (HANA) | E86: VKPMCOR01 | F86: [KR Inv_202501] VKPMCOR01_KPMG Acct Service for Dec'24_KRW 31141000_HANA_Bank 하나은행(85704) | H86: 0 | I86: 715000 | J86: -715000 | K86: Vendor | L86: VKPMCOR01 | M86: KRW | Q86: 45753.834
A87: 45708 | B87: GJ25-0036 | C87: 1112-KR-001 | D87: Cash - KRW (HANA) / 현금 - 원 (HANA) | E87: VKPMCOR01 | F87: [KR Inv_202410] VKPMCOR01_KPMG Acct Service for Sep'24_KRW 48669500_HANA_Bank 하나은행(85704) | H87: 0 | I87: 715000 | J87: -715000 | K87: Vendor | L87: VKPMCOR01 | M87: KRW | Q87: 45753.834
A88: 45707 | B88: GJ25-0034 | C88: 5601-00-000 | D88: Other expenses / 잡손실 | E88: IECKR001 | F88: MSA24Q1,Q2,Q3_ECSK BO 에퀴스센트럴서비스코리아피티이엘티디 (영업소) | H88: 1 | I88: 0 | J88: 1 | K88: G/L Account | M88: KRW | N88: Purchase | P88: GENERAL | Q88: 45753.834
A89: 45707 | B89: GJ25-0033 | C89: 5342-00-000 | D89: FX - realized loss - others / 외환차손 | E89: VHANABA01 | F89: 231 EEKHPL_Unsecured Loan Agreement(USD 260,000)_bank transfer_HANA_Bank 하나은행(70638) | H89: 1817400 | I89: 0 | J89: 1817400 | K89: G/L Account | M89: KRW | N89: Purchase | P89: GENERAL | Q89: 45753.834
A90: 45707 | B90: GJ25-0032 | C90: 5342-00-000 | D90: FX - realized loss - others / 외환차손 | E90: VHANABA01 | F90: 230 EEKHPL_Unsecured Loan Agreement(USD 1,500,000)_bank transfer_HANA_Bank 하나은행(70638) | H90: 10485000 | I90: 0 | J90: 10485000 | K90: G/L Account | M90: KRW | N90: Purchase | P90: GENERAL | Q90: 45753.834
A91: 45707 | B91: GJ25-0029 | C91: 5301-00-000 | D91: Bank charges / 은행 수수료 | E91: VHANABA01 | F91: 공인인증서(은행/보험용)_HANA BANK (주)하나은행_HANA BANK (주)하나은행 | H91: 4000 | I91: 0 | J91: 4000 | K91: Vendor | L91: VHANABA01 | N91: Purchase | P91: GENERAL | Q91: 45753.834
A92: 45707 | B92: GJ25-0028 | C92: 5301-00-000 | D92: Bank charges / 은행 수수료 | E92: VHANABA01 | F92: 공인인증서(은행/보험용)_HANA BANK (주)하나은행_HANA BANK (주)하나은행 | H92: 4000 | I92: 0 | J92: 4000 | K92: Vendor | L92: VHANABA01 | N92: Purchase | P92: GENERAL | Q92: 45753.834
A93: 45707 | B93: GJ25-0029 | C93: 2407-00-000 | D93: GST/VAT receivable / 부가세대급금 | E93: VHANABA01 | F93: 공인인증서(은행/보험용)_HANA BANK (주)하나은행_HANA BANK (주)하나은행 | H93: 400 | I93: 0 | J93: 400 | K93: G/L Account | Q93: 45753.834
A94: 45707 | B94: GJ25-0028 | C94: 2407-00-000 | D94: GST/VAT receivable / 부가세대급금 | E94: VHANABA01 | F94: 공인인증서(은행/보험용)_HANA BANK (주)하나은행_HANA BANK (주)하나은행 | H94: 400 | I94: 0 | J94: 400 | K94: G/L Account | Q94: 45753.834
A95: 45707 | B95: GJ25-0034 | C95: 2203-00-000 | D95: Intercompany Payable / 관계사미지급금 | E95: IECKR001 | F95: MSA24Q1,Q2,Q3_HANA_Bank 하나은행(85704) | H95: 297152364 | I95: 0 | J95: 297152364 | K95: G/L Account | M95: KRW | Q95: 45753.834
A96: 45707 | B96: GJ25-0031 | C96: 2202-00-001 | D96: Other payable / 기타미지급금 | E96: VHANABA01 | F96: Issuance Fee payment_HANA_Bank 하나은행(85704) | H96: 4400 | I96: 0 | J96: 4400 | K96: Bank Account | L96: HANA-KRW | M96: KRW | Q96: 45753.834
A97: 45707 | B97: GJ25-0030 | C97: 2202-00-001 | D97: Other payable / 기타미지급금 | E97: VHANABA01 | F97: Issuance Fee payment_HANA_Bank 하나은행(85704) | H97: 4400 | I97: 0 | J97: 4400 | K97: Bank Account | L97: HANA-KRW | M97: KRW | Q97: 45753.834
A98: 45707 | B98: GJ25-0029 | C98: 2202-00-001 | D98: Other payable / 기타미지급금 | E98: VHANABA01 | F98: 공인인증서(은행/보험용)_HANA BANK (주)하나은행_HANA BANK (주)하나은행 | H98: 0 | I98: 4400 | J98: -4400 | K98: G/L Account | L98: 5301-00-000 | Q98: 45753.834
A99: 45707 | B99: GJ25-0028 | C99: 2202-00-001 | D99: Other payable / 기타미지급금 | E99: VHANABA01 | F99: 공인인증서(은행/보험용)_HANA BANK (주)하나은행_HANA BANK (주)하나은행 | H99: 0 | I99: 4400 | J99: -4400 | K99: G/L Account | L99: 5301-00-000 | Q99: 45753.834
A100: 45707 | B100: GJ25-0034 | C100: 1112-KR-001 | D100: Cash - KRW (HANA) / 현금 - 원 (HANA) | E100: VHANABA01 | F100: MSA24Q1,Q2,Q3_ECSK BO 에퀴스센트럴서비스코리아피티이엘티디 (영업소) | H100: 0 | I100: 297152365 | J100: -297152365 | K100: G/L Account | M100: KRW | Q100: 45753.834
...

Sheet 고객사 확인 요청 사항
A1: 1 | B1: EY 문의 사항
B2: *압해도 태양광 발전사업 - 1차 운영비 지급 건 -아직 자산화 하지 않고, 기타 운영 비용으로 처리 하였는데, 토지 매입 관련 비용으로 자산화 처리 해야 하는지 여부 확인 부탁드립니다. | L2: 건설중 자산 or 토지
B3: 4/11/2025 | C3: 22 | D3: 5108-00-000 | E3: Other operating expense / 기타 운영 비용 | F3: 압해도 태양광 발전사업 개발용역 6-1_늘샘그린에너지 주식회사 | G3: 20000000 | H3: 0
B4: 4/11/2025 | C4: 22 | D4: 2407-00-000 | E4: GST/VAT receivable / 부가세대급금 | F4: 압해도 태양광 발전사업 개발용역 6-1_늘샘그린에너지 주식회사 | G4: 2000000 | H4: 0
B5: 4/11/2025 | C5: 22 | D5: 1112-KR-001 | E5: Cash - KRW (HANA) / 현금 - 원 (HANA) | F5: 압해도 태양광 발전사업 개발용역 6-1_늘샘그린에너지 주식회사 | G5: 0 | H5: 22000000
B6: Equis 답변
B7: 자산화 하라고하심
A10: P5 | B10: EY 문의 사항
B15: ECSK에서 발행된 2025 1Q 세금계산서 있음. 해당 사항 24년도 말 부로 모두 관계사 미지급금으로 재분류 된것을 확인하였으나
B16: 확인된 24년도부터 지속적으로 발생된것으로 보아 계약서가 있을것으로 사려됨
B17: 해당 사항에 대한 증빙이 현재 확인되지 않음으로 관련 서류 요청드립니다.

Sheet BS
A2: 재 무 상 태 표
A3: 2026/03/31
A4: 회 사 명 : 금명 유한회사 | G4: (단위:원)
B5: 과목 | C5: 46053 | D5: 46081 | E5: 46112 | F5: 2025-12-31 | G5: 증가(감소)액 | H5: 증가(감소)율
B6: 자산
B7: 유동자산 | C7: =C8 -> 637162948 | D7: =D8 -> 161358890 | E7: =E8 -> 2543688929 | F7: 1569336905 | G7: =E7-F7 -> 974352024 | H7: 3.48205
B8: 당좌자산 | C8: =C9+C12+C13+C14+C15+C16 -> 637162948 | D8: =D9+D12+D13+D14+D15+D16 -> 161358890 | E8: =E9+E12+E13+E14+E15+E16 -> 2543688929 | F8: 1569336905 | G8: =E8-F8 -> 974352024 | H8: 3.48205
B9: 보통예금 | C9: =C10+C11 -> 291756083 | D9: =D10+D11 -> 84855919 | E9: =E10+E11 -> 2468045538 | F9: 1405309172 | G9: =E9-F9 -> 1062736366 | H9: 4.08529
B10: 현금 - 원 (HANA) | C10: 288507178 | D10: 69264438 | E10: 2467032264 | F10: 1402060267 | G10: =E10-F10 -> 1064971997 | H10: 4.52362
B11: 현금 - 원 (신협) | C11: 3248905 | D11: 15591481 | E11: 1013274 | F11: 3248905 | G11: =E11-F11 -> -2235631 | H11: -0.44571
B12: 선납세금 | C12: 340300 | D12: 340300 | E12: 374020 | F12: 340300 | G12: =E12-F12 -> 33720 | H12: 0%
B13: 기타미수금 | C13: 36539357 | D13: 22404357 | E13: 22404357 | F13: 36539357 | G13: =E13-F13 -> -14135000 | H13: 0%
B14: 선급비용 | D14: 9000000 | E14: 8000000 | G14: =E14-F14 -> 8000000 | H14: -0.18182
B15: 선급금 (유동) | G15: =E15-F15 -> 0 | H15: -1
B16: 부가세대급금 | C16: 308527208 | D16: 44758314 | E16: 44865014 | F16: 127148076 | G16: =E16-F16 -> -82283062 | H16: -0.31639
B17: 재고자산 | G17: =E17-F17 -> 0 | H17: 0%
B18: 비유동자산 | C18: =C19+C20+C24 -> 9683028144 | D18: =D19+D20+D24 -> 10014000244 | E18: =E19+E20+E24 -> 10176426194 | F18: 8577016044 | G18: =E18-F18 -> 1599410150 | H18: 0.03704
B19: 투자자산 | G19: =E19-F19 -> 0 | H19: 0%
B20: 유형자산 | C20: =SUM(C21:C22) -> 9662048144 | D20: =SUM(D21:D22) -> 9993020244 | E20: =SUM(E21:E22) -> 10155446194 | F20: 8556036044 | G20: =E20-F20 -> 1599410150 | H20: 0.03715
B21: 토지 | C21: 8772436144 | D21: 9137120244 | E21: 9299546194 | F21: 7684424044 | G21: =E21-F21 -> 1615122150 | H21: 0.03715
B22: 건설중인자산 | C22: 889612000 | D22: 855900000 | E22: 855900000 | F22: 871612000 | G22: =E22-F22 -> -15712000
B23: 무형자산 | G23: =E23-F23 -> 0 | H23: 0%
B24: 기타비유동자산 | C24: =C25 -> 20980000 | D24: =D25 -> 20980000 | E24: =E25 -> 20980000 | F24: 20980000 | G24: =E24-F24 -> 0 | H24: 0%
B25: 임차보증금 - 비유동 | C25: 20980000 | D25: 20980000 | E25: 20980000 | F25: 20980000 | G25: =E25-F25 -> 0 | H25: 0%
B26: 자산 총 계 | C26: =C18+C7 -> 10320191092 | D26: =D18+D7 -> 10175359134 | E26: =E18+E7 -> 12720115123 | F26: 10146352949 | G26: =E26-F26 -> 2573762174 | H26: 0.26765
B27: 부채 | C27: =C33+C28 -> 9906100377 | D27: =D33+D28 -> 10042633766 | E27: =E33+E28 -> 12970079959 | F27: 9317747503 | G27: =E27-F27 -> 3652332456
B28: 유동부채 | C28: =SUM(C29:C32) -> 618000028 | D28: =SUM(D29:D32) -> 761708457 | E28: =SUM(E29:E32) -> 431102093 | F28: 16535838 | G28: =E28-F28 -> 414566255 | H28: -0.9812
B29: 계약부채 | G29: =E29-F29 -> 0
B30: 기타미지급금 | C30: 10071250 | D30: 14854210 | E30: 9994450 | F30: 7091250 | G30: =E30-F30 -> 2903200 | H30: -0.81823
B31: 관계사미지급금 | C31: 600273205 | D31: 739939715 | E31: 421107643 | F31: 9446439 | G31: =E31-F31 -> 411661204 | H31: -0.99487
B32: 미지급이자비용 - 일반 대출 -단기 | C32: =7657424-1851 -> 7655573 | D32: =6916383-1851 -> 6914532 | G32: =E32-F32 -> 0
B33: 비유동부채 | C33: =SUM(C34:C36) -> 9288100349 | D33: =SUM(D34:D36) -> 9280925309 | E33: =SUM(E34:E36) -> 12538977866 | F33: 9301211665 | G33: =E33-F33 -> 3237766201 | H33: 0.51986
B34: 은행 대출 | C34: 1960000000 | D34: 1960000000 | E34: 1960000000 | F34: 1960000000 | G34: =E34-F34 -> 0 | H34: 0%
B35: 관계사 대출 - 장기 | C35: 5495810680 | D35: 5474444080 | E35: 8716784553 | F35: 5524634080 | G35: =E35-F35 -> 3192150473 | H35: 1.92593
B36: 미지급이자비용 - 관계사 대출 - 장기 | C36: 1832289669 | D36: 1846481229 | E36: 1862193313 | F36: 1816577585 | G36: =E36-F36 -> 45615728 | H36: 0.01833
B37: 부채 총 계 | C37: =C27 -> 9906100377 | D37: =D27 -> 10042633766 | E37: =E27 -> 12970079959 | F37: 9317747503 | G37: =E37-F37 -> 3652332456 | H37: 0.37045
B38: 자본 | C38: =C39+C41+C42+C45+C46 -> 414090715 | D38: =D39+D41+D42+D45+D46 -> 132725368 | E38: =E39+E41+E42+E45+E46 -> -249964836 | F38: 828605446 | G38: =E38-F38 -> -1078570282
B39: 자본금 | C39: 4004550000 | D39: 4004550000 | E39: =E40 -> 4004550000 | F39: 4004550000 | G39: =E39-F39 -> 0 | H39: 0%
B40: 보통주 | C40: 4004550000 | D40: 4004550000 | E40: 4004550000 | F40: 4004550000 | G40: =E40-F40 -> 0 | H40: 0%
B41: 자본잉여금 | G41: =E41-F41 -> 0 | H41: 0%
B42: 자본 조정 | C42: =C43+C44 -> -1373878747 | D42: =D43+D44 -> -1373878747 | E42: =E43+E44 -> -1373878747 | F42: -1373878747 | G42: =E42-F42 -> 0 | H42: 0%
B43: 감자차손 | C43: -1347557747 | D43: -1347557747 | E43: -1347557747 | F43: -1347557747 | G43: =E43-F43 -> 0 | H43: 0%
B44: 주식할인 발행차금 | C44: -26321000 | D44: -26321000 | E44: -26321000 | F44: -26321000 | G44: =E44-F44 -> 0 | H44: 0%
B45: 기타포괄손익 | G45: =E45-F45 -> 0 | H45: 0%
B46: 이익잉여금 | C46: =SUM(C47:C48) -> -2216580538 | D46: -2497945885 | E46: -2880636089 | F46: -1802065807 | G46: =E46-F46 -> -1078570282 | H46: -0.10248
B47: 이익 잉여금 | C47: =F47+F48 -> -1641937559 | D47: =C47 -> -1641937559 | E47: =D47 -> -1641937559 | F47: -839391686 | G47: =E47-F47 -> -802545873 | H47: -2.60591
B48: 당기순이익 | C48: =IS!C36 -> -574642979 | D48: =IS!C36+IS!D36 -> -734660078 | E48: =IS!C36+IS!D36+IS!E36 -> -1117348431 | F48: -802545873 | G48: =E48-F48 -> -314802558 | H48: 0.93685
B49: 자본 총 계 | C49: =C38 -> 414090715 | D49: =D38 -> 132725368 | E49: =E38 -> -249964836 | F49: 828605446 | G49: =E49-F49 -> -1078570282 | H49: -0.04802
B50: 자본 및 부채 총 계 | C50: =C49+C37 -> 10320191092 | D50: =D49+D37 -> 10175359134 | E50: =E49+E37 -> 12720115123 | F50: 10146352949 | G50: =E50-F50 -> 2573762174 | H50: 0.26765
C52: =C26=C37+C49 -> TRUE | D52: =D26=D37+D49 -> TRUE | E52: =E26=E37+E49 -> TRUE | F52: =E47+E48-E46 -> 121350099 | G52: =F47+F48-F46 -> 160128248
C53: =C48=SUM(IS!$C$36:C36) -> TRUE | D53: =D48=SUM(IS!$C$36:D36) -> TRUE | E53: =E48=SUM(IS!$C$36:E36) -> TRUE
C55: =C50-C26 -> 0

Sheet IS
A2: 손 익 계 산 서
A3: 2026/01/01~2026/03/31 ( 2026/01/01~2026/12/31 )
A4: 회 사 명 : 금명 유한회사 | F4: (단위:원)
B5: 과목 | C5: 2026/01/31 | D5: 2026/02/28 | E5: 2026/03/31 | F5: 2026/01/01~2026/12/31
B6: 매출 | F6: 0
B7: 매출원가 | F7: 0
B8: 매출총이익 | F8: 0
B9: 판매비와 관리비 | C9: 557740541 | D9: 143720611 | E9: 141769435 | F9: =SUM(C9:E9) -> 843230587
B10: 관리 수수료 비용 | C10: 327870 | D10: 354330 | E10: 323510 | F10: =SUM(C10:E10) -> 1005710
B11: 공유 서비스 비용 | C11: 2049443 | F11: =SUM(C11:E11) -> 2049443
B12: 기타 법률 및 전문 수수료 | D12: 2700000 | F12: =SUM(C12:E12) -> 2700000
B13: 관리운용비용 | C13: 554311352 | D13: 139654281 | E13: 139697985 | F13: =SUM(C13:E13) -> 833663618
B14: 지급임차료 | C14: 1000000 | D14: 1000000 | E14: 1000000 | F14: =SUM(C14:E14) -> 3000000
B15: 광고비용 | F15: =SUM(C15:E15) -> 0
B16: 은행 수수료 | C16: 51876 | D16: 12000 | E16: 8400 | F16: =SUM(C16:E16) -> 72276
B17: 기부금 | F17: =SUM(C17:E17) -> 0
B18: 기타 운영 비용 | F18: =SUM(C18:E18) -> 0
B19: 여비교통비 | F19: =SUM(C19:E19) -> 0
B20: 세금과 공과 | E20: 739540 | F20: =SUM(C20:E20) -> 739540
B21: 영업이익 | C21: =-C9 -> -557740541 | D21: =-D9 -> -143720611 | E21: =-E9 -> -141769435 | F21: =SUM(C21:E21) -> -843230587
B22: 영업외수익 | C22: -11135400 | D22: -8254600 | E22: -19170929 | F22: =SUM(C22:E22) -> -38560929
B23: 이자수익 - 은행 | E23: 219071 | F23: =SUM(C23:E23) -> 219071
B24: 외화환산이익 | C24: -11135400 | D24: 8254600 | E24: -19390000 | F24: =SUM(C24:E24) -> -22270800
B25: 잡이익 | F25: =SUM(C25:E25) -> 0
B26: 외환차익 | F26: =SUM(C26:E26) -> 0
B27: 영업외비용 | C27: =SUM(C28:C32) -> 5767038 | D27: =SUM(D28:D32) -> 8041888 | E27: =SUM(E28:E32) -> 221747989 | F27: =SUM(C27:E27) -> 235556915
B28: 외환차손 | C28: 410005 | E28: 70172431 | F28: =SUM(C28:E28) -> 70582436
B29: 잡손실 | C29: 18030 | D29: 33716 | E29: 18350 | F29: =SUM(C29:E29) -> 70096
B30: 이자비용 - 회사 간 대출 | C30: 15712084 | D30: 14191560 | E30: 15712084 | F30: =SUM(C30:E30) -> 45615728
B31: 이자비용 - 일반 | C31: 7657424 | D31: 6916383 | E31: 7657424 | F31: =SUM(C31:E31) -> 22231231
B32: 외화환산손실 | C32: -18030505 | D32: -13099771 | E32: 128187700 | F32: =SUM(C32:E32) -> 97057424
B33: 기타 금융 비용 | F33: =SUM(C33:E33) -> 0
B34: 법인세 비용 차감전 순이익 | C34: =C21+C22-C27 -> -574642979 | D34: =D21+D22-D27 -> -160017099 | E34: =E21+E22-E27 -> -382688353 | F34: =SUM(C34:E34) -> -1117348431
B35: 소득세와 법인세 | F35: =SUM(C35:E35) -> 0
B36: 당기순이익 | C36: =C34 -> -574642979 | D36: =D34 -> -160017099 | E36: =E34 -> -382688353 | F36: =SUM(C36:E36) -> -1117348431
C38: =SUM(C36:C36) -> -574642979 | D38: =SUM(C36:D36) -> -734660078 | E38: =SUM(C36:E36) -> -1117348431
C39: =C21-C27+C22 -> -574642979 | D39: =D21-D27+D22 -> -160017099 | E39: =E21-E27+E22 -> -382688353
C40: =C36=C39 -> TRUE | D40: =D36=D39 -> TRUE | E40: =E36=E39 -> TRUE

Sheet TB
A1: 시산표
A2: 금명 유한회사
A3: 2026/03/01 ~ 2026/03/31
A4: 계정 | B4: 계정명 | D4: 차변 | E4: 대변
A5: 1112-KR-001 | B5: Cash - KRW (HANA) / 현금 - 원 (HANA) | C5: 69264438 | D5: 3024823473 | E5: 627055647 | F5: 2467032264
A6: 1108-KR-001 | B6: Cash - USD (HANA) / 현금 - USD (HANA) | C6: 0 | D6: 3024823473 | E6: 3024823473 | F6: 0
A7: 1112-KR-005 | B7: Cash - KRW (SHINHYUP) / 현금 - 원 (신협) | C7: 15591481 | D7: 0 | E7: 14578207 | F7: 1013274
A8: 1211-00-000 | B8: Accounts receivables / 외상매출금 | C8: 11404357 | D8: 0 | E8: 0 | F8: 11404357 | G8: ->기타미수금
A9: 1212-00-000 | B9: Income tax receivables / 선납세금 | C9: 340300 | D9: 33720 | E9: 0 | F9: 374020
A10: 1214-00-000 | B10: Other receivables / 기타미수금 | C10: 11000000 | D10: 0 | E10: 0 | F10: 11000000
A11: 1231-00-000 | B11: Deposits and advances / 임차보증금 - 비유동 | C11: 20980000 | D11: 0 | E11: 0 | F11: 20980000
A12: 1232-00-000 | B12: Prepaid expenses / 선급비용 | C12: 9000000 | D12: 0 | E12: 1000000 | F12: 8000000
A13: 1713-00-000 | B13: Land/토지 | C13: 9137120244 | D13: 173425950 | E13: 9472000 | F13: =C13+D13-E13 -> 9301074194
A14: 2407-00-000 | B14: GST/VAT receivable / 부가세대급금 | C14: 44758314 | D14: 1106700 | E14: 1000000 | F14: =C14+D14-E14 -> 44865014
A15: 1760-00-028 | B15: Construction work in progress / 건설중인 자산 | C15: 855900000 | D15: 1000000 | E15: 1000000 | F15: =C15+D15-E15 -> 855900000
A16: 자산 Total | C16: =SUM(C5:C15) -> 10175359134 | D16: =SUM(D5:D15) -> 6225213316 | E16: =SUM(E5:E15) -> 3678929327 | F16: =SUM(F5:F15) -> 12721643123
A17: 2101-00-000 | B17: Bank loans / 은행 대출 | C17: -1960000000 | F17: -1960000000
A18: 2102-00-000 | B18: Intercompany loans / 관계사 대출 - 장기 | C18: -5474444080 | D18: 3643200 | E18: 3245983673 | F18: -8716784553
A19: 2202-00-001 | B19: Other payable / 기타미지급금 | C19: -14854210 | D19: 169463860 | E19: 175604100 | F19: -20994450
A20: 2203-00-000 | B20: Intercompany Payable / 관계사미지급금 | C20: -739939715 | D20: 737890476 | E20: 419058404 | F20: -421107643
A21: 2204-00-001 | B21: Accrued interest expense - Loan - Long term / 미지급이자비용 - 관계사 대출 - 장기 | C21: -1846481229 | E21: 15712084 | F21: -1862193313
A22: 2204-00-002 | B22: Accrued interest expense - General Loan - Short term / 미지급이자비용 - 일반 대출 - 단기 | C22: -6916383 | D22: 14573807 | E22: 7657424 | F22: 0
A23: 부채 Total | C23: =SUM(C17:C22) -> -10042635617 | D23: =SUM(D17:D22) -> 925571343 | E23: =SUM(E17:E22) -> 3864015685 | F23: =SUM(F17:F22) -> -12981079959
A24: 3111-00-000 | B24: Ordinary shares / 보통주 | C24: -4004550000 | F24: -4004550000
A25: 3113-00-001 | B25: Discount on stock issuance / 주식할인 발행차금 | C25: 26321000 | F25: 26321000
A26: 3304-00-000 | B26: Loss on capital reduction / 감자차손 | C26: 1347557747 | F26: 1347557747
A27: 3401-00-000 | B27: Retained earnings / 이익 잉여금 | C27: 1802067658 | F27: 1802067658
A28: 자본 Total | C28: =SUM(C24:C27) -> -828603595 | D28: =SUM(D24:D27) -> 0 | E28: =SUM(E24:E27) -> 0 | F28: =SUM(F24:F27) -> -828603595
A29: 5101-00-000 | B29: Management fee expense / 관리 수수료 비용 | C29: 682200 | D29: 323510 | E29: 0 | F29: =C29+D29-E29 -> 1005710
A30: 5106-00-000 | B30: Shared service charges / 공유 서비스 비용 | C30: 2049443 | D30: 0 | E30: 0 | F30: =C30+D30-E30 -> 2049443
A31: 5211-00-000 | B31: Organizational expenses / 관리운용비용 | C31: 693965633 | D31: 418998395 | E31: 279300410 | F31: =C31+D31-E31 -> 833663618
A32: 5108-00-000 | B32: Other operating expense / 기타 운영 비용 | C32: 1800000 | D32: 0 | E32: 0 | F32: =C32+D32-E32 -> 1800000
A33: 5249-00-000 | B33: Other legal and professional fees / 기타 법률 및 전문 수수료 | C33: 2700000 | D33: 0 | E33: 0 | F33: =C33+D33-E33 -> 2700000 | H33: `
A34: 5263-00-000 | B34: Advertising / 광고비용 | C34: 4505000 | D34: 0 | E34: 0 | F34: =C34+D34-E34 -> 4505000
A35: 5279-00-000 | B35: Other travel, entertainment & social events / 여비교통비 - 기타 | C35: 39000 | D35: 0 | E35: 0 | F35: =C35+D35-E35 -> 39000
A36: 5243-00-000 | B36: Tax consultancy fees / 세금과공과 | C36: 0 | D36: 739540 | E36: 0 | F36: =C36+D36-E36 -> 739540
A37: 7103-00-000 | B37: Other tax expense / 기타 세금과공과 | C37: 55000 | D37: 0 | E37: 0 | F37: =C37+D37-E37 -> 55000
A38: 5281-00-000 | B38: Rent / 지급임차료 | C38: 2000000 | D38: 10472000 | E38: 0 | F38: =C38+D38-E38 -> 12472000
A39: 5301-00-000 | B39: Bank charges / 은행 수수료 | C39: 63876 | D39: 8400 | E39: 0 | F39: =C39+D39-E39 -> 72276
A40: 5319-00-000 | B40: Donations / 기부금 | C40: 20000000 | D40: 0 | E40: 0 | F40: =C40+D40-E40 -> 20000000
A41: 5341-00-000 | B41: FX - realized gains - others / 외환차익 | C41: 0 | D41: 0 | E41: 0 | F41: =C41+D41-E41 -> 0
A42: 5342-00-000 | B42: FX - realized loss - others / 외환차손 | C42: 410005 | D42: 70172431 | E42: 0 | F42: =C42+D42-E42 -> 70582436
A43: 4401-00-000 | B43: Other income / 잡이익 | C43: -9999 | D43: 0 | E43: 0 | F43: =C43+D43-E43 -> -9999
A44: 5601-00-000 | B44: Other expenses / 잡손실 | C44: 51746 | D44: 18350 | E44: 0 | F44: =C44+D44-E44 -> 70096
A45: 5612-00-000 | B45: Interest income - bank / 이자수익 - 은행 | C45: 0 | D45: 0 | E45: 219071 | F45: =C45+D45-E45 -> -219071
... A50: 6402-00-002 | B50: FX - unrealized gains - others / 외화환산손실 | C50: -31130276 | D50: 131843129 | E50: 3655429 | F50: =C50+D50-E50 -> 97057424
A51: 비용 Total | C51: =SUM(C29:C50) -> 722473458 | D51: =SUM(D29:D50) -> 675335263 | E51: =SUM(E29:E50) -> 283174910 | F51: =SUM(F29:F50) -> 1114633811
B52: Total | C52: =C16+C23+C28+C51 -> 26593380 | D52: =D16+D23+D28+D51 -> 7826119922 | E52: =E16+E23+E28+E51 -> 7826119922 | F52: =F16+F23+F28+F51 -> 26593380

Sheet JE(5)
A1: Posting Date | B1: 날짜 | C1: Document No. | D1: G/L Account No. | E1: G/L Account Name | F1: Description | G1: Debit Amount (LCY) | H1: Credit Amount (LCY) | I1: Vendor Code
A2: 1/1/2024 | B2: =TEXT(DATE(RIGHT(A2,4),LEFT(A2,FIND("/",A2)-1),MID(A2,FIND("/",A2)+1,FIND("/",A2,FIND("/",A2)+1)-FIND("/",A2)-1)),"yyyy/mm/dd") -> 2024/01/01 | C2: 20241130-1 | D2: 1211-00-000 | E2: Accounts receivables / 외상매출금 | F2: 2023년 확정 (본사직원) 고용보험료 (분할신설법인 부담분) | G2: 36448817 | H2: 0
A3: 1/1/2024 | B3: =TEXT(DATE(RIGHT(A3,4),LEFT(A3,FIND("/",A3)-1),MID(A3,FIND("/",A3)+1,FIND("/",A3,FIND("/",A3)+1)-FIND("/",A3)-1)),"yyyy/mm/dd") -> 2024/01/01 | C3: 20241130-1 | D3: 1211-00-000 | E3: Accounts receivables / 외상매출금 | F3: 2023년 확정 (본사직원) 고용보험료 (분할신설법인 부담분) | G3: 0 | H3: 36448817
A4: 2/1/2024 | B4: =TEXT(DATE(RIGHT(A4,4),LEFT(A4,FIND("/",A4)-1),MID(A4,FIND("/",A4)+1,FIND("/",A4,FIND("/",A4)+1)-FIND("/",A4)-1)),"yyyy/mm/dd") -> 2024/02/01 | C4: 20241130-1 | D4: 2203-00-000 | E4: Intercompany Payable / 관계사미지급금 | F4: IECSG001-INV24-0044 | G4: 0 | H4: 769691
A5: 2/1/2024 | B5: =TEXT(DATE(RIGHT(A5,4),LEFT(A5,FIND("/",A5)-1),MID(A5,FIND("/",A5)+1,FIND("/",A5,FIND("/",A5)+1)-FIND("/",A5)-1)),"yyyy/mm/dd") -> 2024/02/01 | C5: 20241130-1 | D5: 2203-00-000 | E5: Intercompany Payable / 관계사미지급금 | F5: IECSG001-INV24-0044 | G5: 769691 | H5: 0
A6: 3/29/2024 | B6: =TEXT(DATE(RIGHT(A6,4),LEFT(A6,FIND("/",A6)-1),MID(A6,FIND("/",A6)+1,FIND("/",A6,FIND("/",A6)+1)-FIND("/",A6)-1)),"yyyy/mm/dd") -> 2024/03/29 | C6: 20241130-2 | D6: 1211-00-000 | E6: Accounts receivables / 외상매출금 | F6: 2023년 확정 (본사직원) 고용보험료 (분할신설법인 부담분) | G6: 52910 | H6: 0
A7: 3/29/2024 | B7: =TEXT(DATE(RIGHT(A7,4),LEFT(A7,FIND("/",A7)-1),MID(A7,FIND("/",A7)+1,FIND("/",A7,FIND("/",A7)+1)-FIND("/",A7)-1)),"yyyy/mm/dd") -> 2024/03/29 | C7: 20241130-2 | D7: 1211-00-000 | E7: Accounts receivables / 외상매출금 | F7: 2023년 확정 (본사직원) 고용보험료 (분할신설법인 부담분) | G7: 0 | H7: 52910
A8: 3/29/2024 | B8: =TEXT(DATE(RIGHT(A8,4),LEFT(A8,FIND("/",A8)-1),MID(A8,FIND("/",A8)+1,FIND("/",A8,FIND("/",A8)+1)-FIND("/",A8)-1)),"yyyy/mm/dd") -> 2024/03/29 | C8: 20241130-3 | D8: 1211-00-000 | E8: Accounts receivables / 외상매출금 | F8: 2023년 확정 (본사직원) 산재보험료 (분할신설법인 부담분) | G8: 37630 | H8: 0
A9: 3/29/2024 | B9: =TEXT(DATE(RIGHT(A9,4),LEFT(A9,FIND("/",A9)-1),MID(A9,FIND("/",A9)+1,FIND("/",A9,FIND("/",A9)+1)-FIND("/",A9)-1)),"yyyy/mm/dd") -> 2024/03/29 | C9: 20241130-3 | D9: 1211-00-000 | E9: Accounts receivables / 외상매출금 | F9: 2023년 확정 (본사직원) 산재보험료 (분할신설법인 부담분) | G9: 0 | H9: 37630
A10: 5/31/2024 | B10: =TEXT(DATE(RIGHT(A10,4),LEFT(A10,FIND("/",A10)-1),MID(A10,FIND("/",A10)+1,FIND("/",A10,FIND("/",A10)+1)-FIND("/",A10)-1)),"yyyy/mm/dd") -> 2024/05/31 | C10: 20241130-2 | D10: 2203-00-000 | E10: Intercompany Payable / 관계사미지급금 | F10: 1Q Interco Billing | G10: 0 | H10: 141245630
A11: 5/31/2024 | B11: =TEXT(DATE(RIGHT(A11,4),LEFT(A11,FIND("/",A11)-1),MID(A11,FIND("/",A11)+1,FIND("/",A11,FIND("/",A11)+1)-FIND("/",A11)-1)),"yyyy/mm/dd") -> 2024/05/31 | C11: 20241130-2 | D11: 2203-00-000 | E11: Intercompany Payable / 관계사미지급금 | F11: 1Q Interco Billing | G11: 141245630 | H11: 0
A12: 7/1/2024 | B12: =TEXT(DATE(RIGHT(A12,4),LEFT(A12,FIND("/",A12)-1),MID(A12,FIND("/",A12)+1,FIND("/",A12,FIND("/",A12)+1)-FIND("/",A12)-1)),"yyyy/mm/dd") -> 2024/07/01 | C12: 20241130-3 | D12: 2203-00-000 | E12: Intercompany Payable / 관계사미지급금 | F12: 2Q Interco Billing | G12: 0 | H12: 117281772
A13: 7/1/2024 | B13: =TEXT(DATE(RIGHT(A13,4),LEFT(A13,FIND("/",A13)-1),MID(A13,FIND("/",A13)+1,FIND("/",A13,FIND("/",A13)+1)-FIND("/",A13)-1)),"yyyy/mm/dd") -> 2024/07/01 | C13: 20241130-3 | D13: 2203-00-000 | E13: Intercompany Payable / 관계사미지급금 | F13: 2Q Interco Billing | G13: 117281772 | H13: 0
... A160: 12/31/2024 | B160: =TEXT(DATE(RIGHT(A160,4),LEFT(A160,FIND("/",A160)-1),MID(A160,FIND("/",A160)+1,FIND("/",A160,FIND("/",A160)+1)-FIND("/",A160)-1)),"yyyy/mm/dd") -> 2024/12/31 | C160: GJ24-0023 | D160: 2202-00-001 | E160: Other payable / 기타미지급금 | F160: Other legal and professional fees / 기타 법률 및 전문 수수료 | G160: 0 | H160: 715000
A161: 12/31/2024 | B161: =TEXT(DATE(RIGHT(A161,4),LEFT(A161,FIND("/",A161)-1),MID(A161,FIND("/",A161)+1,FIND("/",A161,FIND("/",A161)+1)-FIND("/",A161)-1)),"yyyy/mm/dd") -> 2024/12/31 | C161: GJ24-0026 | D161: 5211-00-000 | E161: Organizational expenses / 관리운용비용 | F161: Organizational expenses / 관리운용비용 | G161: 58318120 | H161: 0 | I161: IECKR001
A162: 12/31/2024 | B162: =TEXT(DATE(RIGHT(A162,4),LEFT(A162,FIND("/",A162)-1),MID(A162,FIND("/",A162)+1,FIND("/",A162,FIND("/",A162)+1)-FIND("/",A162)-1)),"yyyy/mm/dd") -> 2024/12/31 | C162: GJ24-0026 | D162: 2202-00-000 | E162: Accrued liabilities / 계약부채 | F162: Organizational expenses / 관리운용비용 | G162: 0 | H162: 58318120 | I162: IECKR001
A163: 12/31/2024 | B163: =TEXT(DATE(RIGHT(A163,4),LEFT(A163,FIND("/",A163)-1),MID(A163,FIND("/",A163)+1,FIND("/",A163,FIND("/",A163)+1)-FIND("/",A163)-1)),"yyyy/mm/dd") -> 2024/12/31 | C163: GJ24-0027 | D163: 2203-00-000 | E163: Intercompany Payable / 관계사미지급금 | F163: Accrued liabilities / 계약부채 | G163: 0 | H163: 147977176 | I163: IECKR001
A164: 12/31/2024 | B164: =TEXT(DATE(RIGHT(A164,4),LEFT(A164,FIND("/",A164)-1),MID(A164,FIND("/",A164)+1,FIND("/",A164,FIND("/",A164)+1)-FIND("/",A164)-1)),"yyyy/mm/dd") -> 2024/12/31 | C164: GJ24-0027 | D164: 2202-00-000 | E164: Accrued liabilities / 계약부채 | F164: Accrued liabilities / 계약부채 | G164: 147977176 | H164: 0 | I164: IECKR001
A165: 12/31/2024 | B165: =TEXT(DATE(RIGHT(A165,4),LEFT(A165,FIND("/",A165)-1),MID(A165,FIND("/",A165)+1,FIND("/",A165,FIND("/",A165)+1)-FIND("/",A165)-1)),"yyyy/mm/dd") -> 2024/12/31 | C165: GJ24-0028 | D165: 2203-00-000 | E165: Intercompany Payable / 관계사미지급금 | F165: Accrued liabilities / 계약부채 | G165: 1 | H165: 0
A166: 12/31/2024 | B166: =TEXT(DATE(RIGHT(A166,4),LEFT(A166,FIND("/",A166)-1),MID(A166,FIND("/",A166)+1,FIND("/",A166,FIND("/",A166)+1)-FIND("/",A166)-1)),"yyyy/mm/dd") -> 2024/12/31 | C166: GJ24-0028 | D166: 2202-00-000 | E166: Accrued liabilities / 계약부채 | F166: Accrued liabilities / 계약부채 | G166: 0 | H166: 1
A167: 12/31/2024 | B167: =TEXT(DATE(RIGHT(A167,4),LEFT(A167,FIND("/",A167)-1),MID(A167,FIND("/",A167)+1,FIND("/",A167,FIND("/",A167)+1)-FIND("/",A167)-1)),"yyyy/mm/dd") -> 2024/12/31 | C167: GJ24-0029 | D167: 7103-00-000 | E167: Other tax expense / 기타 세금과공과 | F167: Close Income Statement | G167: 0 | H167: 4703720
A168: 12/31/2024 | B168: =TEXT(DATE(RIGHT(A168,4),LEFT(A168,FIND("/",A168)-1),MID(A168,FIND("/",A168)+1,FIND("/",A168,FIND("/",A168)+1)-FIND("/",A168)-1)),"yyyy/mm/dd") -> 2024/12/31 | C168: GJ24-0029 | D168: 5719-00-000 | E168: Interest expense - External / 이자비용 - 일반 | F168: Close Income Statement | G168: 0 | H168: 94634669
A169: 12/31/2024 | B169: =TEXT(DATE(RIGHT(A169,4),LEFT(A169,FIND("/",A169)-1),MID(A169,FIND("/",A169)+1,FIND("/",A169,FIND("/",A169)+1)-FIND("/",A169)-1)),"yyyy/mm/dd") -> 2024/12/31 | C169: GJ24-0029 | D169: 5717-00-000 | E169: Interest expense - InterCo / 이자비용 - 회사 간 대출 | F169: Close Income Statement | G169: 0 | H169: 757260510
A170: 12/31/2024 | B170: =TEXT(DATE(RIGHT(A170,4),LEFT(A170,FIND("/",A170)-1),MID(A170,FIND("/",A170)+1,FIND("/",A170,FIND("/",A170)+1)-FIND("/",A170)-1)),"yyyy/mm/dd") -> 2024/12/31 | C170: GJ24-0029 | D170: 5711-00-000 | E170: ROU Lease - Interest expense / 금융리스 - 이자비용 | F170: Close Income Statement | G170: 0 | H170: 8360655
A171: 12/31/2024 | B171: =TEXT(DATE(RIGHT(A171,4),LEFT(A171,FIND("/",A171)-1),MID(A171,FIND("/",A171)+1,FIND("/",A171,FIND("/",A171)+1)-FIND("/",A171)-1)),"yyyy/mm/dd") -> 2024/12/31 | C171: GJ24-0029 | D171: 5612-00-000 | E171: Interest income - bank / 이자수익 - 은행 | F171: Close Income Statement | G171: 754509 | H171: 0
A172: 12/31/2024 | B172: =TEXT(DATE(RIGHT(A172,4),LEFT(A172,FIND("/",A172)-1),MID(A172,FIND("/",A172)+1,FIND("/",A172,FIND("/",A172)+1)-FIND("/",A172)-1)),"yyyy/mm/dd") -> 2024/12/31 | C172: GJ24-0029 | D172: 5601-00-000 | E172: Other expenses / 잡손실 | F172: Close Income Statement | G172: 0 | H172: 797033
A173: 12/31/2024 | B173: =TEXT(DATE(RIGHT(A173,4),LEFT(A173,FIND("/",A173)-1),MID(A173,FIND("/",A173)+1,FIND("/",A173,FIND("/",A173)+1)-FIND("/",A173)-1)),"yyyy/mm/dd") -> 2024/12/31 | C173: GJ24-0029 | D173: 5342-00-000 | E173: FX - realized loss - others / 외환차손 | F173: Close Income Statement | G173: 0 | H173: 72876
A174: 12/31/2024 | B174: =TEXT(DATE(RIGHT(A174,4),LEFT(A174,FIND("/",A174)-1),MID(A174,FIND("/",A174)+1,FIND("/",A174,FIND("/",A174)+1)-FIND("/",A174)-1)),"yyyy/mm/dd") -> 2024/12/31 | C174: GJ24-0029 | D174: 5318-00-000 | E174: Social events / 행사비 | F174: Close Income Statement | G174: 0 | H174: 2000000
A175: 12/31/2024 | B175: =TEXT(DATE(RIGHT(A175,4),LEFT(A175,FIND("/",A175)-1),MID(A175,FIND("/",A175)+1,FIND("/",A175,FIND("/",A175)+1)-FIND("/",A175)-1)),"yyyy/mm/dd") -> 2024/12/31 | C175: GJ24-0029 | D175: 5301-00-000 | E175: Bank charges / 은행 수수료 | F175: Close Income Statement | G175: 0 | H175: 59500
A176: 12/31/2024 | B176: =TEXT(DATE(RIGHT(A176,4),LEFT(A176,FIND("/",A176)-1),MID(A176,FIND("/",A176)+1,FIND("/",A176,FIND("/",A176)+1)-FIND("/",A176)-1)),"yyyy/mm/dd") -> 2024/12/31 | C176: GJ24-0029 | D176: 5291-00-000 | E176: Telecommunication expenses / 통신비 | F176: Close Income Statement | G176: 0 | H176: 409550
... A180: 12/31/2024 | B180: =TEXT(DATE(RIGHT(A180,4),LEFT(A180,FIND("/",A180)-1),MID(A180,FIND("/",A180)+1,FIND("/",A180,FIND("/",A180)+1)-FIND("/",A180)-1)),"yyyy/mm/dd") -> 2024/12/31 | C180: GJ24-0029 | D180: 5227-SG-002 | E180: Insurance - Employee / 고용 산재보험료 | F180: Close Income Statement | G180: 0 | H180: 436030
A181: 12/31/2024 | B181: =TEXT(DATE(RIGHT(A181,4),LEFT(A181,FIND("/",A181)-1),MID(A181,FIND("/",A181)+1,FIND("/",A181,FIND("/",A181)+1)-FIND("/",A181)-1)),"yyyy/mm/dd") -> 2024/12/31 | C181: GJ24-0029 | D181: 5211-00-000 | E181: Organizational expenses / 관리운용비용 | F181: Close Income Statement | G181: 0 | H181: 58318120 | I181: IECKR001
A182: 12/31/2024 | B182: =TEXT(DATE(RIGHT(A182,4),LEFT(A182,FIND("/",A182)-1),MID(A182,FIND("/",A182)+1,FIND("/",A182,FIND("/",A182)+1)-FIND("/",A182)-1)),"yyyy/mm/dd") -> 2024/12/31 | C182: GJ24-0029 | D182: 5211-00-000 | E182: Organizational expenses / 관리운용비용 | F182: Close Income Statement | G182: 0 | H182: 415073691
A183: 12/31/2024 | B183: =TEXT(DATE(RIGHT(A183,4),LEFT(A183,FIND("/",A183)-1),MID(A183,FIND("/",A183)+1,FIND("/",A183,FIND("/",A183)+1)-FIND("/",A183)-1)),"yyyy/mm/dd") -> 2024/12/31 | C183: GJ24-0029 | D183: 5101-00-000 | E183: Management fee expense / 관리 수수료 비용 | F183: Close Income Statement | G183: 0 | H183: 407440
A184: 12/31/2024 | B184: =TEXT(DATE(RIGHT(A184,4),LEFT(A184,FIND("/",A184)-1),MID(A184,FIND("/",A184)+1,FIND("/",A184,FIND("/",A184)+1)-FIND("/",A184)-1)),"yyyy/mm/dd") -> 2024/12/31 | C184: GJ24-0029 | D184: 4401-00-000 | E184: Other income / 잡이익 | F184: Close Income Statement | G184: 8270 | H184: 0
A185: 12/31/2024 | B185: =TEXT(DATE(RIGHT(A185,4),LEFT(A185,FIND("/",A185)-1),MID(A185,FIND("/",A185)+1,FIND("/",A185,FIND("/",A185)+1)-FIND("/",A185)-1)),"yyyy/mm/dd") -> 2024/12/31 | C185: GJ24-0029 | D185: 3401-00-000 | E185: Retained earnings / 이익 잉여금 | F185: Close Income Statement | G185: 1362082031 | H185: 0
A186: 1/2/2025 | B186: =TEXT(DATE(RIGHT(A186,4),LEFT(A186,FIND("/",A186)-1),MID(A186,FIND("/",A186)+1,FIND("/",A186,FIND("/",A186)+1)-FIND("/",A186)-1)),"yyyy/mm/dd") -> 2025/01/02 | C186: GJ25-0001 | D186: 5301-00-000 | E186: Bank charges / 은행 수수료 | F186: (HTX)_공인인증서(은행/보험용) / 은행 수수료 | G186: 4000 | H186: 0
A187: 1/2/2025 | B187: =TEXT(DATE(RIGHT(A187,4),LEFT(A187,FIND("/",A187)-1),MID(A187,FIND("/",A187)+1,FIND("/",A187,FIND("/",A187)+1)-FIND("/",A187)-1)),"yyyy/mm/dd") -> 2025/01/02 | C187: GJ25-0001 | D187: 2407-00-000 | E187: GST/VAT receivable / 부가세대급금 | F187: (HTX)_공인인증서(은행/보험용) / 부가세대급금 | G187: 400 | H187: 0
A188: 1/2/2025 | B188: =TEXT(DATE(RIGHT(A188,4),LEFT(A188,FIND("/",A188)-1),MID(A188,FIND("/",A188)+1,FIND("/",A188,FIND("/",A188)+1)-FIND("/",A188)-1)),"yyyy/mm/dd") -> 2025/01/02 | C188: GJ25-0001 | D188: 2202-00-001 | E188: Other payable / 기타미지급금 | F188: (HTX)_공인인증서(은행/보험용) / 기타미지급금 | G188: 0 | H188: 4400
A189: 1/2/2025 | B189: =TEXT(DATE(RIGHT(A189,4),LEFT(A189,FIND("/",A189)-1),MID(A189,FIND("/",A189)+1,FIND("/",A189,FIND("/",A189)+1)-FIND("/",A189)-1)),"yyyy/mm/dd") -> 2025/01/02 | C189: GJ25-0002 | D189: 5301-00-000 | E189: Bank charges / 은행 수수료 | F189: [KR Inv_202412] VJIPYON02_Kummyung_Registration fee for debt to equity_KRW 23487000 _ 은행 수수료 | G189: 500 | H189: 0
A190: 1/2/2025 | B190: =TEXT(DATE(RIGHT(A190,4),LEFT(A190,FIND("/",A190)-1),MID(A190,FIND("/",A190)+1,FIND("/",A190,FIND("/",A190)+1)-FIND("/",A190)-1)),"yyyy/mm/dd") -> 2025/01/02 | C190: GJ25-0002 | D190: 2202-00-001 | E190: Other payable / 기타미지급금 | F190: [KR Inv_202412] VJIPYON02_Kummyung_Registration fee for debt to equity_KRW 23487000 _ 기타미지급금 | G190: 23487000 | H190: 0
A191: 1/2/2025 | B191: =TEXT(DATE(RIGHT(A191,4),LEFT(A191,FIND("/",A191)-1),MID(A191,FIND("/",A191)+1,FIND("/",A191,FIND("/",A191)+1)-FIND("/",A191)-1)),"yyyy/mm/dd") -> 2025/01/02 | C191: GJ25-0002 | D191: 1112-KR-001 | E191: Cash - KRW (HANA) / 현금 - 원 (HANA) | F191: [KR Inv_202412] VJIPYON02_Kummyung_Registration fee for debt to equity_KRW 23487000 _ 현금 - 원 (HANA) | G191: 0 | H191: 23487500
A192: 1/2/2025 | B192: =TEXT(DATE(RIGHT(A192,4),LEFT(A192,FIND("/",A192)-1),MID(A192,FIND("/",A192)+1,FIND("/",A192,FIND("/",A192)+1)-FIND("/",A192)-1)),"yyyy/mm/dd") -> 2025/01/02 | C192: GJ25-0003 | D192: 5301-00-000 | E192: Bank charges / 은행 수수료 | F192: [KR Inv_202411] VNEULSA01_Kummyung_Real estate transaction amount_KRW 12000000 _ 은행 수수료 | G192: 500 | H192: 0
A193: 1/2/2025 | B193: =TEXT(DATE(RIGHT(A193,4),LEFT(A193,FIND("/",A193)-1),MID(A193,FIND("/",A193)+1,FIND("/",A193,FIND("/",A193)+1)-FIND("/",A193)-1)),"yyyy/mm/dd") -> 2025/01/02 | C193: GJ25-0003 | D193: 2202-00-001 | E193: Other payable / 기타미지급금 | F193: [KR Inv_202411] VNEULSA01_Kummyung_Real estate transaction amount_KRW 12000000 _ 기타미지급금 | G193: 12000000 | H193: 0
... A242: 1/31/2025 | B242: =TEXT(DATE(RIGHT(A242,4),LEFT(A242,FIND("/",A242)-1),MID(A242,FIND("/",A242)+1,FIND("/",A242,FIND("/",A242)+1)-FIND("/",A242)-1)),"yyyy/mm/dd") -> 2025/01/31 | C242: GJ25-0075 | D242: 2203-00-000 | E242: Intercompany Payable / 관계사미지급금 | F242: Intercompany Payable / 관계사미지급금 | G242: 147977175 | H242: 0
A243: 2/3/2025 | B243: =TEXT(DATE(RIGHT(A243,4),LEFT(A243,FIND("/",A243)-1),MID(A243,FIND("/",A243)+1,FIND("/",A243,FIND("/",A243)+1)-FIND("/",A243)-1)),"yyyy/mm/dd") -> 2025/02/03 | C243: GJ25-0019 | D243: 5106-00-000 | E243: Shared service charges / 공유 서비스 비용 | F243: IECSG001-INV25-0041(SGD 2413.07*@ 1,073.60)_ECSS PL Equis Central Service Singapore Pte. Ltd. | G243: 2767811966 | H243: 0 | I243: IECSG001
A244: 2/3/2025 | B244: =TEXT(DATE(RIGHT(A244,4),LEFT(A244,FIND("/",A244)-1),MID(A244,FIND("/",A244)+1,FIND("/",A244,FIND("/",A244)+1)-FIND("/",A244)-1)),"yyyy/mm/dd") -> 2025/02/03 | C244: GJ25-0019 | D244: 2203-00-000 | E244: Intercompany Payable / 관계사미지급금 | F244: IECSG001-INV25-0041(SGD 2413.07*@ 1,073.60)_ECSS PL Equis Central Service Singapore Pte. Ltd. | G244: 0 | H244: 2767811966 | I244: IECSG001
A245: 2/3/2025 | B245: =TEXT(DATE(RIGHT(A245,4),LEFT(A245,FIND("/",A245)-1),MID(A245,FIND("/",A245)+1,FIND("/",A245,FIND("/",A245)+1)-FIND("/",A245)-1)),"yyyy/mm/dd") -> 2025/02/03 | C245: GJ25-0047 | D245: 5106-00-000 | E245: Shared service charges / 공유 서비스 비용 | F245: IECSG001-INV25-0041(SGD 2413.07*@ 1,073.60)_ECSS PL Equis Central Service Singapore Pte. Ltd. | G245: 0 | H245: 2767811966 | I245: IECSG001
A246: 2/3/2025 | B246: =TEXT(DATE(RIGHT(A246,4),LEFT(A246,FIND("/",A246)-1),MID(A246,FIND("/",A246)+1,FIND("/",A246,FIND("/",A246)+1)-FIND("/",A246)-1)),"yyyy/mm/dd") -> 2025/02/03 | C246: GJ25-0047 | D246: 2203-00-000 | E246: Intercompany Payable / 관계사미지급금 | F246: IECSG001-INV25-0041(SGD 2413.07*@ 1,073.60)_ECSS PL Equis Central Service Singapore Pte. Ltd. | G246: 2767811966 | H246: 0 | I246: IECSG001
A247: 2/3/2025 | B247: =TEXT(DATE(RIGHT(A247,4),LEFT(A247,FIND("/",A247)-1),MID(A247,FIND("/",A247)+1,FIND("/",A247,FIND("/",A247)+1)-FIND("/",A247)-1)),"yyyy/mm/dd") -> 2025/02/03 | C247: GJ25-0048 | D247: 5106-00-000 | E247: Shared service charges / 공유 서비스 비용 | F247: Mgmt & Shared Service Fee Q4 2024-Keummyeong Co. Ltd_ECSS PL Equis Central Service Singapore Pte. Lt | G247: 2590672 | H247: 0 | I247: IECSG001
A248: 2/3/2025 | B248: =TEXT(DATE(RIGHT(A248,4),LEFT(A248,FIND("/",A248)-1),MID(A248,FIND("/",A248)+1,FIND("/",A248,FIND("/",A248)+1)-FIND("/",A248)-1)),"yyyy/mm/dd") -> 2025/02/03 | C248: GJ25-0048 | D248: 2203-00-000 | E248: Intercompany Payable / 관계사미지급금 | F248: IECSG001-INV25-0041(SGD 2413.07*@ 1,073.60)_ECSS PL Equis Central Service Singapore Pte. Ltd. | G248: 0 | H248: 2590672 | I248: IECSG001
A249: 2/6/2025 | B249: =TEXT(DATE(RIGHT(A249,4),LEFT(A249,FIND("/",A249)-1),MID(A249,FIND("/",A249)+1,FIND("/",A249,FIND("/",A249)+1)-FIND("/",A249)-1)),"yyyy/mm/dd") -> 2025/02/06 | C249: GJ25-0020 | D249: 5301-00-000 | E249: Bank charges / 은행 수수료 | F249: 공인인증서(은행/보험용)_HANA BANK (주)하나은행_HANA BANK (주)하나은행 | G249: 4000 | H249: 0 | I249: VHANABA01
A250: 2/6/2025 | B250: =TEXT(DATE(RIGHT(A250,4),LEFT(A250,FIND("/",A250)-1),MID(A250,FIND("/",A250)+1,FIND("/",A250,FIND("/",A250)+1)-FIND("/",A250)-1)),"yyyy/mm/dd") -> 2025/02/06 | C250: GJ25-0020 | D250: 2407-00-000 | E250: GST/VAT receivable / 부가세대급금 | F250: 공인인증서(은행/보험용)_HANA BANK (주)하나은행_HANA BANK (주)하나은행 | G250: 400 | H250: 0 | I250: VHANABA01
A251: 2/6/2025 | B251: =TEXT(DATE(RIGHT(A251,4),LEFT(A251,FIND("/",A251)-1),MID(A251,FIND("/",A251)+1,FIND("/",A251,FIND("/",A251)+1)-FIND("/",A251)-1)),"yyyy/mm/dd") -> 2025/02/06 | C251: GJ25-0020 | D251: 2202-00-001 | E251: Other payable / 기타미지급금 | F251: 공인인증서(은행/보험용)_HANA BANK (주)하나은행_HANA BANK (주)하나은행 | G251: 0 | H251: 4400 | I251: VHANABA01
A252: 2/6/2025 | B252: =TEXT(DATE(RIGHT(A252,4),LEFT(A252,FIND("/",A252)-1),MID(A252,FIND("/",A252)+1,FIND("/",A252,FIND("/",A252)+1)-FIND("/",A252)-1)),"yyyy/mm/dd") -> 2025/02/06 | C252: GJ25-0021 | D252: 2202-00-001 | E252: Other payable / 기타미지급금 | F252: Issuance Fee payment_HANA BANK (주)하나은행 | G252: 4400 | H252: 0 | I252: VHANABA01
A253: 2/6/2025 | B253: =TEXT(DATE(RIGHT(A253,4),LEFT(A253,FIND("/",A253)-1),MID(A253,FIND("/",A253)+1,FIND("/",A253,FIND("/",A253)+1)-FIND("/",A253)-1)),"yyyy/mm/dd") -> 2025/02/06 | C253: GJ25-0021 | D253: 1112-KR-001 | E253: Cash - KRW (HANA) / 현금 - 원 (HANA) | F253: Issuance Fee payment_HANA BANK (주)하나은행 | G253: 0 | H253: 4400 | I253: VHANABA01
A254: 2/10/2025 | B254: =TEXT(DATE(RIGHT(A254,4),LEFT(A254,FIND("/",A254)-1),MID(A254,FIND("/",A254)+1,FIND("/",A254,FIND("/",A254)+1)-FIND("/",A254)-1)),"yyyy/mm/dd") -> 2025/02/10 | C254: GJ25-0022 | D254: 5101-00-000 | E254: Management fee expense / 관리 수수료 비용 | F254: 관리비_세정아울렛 관리단_세정아울렛 관리단 | G254: 332530 | H254: 0 | I254: VSEJUNG01
... A312: 2/28/2025 | B312: =TEXT(DATE(RIGHT(A312,4),LEFT(A312,FIND("/",A312)-1),MID(A312,FIND("/",A312)+1,FIND("/",A312,FIND("/",A312)+1)-FIND("/",A312)-1)),"yyyy/mm/dd") -> 2025/02/28 | C312: GJ25-0046 | D312: 1232-00-000 | E312: Prepaid expenses / 선급비용 | F312: Office rent_유한회사 삼형 | G312: 0 | H312: 1000000 | I312: VSAMHYO01
A313: 3/6/2025 | B313: =TEXT(DATE(RIGHT(A313,4),LEFT(A313,FIND("/",A313)-1),MID(A313,FIND("/",A313)+1,FIND("/",A313,FIND("/",A313)+1)-FIND("/",A313)-1)),"yyyy/mm/dd") -> 2025/03/06 | C313: GJ25-0049 | D313: 5301-00-000 | E313: Bank charges / 은행 수수료 | F313: 공인인증서(은행/보험용)_HANA BANK (주)하나은행 | G313: 4000 | H313: 0
A314: 3/6/2025 | B314: =TEXT(DATE(RIGHT(A314,4),LEFT(A314,FIND("/",A314)-1),MID(A314,FIND("/",A314)+1,FIND("/",A314,FIND("/",A314)+1)-FIND("/",A314)-1)),"yyyy/mm/dd") -> 2025/03/06 | C314: GJ25-0049 | D314: 2407-00-000 | E314: GST/VAT receivable / 부가세대급금 | F314: 공인인증서(은행/보험용)_HANA BANK (주)하나은행 | G314: 400 | H314: 0
A315: 3/6/2025 | B315: =TEXT(DATE(RIGHT(A315,4),LEFT(A315,FIND("/",A315)-1),MID(A315,FIND("/",A315)+1,FIND("/",A315,FIND("/",A315)+1)-FIND("/",A315)-1)),"yyyy/mm/dd") -> 2025/03/06 | C315: GJ25-0049 | D315: 2202-00-001 | E315: Other payable / 기타미지급금 | F315: 공인인증서(은행/보험용)_HANA BANK (주)하나은행 | G315: 0 | H315: 4400
A316: 3/6/2025 | B316: =TEXT(DATE(RIGHT(A316,4),LEFT(A316,FIND("/",A316)-1),MID(A316,FIND("/",A316)+1,FIND("/",A316,FIND("/",A316)+1)-FIND("/",A316)-1)),"yyyy/mm/dd") -> 2025/03/06 | C316: GJ25-0055 | D316: 2202-00-001 | E316: Other payable / 기타미지급금 | F316: Issuance Fee payment | G316: 4400 | H316: 0 | I316: VHANABA01
A317: 3/6/2025 | B317: =TEXT(DATE(RIGHT(A317,4),LEFT(A317,FIND("/",A317)-1),MID(A317,FIND("/",A317)+1,FIND("/",A317,FIND("/",A317)+1)-FIND("/",A317)-1)),"yyyy/mm/dd") -> 2025/03/06 | C317: GJ25-0055 | D317: 1112-KR-001 | E317: Cash - KRW (HANA) / 현금 - 원 (HANA) | F317: Issuance Fee payment | G317: 0 | H317: 4400 | I317: VHANABA01
A318: 3/10/2025 | B318: =TEXT(DATE(RIGHT(A318,4),LEFT(A318,FIND("/",A318)-1),MID(A318,FIND("/",A318)+1,FIND("/",A318,FIND("/",A318)+1)-FIND("/",A318)-1)),"yyyy/mm/dd") -> 2025/03/10 | C318: GJ25-0050 | D318: 5101-00-000 | E318: Management fee expense / 관리 수수료 비용 | F318: 관리비_세정아울렛 관리단 | G318: 383018 | H318: 0
A319: 3/10/2025 | B319: =TEXT(DATE(RIGHT(A319,4),LEFT(A319,FIND("/",A319)-1),MID(A319,FIND("/",A319)+1,FIND("/",A319,FIND("/",A319)+1)-FIND("/",A319)-1)),"yyyy/mm/dd") -> 2025/03/10 | C319: GJ25-0050 | D319: 2407-00-000 | E319: GST/VAT receivable / 부가세대급금 | F319: 관리비_세정아울렛 관리단 | G319: 38302 | H319: 0
A320: 3/10/2025 | B320: =TEXT(DATE(RIGHT(A320,4),LEFT(A320,FIND("/",A320)-1),MID(A320,FIND("/",A320)+1,FIND("/",A320,FIND("/",A320)+1)-FIND("/",A320)-1)),"yyyy/mm/dd") -> 2025/03/10 | C320: GJ25-0050 | D320: 2202-00-001 | E320: Other payable / 기타미지급금 | F320: 관리비_세정아울렛 관리단 | G320: 0 | H320: 421320
A321: 3/10/2025 | B321: =TEXT(DATE(RIGHT(A321,4),LEFT(A321,FIND("/",A321)-1),MID(A321,FIND("/",A321)+1,FIND("/",A321,FIND("/",A321)+1)-FIND("/",A321)-1)),"yyyy/mm/dd") -> 2025/03/10 | C321: GJ25-0069 | D321: 5101-00-000 | E321: Management fee expense / 관리 수수료 비용 | F321: 수정분개 | G321: 0 | H321: 383018 | I321: VSEJUNG01
A322: 3/10/2025 | B322: =TEXT(DATE(RIGHT(A322,4),LEFT(A322,FIND("/",A322)-1),MID(A322,FIND("/",A322)+1,FIND("/",A322,FIND("/",A322)+1)-FIND("/",A322)-1)),"yyyy/mm/dd") -> 2025/03/10 | C322: GJ25-0069 | D322: 2407-00-000 | E322: GST/VAT receivable / 부가세대급금 | F322: 수정분개 | G322: 0 | H322: 38302 | I322: VSEJUNG01
A323: 3/10/2025 | B323: =TEXT(DATE(RIGHT(A323,4),LEFT(A323,FIND("/",A323)-1),MID(A323,FIND("/",A323)+1,FIND("/",A323,FIND("/",A323)+1)-FIND("/",A323)-1)),"yyyy/mm/dd") -> 2025/03/10 | C323: GJ25-0069 | D323: 2202-00-001 | E323: Other payable / 기타미지급금 | F323: 수정분개 | G323: 421320 | H323: 0 | I323: VSEJUNG01
A324: 3/10/2025 | B324: =TEXT(DATE(RIGHT(A324,4),LEFT(A324,FIND("/",A324)-1),MID(A324,FIND("/",A324)+1,FIND("/",A324,FIND("/",A324)+1)-FIND("/",A324)-1)),"yyyy/mm/dd") -> 2025/03/10 | C324: GJ25-0070 | D324: 5101-00-000 | E324: Management fee expense / 관리 수수료 비용 | F324: 관리비_세정아울렛 관리단 | G324: 383020 | H324: 0 | I324: VSEJUNG01
A325: 3/10/2025 | B325: =TEXT(DATE(RIGHT(A325,4),LEFT(A325,FIND("/",A325)-1),MID(A325,FIND("/",A325)+1,FIND("/",A325,FIND("/",A325)+1)-FIND("/",A325)-1)),"yyyy/mm/dd") -> 2025/03/10 | C325: GJ25-0070 | D325: 2407-00-000 | E325: GST/VAT receivable / 부가세대급금 | F325: 관리비_세정아울렛 관리단 | G325: 38300 | H325: 0 | I325: VSEJUNG01
A326: 3/10/2025 | B326: =TEXT(DATE(RIGHT(A326,4),LEFT(A326,FIND("/",A326)-1),MID(A326,FIND("/",A326)+1,FIND("/",A326,FIND("/",A326)+1)-FIND("/",A326)-1)),"yyyy/mm/dd") -> 2025/03/10 | C326: GJ25-0070 | D326: 2202-00-001 | E326: Other payable / 기타미지급금 | F326: 관리비_세정아울렛 관리단 | G326: 0 | H326: 421320 | I326: VSEJUNG01
A327: 3/13/2025 | B327: =TEXT(DATE(RIGHT(A327,4),LEFT(A327,FIND("/",A327)-1),MID(A327,FIND("/",A327)+1,FIND("/",A327,FIND("/",A327)+1)-FIND("/",A327)-1)),"yyyy/mm/dd") -> 2025/03/13 | C327: GJ25-0051 | D327: 5263-00-000 | E327: Advertising / 광고비용 | F327: 신안군기념품(타올)구입_유한회사 파란디 | G327: 2727273 | H327: 0 | I327: VPRDLTD01
A328: 3/13/2025 | B328: =TEXT(DATE(RIGHT(A328,4),LEFT(A328,FIND("/",A328)-1),MID(A328,FIND("/",A328)+1,FIND("/",A328,FIND("/",A328)+1)-FIND("/",A328)-1)),"yyyy/mm/dd") -> 2025/03/13 | C328: GJ25-0051 | D328: 2407-00-000 | E328: GST/VAT receivable / 부가세대급금 | F328: 신안군기념품(타올)구입_유한회사 파란디 | G328: 272727 | H328: 0 | I328: VPRDLTD01
A329: 3/13/2025 | B329: =TEXT(DATE(RIGHT(A329,4),LEFT(A329,FIND("/",A329)-1),MID(A329,FIND("/",A329)+1,FIND("/",A329,FIND("/",A329)+1)-FIND("/",A329)-1)),"yyyy/mm/dd") -> 2025/03/13 | C329: GJ25-0051 | D329: 2202-00-001 | E329: Other payable / 기타미지급금 | F329: 신안군기념품(타올)구입_유한회사 파란디 | G329: 0 | H329: 3000000 | I329: VPRDLTD01
A330: 3/15/2025 | B330: =TEXT(DATE(RIGHT(A330,4),LEFT(A330,FIND("/",A330)-1),MID(A330,FIND("/",A330)+1,FIND("/",A330,FIND("/",A330)+1)-FIND("/",A330)-1)),"yyyy/mm/dd") -> 2025/03/15 | C330: GJ25-0056 | D330: 5612-00-000 | E330: Interest income - bank / 이자수익 - 은행 | F330: bank interest income(예금이자 201,741 소득세 28,240 지방소득세 2,820) | G330: 0 | H330: 201741 | I330: VHANABA01
A331: 3/15/2025 | B331: =TEXT(DATE(RIGHT(A331,4),LEFT(A331,FIND("/",A331)-1),MID(A331,FIND("/",A331)+1,FIND("/",A331,FIND("/",A331)+1)-FIND("/",A331)-1)),"yyyy/mm/dd") -> 2025/03/15 | C331: GJ25-0056 | D331: 1212-00-000 | E331: Income tax receivables / 선납세금 | F331: bank interest income(예금이자 201,741 소득세 28,240 지방소득세 2,820) | G331: 2820 | H331: 0
A332: 3/15/2025 | B332: =TEXT(DATE(RIGHT(A332,4),LEFT(A332,FIND("/",A332)-1),MID(A332,FIND("/",A332)+1,FIND("/",A332,FIND("/",A332)+1)-FIND("/",A332)-1)),"yyyy/mm/dd") -> 2025/03/15 | C332: GJ25-0056 | D332: 1212-00-000 | E332: Income tax receivables / 선납세금 | F332: bank interest income(예금이자 201,741 소득세 28,240 지방소득세 2,820) | G332: 28240 | H332: 0
A333: 3/15/2025 | B333: =TEXT(DATE(RIGHT(A333,4),LEFT(A333,FIND("/",A333)-1),MID(A333,FIND("/",A333)+1,FIND("/",A333,FIND("/",A333)+1)-FIND("/",A333)-1)),"yyyy/mm/dd") -> 2025/03/15 | C333: GJ25-0056 | D333: 1112-KR-001 | E333: Cash - KRW (HANA) / 현금 - 원 (HANA) | F333: bank interest income(예금이자 201,741 소득세 28,240 지방소득세 2,820) | G333: 170681 | H333: 0 | I333: VHANABA01
A334: 3/17/2025 | B334: =TEXT(DATE(RIGHT(A334,4),LEFT(A334,FIND("/",A334)-1),MID(A334,FIND("/",A334)+1,FIND("/",A334,FIND("/",A334)+1)-FIND("/",A334)-1)),"yyyy/mm/dd") -> 2025/03/17 | C334: GJ25-0052 | D334: 5263-00-000 | E334: Advertising / 광고비용 | F334: 떡류_현창떡집 | G334: 822727 | H334: 0 | I334: VHYCHNG01
A335: 3/17/2025 | B335: =TEXT(DATE(RIGHT(A335,4),LEFT(A335,FIND("/",A335)-1),MID(A335,FIND("/",A335)+1,FIND("/",A335,FIND("/",A335)+1)-FIND("/",A335)-1)),"yyyy/mm/dd") -> 2025/03/17 | C335: GJ25-0052 | D335: 2407-00-000 | E335: GST/VAT receivable / 부가세대급금 | F335: 떡류_현창떡집 | G335: 82273 | H335: 0 | I335: VHYCHNG01
A336: 3/17/2025 | B336: =TEXT(DATE(RIGHT(A336,4),LEFT(A336,FIND("/",A336)-1),MID(A336,FIND("/",A336)+1,FIND("/",A336,FIND("/",A336)+1)-FIND("/",A336)-1)),"yyyy/mm/dd") -> 2025/03/17 | C336: GJ25-0052 | D336: 2202-00-001 | E336: Other payable / 기타미지급금 | F336: 떡류_현창떡집 | G336: 0 | H336: 905000 | I336: VHYCHNG01
A337: 3/20/2025 | B337: =TEXT(DATE(RIGHT(A337,4),LEFT(A337,FIND("/",A337)-1),MID(A337,FIND("/",A337)+1,FIND("/",A337,FIND("/",A337)+1)-FIND("/",A337)-1)),"yyyy/mm/dd") -> 2025/03/20 | C337: GJ25-0057 | D337: 2202-00-001 | E337: Other payable / 기타미지급금 | F337: [KR Inv_202501] VKPMCOR01_KPMG Acct Service for Dec'24_KRW 31141000 | G337: 715000 | H337: 0 | I337: VKPMCOR01
A338: 3/20/2025 | B338: =TEXT(DATE(RIGHT(A338,4),LEFT(A338,FIND("/",A338)-1),MID(A338,FIND("/",A338)+1,FIND("/",A338,FIND("/",A338)+1)-FIND("/",A338)-1)),"yyyy/mm/dd") -> 2025/03/20 | C338: GJ25-0057 | D338: 1112-KR-001 | E338: Cash - KRW (HANA) / 현금 - 원 (HANA) | F338: [KR Inv_202501] VKPMCOR01_KPMG Acct Service for Dec'24_KRW 31141000 | G338: 0 | H338: 715000 | I338: VKPMCOR01
A339: 3/20/2025 | B339: =TEXT(DATE(RIGHT(A339,4),LEFT(A339,FIND("/",A339)-1),MID(A339,FIND("/",A339)+1,FIND("/",A339,FIND("/",A339)+1)-FIND("/",A339)-1)),"yyyy/mm/dd") -> 2025/03/20 | C339: GJ25-0058 | D339: 2202-00-001 | E339: Other payable / 기타미지급금 | F339: [KR Inv_202503] VKPMCOR01_KPMG Acct Service for Jan'24_KRW 73372750 | G339: 1540000 | H339: 0 | I339: VKPMCOR01
A340: 3/20/2025 | B340: =TEXT(DATE(RIGHT(A340,4),LEFT(A340,FIND("/",A340)-1),MID(A340,FIND("/",A340)+1,FIND("/",A340,FIND("/",A340)+1)-FIND("/",A340)-1)),"yyyy/mm/dd") -> 2025/03/20 | C340: GJ25-0058 | D340: 1112-KR-001 | E340: Cash - KRW (HANA) / 현금 - 원 (HANA) | F340: [KR Inv_202503] VKPMCOR01_KPMG Acct Service for Jan'24_KRW 73372750 | G340: 0 | H340: 1540000 | I340: VKPMCOR01
A341: 3/20/2025 | B341: =TEXT(DATE(RIGHT(A341,4),LEFT(A341,FIND("/",A341)-1),MID(A341,FIND("/",A341)+1,FIND("/",A341,FIND("/",A341)+1)-FIND("/",A341)-1)),"yyyy/mm/dd") -> 2025/03/20 | C341: GJ25-0059 | D341: 2202-00-001 | E341: Other payable / 기타미지급금 | F341: [KR Inv_202503] VSEJUNG01_Kummyung office maintenance fee_KRW 439,610 | G341: 439610 | H341: 0 | I341: VSEJUNG01
A342: 3/20/2025 | B342: =TEXT(DATE(RIGHT(A342,4),LEFT(A342,FIND("/",A342)-1),MID(A342,FIND("/",A342)+1,FIND("/",A342,FIND("/",A342)+1)-FIND("/",A342)-1)),"yyyy/mm/dd") -> 2025/03/20 | C342: GJ25-0059 | D342: 1112-KR-001 | E342: Cash - KRW (HANA) / 현금 - 원 (HANA) | F342: [KR Inv_202503] VSEJUNG01_Kummyung office maintenance fee_KRW 439,610 | G342: 0 | H342: 439610 | I342: VSEJUNG01
A343: 3/21/2025 | B343: =TEXT(DATE(RIGHT(A343,4),LEFT(A343,FIND("/",A343)-1),MID(A343,FIND("/",A343)+1,FIND("/",A343,FIND("/",A343)+1)-FIND("/",A343)-1)),"yyyy/mm/dd") -> 2025/03/21 | C343: GJ25-0053 | D343: 2202-00-001 | E343: Other payable / 기타미지급금 | F343: 소유권이전 (분매리134-249외 4필지, 총 2100평)_김윤석 법무사 | G343: 0 | H343: 330000 | I343: VKIMYUN01
A344: 3/21/2025 | B344: =TEXT(DATE(RIGHT(A344,4),LEFT(A344,FIND("/",A344)-1),MID(A344,FIND("/",A344)+1,FIND("/",A344,FIND("/",A344)+1)-FIND("/",A344)-1)),"yyyy/mm/dd") -> 2025/03/21 | C344: GJ25-0053 | D344: 1712-00-000 | E344: Leasehold land / 토지 | F344: VAT_소유권이전 (분매리134-249외 4필지, 총 2100평)_김윤석 법무사 | G344: 30000 | H344: 0 | I344: VKIMYUN01
... A380: 4/9/2025 | B380: =TEXT(DATE(RIGHT(A380,4),LEFT(A380,FIND("/",A380)-1),MID(A380,FIND("/",A380)+1,FIND("/",A380,FIND("/",A380)+1)-FIND("/",A380)-1)),"yyyy/mm/dd") -> 2025/04/09 | C380: 4 | D380: 5101-00-000 | E380: Management fee expense / 관리 수수료 비용 | F380: 관리비_세정아울렛 관리단 | G380: 0 | H380: 383018 | I380: VSEJUNG01
A381: 4/9/2025 | B381: =TEXT(DATE(RIGHT(A381,4),LEFT(A381,FIND("/",A381)-1),MID(A381,FIND("/",A381)+1,FIND("/",A381,FIND("/",A381)+1)-FIND("/",A381)-1)),"yyyy/mm/dd") -> 2025/04/09 | C381: 4 | D381: 5101-00-000 | E381: Management fee expense / 관리 수수료 비용 | F381: 관리비_세정아울렛 관리단 | G381: 383018 | H381: 0
A382: 4/9/2025 | B382: =TEXT(DATE(RIGHT(A382,4),LEFT(A382,FIND("/",A382)-1),MID(A382,FIND("/",A382)+1,FIND("/",A382,FIND("/",A382)+1)-FIND("/",A382)-1)),"yyyy/mm/dd") -> 2025/04/09 | C382: 4 | D382: 2407-00-000 | E382: GST/VAT receivable / 부가세대급금 | F382: 관리비_세정아울렛 관리단 | G382: 34775 | H382: 0 | I382: VSEJUNG01
A383: 4/9/2025 | B383: =TEXT(DATE(RIGHT(A383,4),LEFT(A383,FIND("/",A383)-1),MID(A383,FIND("/",A383)+1,FIND("/",A383,FIND("/",A383)+1)-FIND("/",A383)-1)),"yyyy/mm/dd") -> 2025/04/09 | C383: 4 | D383: 2407-00-000 | E383: GST/VAT receivable / 부가세대급금 | F383: 관리비_세정아울렛 관리단 | G383: 0 | H383: 38302 | I383: VSEJUNG01
A384: 4/9/2025 | B384: =TEXT(DATE(RIGHT(A384,4),LEFT(A384,FIND("/",A384)-1),MID(A384,FIND("/",A384)+1,FIND("/",A384,FIND("/",A384)+1)-FIND("/",A384)-1)),"yyyy/mm/dd") -> 2025/04/09 | C384: 4 | D384: 2407-00-000 | E384: GST/VAT receivable / 부가세대급금 | F384: 관리비_세정아울렛 관리단 | G384: 38302 | H384: 0
A385: 4/9/2025 | B385: =TEXT(DATE(RIGHT(A385,4),LEFT(A385,FIND("/",A385)-1),MID(A385,FIND("/",A385)+1,FIND("/",A385,FIND("/",A385)+1)-FIND("/",A385)-1)),"yyyy/mm/dd") -> 2025/04/09 | C385: 4 | D385: 2202-00-001 | E385: Other payable / 기타미지급금 | F385: 관리비_세정아울렛 관리단 | G385: 0 | H385: 382530 | I385: VSEJUNG01
A386: 4/9/2025 | B386: =TEXT(DATE(RIGHT(A386,4),LEFT(A386,FIND("/",A386)-1),MID(A386,FIND("/",A386)+1,FIND("/",A386,FIND("/",A386)+1)-FIND("/",A386)-1)),"yyyy/mm/dd") -> 2025/04/09 | C386: 4 | D386: 2202-00-001 | E386: Other payable / 기타미지급금 | F386: 관리비_세정아울렛 관리단 | G386: 421320 | H386: 0 | I386: VSEJUNG01
A387: 4/9/2025 | B387: =TEXT(DATE(RIGHT(A387,4),LEFT(A387,FIND("/",A387)-1),MID(A387,FIND("/",A387)+1,FIND("/",A387,FIND("/",A387)+1)-FIND("/",A387)-1)),"yyyy/mm/dd") -> 2025/04/09 | C387: 4 | D387: 2202-00-001 | E387: Other payable / 기타미지급금 | F387: 관리비_세정아울렛 관리단 | G387: 0 | H387: 421320
A388: 4/9/2025 | B388: =TEXT(DATE(RIGHT(A388,4),LEFT(A388,FIND("/",A388)-1),MID(A388,FIND("/",A388)+1,FIND("/",A388,FIND("/",A388)+1)-FIND("/",A388)-1)),"yyyy/mm/dd") -> 2025/04/09 | C388: 29 | D388: 5101-00-000 | E388: Management fee expense / 관리 수수료 비용 | F388: 관리비_세정아울렛 관리단 | G388: 0 | H388: 347755 | I388: VSEJUNG01
A389: 4/9/2025 | B389: =TEXT(DATE(RIGHT(A389,4),LEFT(A389,FIND("/",A389)-1),MID(A389,FIND("/",A389)+1,FIND("/",A389,FIND("/",A389)+1)-FIND("/",A389)-1)),"yyyy/mm/dd") -> 2025/04/09 | C389: 29 | D389: 2407-00-000 | E389: GST/VAT receivable / 부가세대급금 | F389: 관리비_세정아울렛 관리단 | G389: 0 | H389: 34775 | I389: VSEJUNG01
...

Sheet COA
A1: 계정코드 | B1: 국문명 | C1: 다국어 | D1: 분류 | E1: 코드성격 | F1: 보조계정 | G1: 보조국문명 | H1: 보조국문명 | I1: 사용여부
A2: 1101-00-000 | B2: 현금 - CNY | C2: Cash - CNY | D2: A | E2: ZZ | I2: Y
A3: 1102-00-000 | B3: 현금 - HKD | C3: Cash - HKD | D3: A | E3: ZZ | I3: Y
A4: 1103-00-000 | B4: 현금 - INR | C4: Cash - INR | D4: A | E4: ZZ | I4: Y
A5: 1104-00-000 | B5: 현금 - 엔 | C5: Cash - JPY | D5: A | E5: ZZ | I5: Y
A6: 1105-00-000 | B6: 현금 - PHP | C6: Cash - PHP | D6: A | E6: ZZ | I6: Y
A7: 1106-00-000 | B7: 현금 - SGD | C7: Cash - SGD | D7: A | E7: ZZ | I7: Y
A8: 1107-00-000 | B8: 현금 - THB | C8: Cash - THB | D8: A | E8: ZZ | I8: Y
A9: 1108-00-000 | B9: 현금 - USD | C9: Cash - USD | D9: A | E9: ZZ | I9: Y
A10: 1108-00-001 | B10: 현금 - USD (HSBC) | C10: Cash - USD (HSBC) | D10: A | E10: ZZ | I10: Y
A11: 1108-00-002 | B11: 현금 - USD (스탠다드차타드) | C11: Cash - USD (Standard Chartered) | D11: A | E11: ZZ | I11: Y
A12: 1108-KR-001 | B12: 현금 - USD (HANA) | C12: Cash - USD (HANA) | D12: A | E12: ZZ | I12: Y
A13: 1108-KR-002 | B13: 현금 - USD (HSBC) | C13: Cash - USD (HSBC) | D13: A | E13: ZZ | I13: Y
... A532: 9902-00-000 | B532: 아메리칸 익스프레스 법인 카드 클리어링 계정 | C532: American Express Corporate Card Clearing Account | D532: L | E532: ZZ | I532: Y

Sheet 잔액명세서
C2: BS 거래처별 잔액명세서
C3: 금명 유한회사
C4: 2025/01/31 ~ 2025/02/28
A5: =IF(C5="",A4,C5) -> 계정 | B5: =IF(D5="",B4,D5) -> 계정명 | C5: 계정 | D5: 계정명 | E5: 거래처코드 | G5: 거래처명 | I5: 2025/01/31 | J5: 2025/02/28
A6: =IF(C6="",A5,C6) -> 자산 | B6: =IF(D6="",B5,D6) -> 계정명 | C6: 자산
A7: =IF(C7="",A6,C7) -> 1112-KR-001 | B7: =IF(D7="",B6,D7) -> 현금 - 원 (HANA) | C7: 1112-KR-001 | D7: 현금 - 원 (HANA) | E7: 201-910031-85704 | G7: HANA_Bank 하나은행(85704) | I7: 325492654 | J7: 2106438696
A8: =IF(C8="",A7,C8) -> 1112-KR-001 | B8: =IF(D8="",B7,D8) -> 현금 - 원 (HANA) | C8: 1112-KR-001 | I8: 325492654 | J8: 2106438696
A9: =IF(C9="",A8,C9) -> 1112-KR-005 | B9: =IF(D9="",B8,D9) -> 현금 - 원 (신협) | C9: 1112-KR-005 | D9: 현금 - 원 (신협) | E9: 131-022-007238 | G9: 신협 (007238) | I9: 28229508 | J9: 20448685
A10: =IF(C10="",A9,C10) -> 1112-KR-005 | B10: =IF(D10="",B9,D10) -> 현금 - 원 (신협) | C10: 1112-KR-005 | I10: 28229508 | J10: 20448685
A11: =IF(C11="",A10,C11) -> 1212-00-000 | B11: =IF(D11="",B10,D11) -> 선납세금 | C11: 1212-00-000 | D11: 선납세금 | E11: 4617043000 | G11: Naju Districted Office_나주시청 | I11: 21560 | J11: 21560
A12: =IF(C12="",A11,C12) -> 1212-00-000 | B12: =IF(D12="",B11,D12) -> 선납세금 | E12: TAX412 | G12: Naju Tax Office 나주세무서 | I12: 215870 | J12: 215870
A13: =IF(C13="",A12,C13) -> 1212-00-000 | B13: =IF(D13="",B12,D13) -> 선납세금 | C13: 1212-00-000 | I13: 237430 | J13: 237430
A14: =IF(C14="",A13,C14) -> 1214-00-000 | B14: =IF(D14="",B13,D14) -> 기타미수금 | C14: 1214-00-000 | D14: 기타미수금 | E14: 4808102805 | G14: 주시회사 금명건설 | I14: 36539357 | J14: 36539357
A15: =IF(C15="",A14,C15) -> 1214-00-000 | B15: =IF(D15="",B14,D15) -> 기타미수금 | E15: TAX412 | G15: Naju Tax Office 나주세무서 | I15: 22046685 | J15: 0
A16: =IF(C16="",A15,C16) -> 1214-00-000 | B16: =IF(D16="",B15,D16) -> 기타미수금 | C16: 1214-00-000 | I16: 58586042 | J16: 36539357
A17: =IF(C17="",A16,C17) -> 1231-00-000 | B17: =IF(D17="",B16,D17) -> 임차보증금 - 비유동 | C17: 1231-00-000 | D17: 임차보증금 - 비유동 | E17: 1168268413 | G17: 세정아울렛 관리단 | I17: 980000 | J17: 980000
A18: =IF(C18="",A17,C18) -> 1231-00-000 | B18: =IF(D18="",B17,D18) -> 임차보증금 - 비유동 | E18: 1608101862 | G18: 유한회사 삼형 | I18: 20000000 | J18: 20000000
A19: =IF(C19="",A18,C19) -> 1231-00-000 | B19: =IF(D19="",B18,D19) -> 임차보증금 - 비유동 | C19: 1231-00-000 | I19: 20980000 | J19: 20980000
A20: =IF(C20="",A19,C20) -> 1232-00-000 | B20: =IF(D20="",B19,D20) -> 선급비용 | C20: 1232-00-000 | D20: 선급비용 | E20: 1608101862 | G20: 유한회사 삼형 | I20: 10000000 | J20: 9000000
A21: =IF(C21="",A20,C21) -> 1232-00-000 | B21: =IF(D21="",B20,D21) -> 선급비용 | C21: 1232-00-000 | I21: 10000000 | J21: 9000000
A22: =IF(C22="",A21,C22) -> 1233-00-000 | B22: =IF(D22="",B21,D22) -> 선급금 (유동) | C22: 1233-00-000 | D22: 선급금 (유동) | E22: 2208711247 | G22: 삼정 KPMG AAS (proxy payment) | I22: 43834 | J22: 0
A23: =IF(C23="",A22,C23) -> 1233-00-000 | B23: =IF(D23="",B22,D23) -> 선급금 (유동) | C23: 1233-00-000 | I23: 43834 | J23: 0
A24: =IF(C24="",A23,C24) -> 1712-00-000 | B24: =IF(D24="",B23,D24) -> 토지 | C24: 1712-00-000 | D24: 토지 | I24: 3016419000 | J24: 3016419000
A25: =IF(C25="",A24,C25) -> 1712-00-000 | B25: =IF(D25="",B24,D25) -> 토지 | E25: 1546700144 | G25: 법무사정찬선 사무소 | I25: 7730646 | J25: 7730646
A26: =IF(C26="",A25,C26) -> 1712-00-000 | B26: =IF(D26="",B25,D26) -> 토지 | E26: 4110279147 | G26: 김윤석 법무사 | I26: 10739760 | J26: 10739760
A27: =IF(C27="",A26,C27) -> 1712-00-000 | B27: =IF(D27="",B26,D27) -> 토지 | E27: 4118183990 | G27: (유)늘샘쏠라에너지 | I27: 2692540000 | J27: 2944540000
A28: =IF(C28="",A27,C28) -> 1712-00-000 | B28: =IF(D28="",B27,D28) -> 토지 | E28: 4118202510 | G28: 목포신용협동조합 | I28: 44432873 | J28: 44432873
A29: =IF(C29="",A28,C29) -> 1712-00-000 | B29: =IF(D29="",B28,D29) -> 토지 | E29: 4617043000 | G29: Naju Districted Office_나주시청 | I29: 262060100 | J29: 262060100
A30: =IF(C30="",A29,C30) -> 1712-00-000 | B30: =IF(D30="",B29,D30) -> 토지 | E30: 4691025300 | G30: Sinan Districted Office_신안군청 | I30: 552000 | J30: 552000
A31: =IF(C31="",A30,C31) -> 1712-00-000 | B31: =IF(D31="",B30,D31) -> 토지 | E31: 5438101960 | G31: 법무사법인 목포 | I31: 3880100 | J31: 3880100
A32: =IF(C32="",A31,C32) -> 1712-00-000 | B32: =IF(D32="",B31,D32) -> 토지 | E32: 5571701838 | G32: 법무사이형오사무소 | I32: 4683230 | J32: 4683230
A33: =IF(C33="",A32,C33) -> 1712-00-000 | B33: =IF(D33="",B32,D33) -> 토지 | E33: 5998701228 | G33: ㈜삼정개발 | I33: 155971200 | J33: 155971200
A34: =IF(C34="",A33,C34) -> 1712-00-000 | B34: =IF(D34="",B33,D34) -> 토지 | E34: 8258101824 | G34: EEK 2 에퀴스에너지코리아2 유한회사 | I34: 583660095 | J34: 583660095
A35: =IF(C35="",A34,C35) -> 1712-00-000 | B35: =IF(D35="",B34,D35) -> 토지 | C35: 1712-00-000 | I35: 6782669004 | J35: 7034669004
A36: =IF(C36="",A35,C36) -> 2407-00-000 | B36: =IF(D36="",B35,D36) -> 부가세대급금 | C36: 2407-00-000 | D36: 부가세대급금 | E36: 1028134334 | G36: KPMG 삼정회계법인 | I36: 140000 | J36: 205000
A37: =IF(C37="",A36,C37) -> 2407-00-000 | B37: =IF(D37="",B36,D37) -> 부가세대급금 | E37: 1168268413 | G37: 세정아울렛 관리단 | I37: 33310 | J37: 66560
A38: =IF(C38="",A37,C38) -> 2407-00-000 | B38: =IF(D38="",B37,D38) -> 부가세대급금 | E38: 2028114695 | G38: HANA BANK (주)하나은행 | I38: 400 | J38: 2000
A39: =IF(C39="",A38,C39) -> 2407-00-000 | B39: =IF(D39="",B38,D39) -> 부가세대급금 | E39: 5028400374 | G39: ECSK BO 에퀴스센트럴서비스코리아피티이엘티디 (영업소) | I39: 14797717 | J39: 14797717
A40: =IF(C40="",A39,C40) -> 2407-00-000 | B40: =IF(D40="",B39,D40) -> 부가세대급금 | C40: 2407-00-000 | I40: 14971427 | J40: 15071277
A41: =IF(C41="",A40,C41) -> 자산 | B41: =IF(D41="",B40,D41) -> Total | C41: 자산 | D41: Total | I41: 7241209899 | J41: 9243384449
A42: =IF(C42="",A41,C42) -> 부채 | B42: =IF(D42="",B41,D42) -> Total | C42: 부채
A43: =IF(C43="",A42,C43) -> 2101-00-000 | B43: =IF(D43="",B42,D43) -> 은행 대출 | C43: 2101-00-000 | D43: 은행 대출 | E43: 4118202510 | G43: 목포신용협동조합 | I43: 2000000000 | J43: 2000000000
A44: =IF(C44="",A43,C44) -> 2101-00-000 | B44: =IF(D44="",B43,D44) -> 은행 대출 | C44: 2101-00-000 | I44: 2000000000 | J44: 2000000000
A45: =IF(C45="",A44,C45) -> 2102-00-000 | B45: =IF(D45="",B44,D45) -> 관계사 대출 - 장기 | C45: 2102-00-000 | D45: 관계사 대출 - 장기 | E45: 201907742E | G45: EEKH PL Equis Energy (Korea) Holdings Pte. Ltd. | I45: 0 | J45: 2544942400
A46: =IF(C46="",A45,C46) -> 2102-00-000 | B46: =IF(D46="",B45,D46) -> 관계사 대출 - 장기 | E46: 8258101824 | G46: EEK 2 에퀴스에너지코리아2 유한회사 | I46: 1321408000 | J46: 1321408000
A47: =IF(C47="",A46,C47) -> 2102-00-000 | B47: =IF(D47="",B46,D47) -> 관계사 대출 - 장기 | C47: 2102-00-000 | I47: 1321408000 | J47: 3866350400
A48: =IF(C48="",A47,C48) -> 2202-00-001 | B48: =IF(D48="",B47,D48) -> 기타미지급금 | C48: 2202-00-001 | D48: 기타미지급금 | E48: 1028134334 | G48: KPMG 삼정회계법인 | I48: 2970000 | J48: 2255000
A49: =IF(C49="",A48,C49) -> 2202-00-001 | B49: =IF(D49="",B48,D49) -> 기타미지급금 | E49: 4808102805 | G49: 주시회사 금명건설 | I49: 5444960 | J49: 5444960
A50: =IF(C50="",A49,C50) -> 2202-00-001 | B50: =IF(D50="",B49,D50) -> 기타미지급금 | C50: 2202-00-001 | I50: 8414960 | J50: 7699960
A51: =IF(C51="",A50,C51) -> 2203-00-000 | B51: =IF(D51="",B50,D51) -> 관계사미지급금 | C51: 2203-00-000 | D51: 관계사미지급금 | E51: 201726513C | G51: ECSS PL Equis Central Service Singapore Pte. Ltd. | I51: 0 | J51: 2590672
A52: =IF(C52="",A51,C52) -> 2203-00-000 | B52: =IF(D52="",B51,D52) -> 관계사미지급금 | E52: 5028400374 | G52: ECSK BO 에퀴스센트럴서비스코리아피티이엘티디 (영업소) | I52: 519927257 | J52: 0
A53: =IF(C53="",A52,C53) -> 2203-00-000 | B53: =IF(D53="",B52,D53) -> 관계사미지급금 | C53: 2203-00-000 | I53: 519927257 | J53: 2590672
A54: =IF(C54="",A53,C54) -> 2204-00-001 | B54: =IF(D54="",B53,D54) -> 미지급이자비용 - 관계사 대출 - 장기 | C54: 2204-00-001 | D54: 미지급이자비용 - 관계사 대출 - 장기 | E54: 8258101824 | G54: EEK 2 에퀴스에너지코리아2 유한회사 | I54: 1647292549 | J54: 1661484109
A55: =IF(C55="",A54,C55) -> 2204-00-001 | B55: =IF(D55="",B54,D55) -> 미지급이자비용 - 관계사 대출 - 장기 | C55: 2204-00-001 | I55: 1647292549 | J55: 1661484109
A56: =IF(C56="",A55,C56) -> 부채 | B56: =IF(D56="",B55,D56) -> Total | C56: 부채 | D56: Total | I56: 5497042766 | J56: 7538125141
A57: =IF(C57="",A56,C57) -> 자본 | B57: =IF(D57="",B56,D57) -> Total | C57: 자본
A58: =IF(C58="",A57,C58) -> 3111-00-000 | B58: =IF(D58="",B57,D58) -> 보통주 | C58: 3111-00-000 | D58: 보통주 | E58: 8258101824 | G58: EEK 2 에퀴스에너지코리아2 유한회사 | I58: 4004550000 | J58: 4004550000
A59: =IF(C59="",A58,C59) -> 3111-00-000 | B59: =IF(D59="",B58,D59) -> 보통주 | C59: 3111-00-000 | I59: 4004550000 | J59: 4004550000
A60: =IF(C60="",A59,C60) -> 3113-00-001 | B60: =IF(D60="",B59,D60) -> 주식할인 발행차금 | C60: 3113-00-001 | D60: 주식할인 발행차금 | E60: 1048617068 | G60: JIPYONG LLC.법무법인(유한) 지평 | I60: -23137000 | J60: -23137000
A61: =IF(C61="",A60,C61) -> 3113-00-001 | B61: =IF(D61="",B60,D61) -> 주식할인 발행차금 | E61: 2018112563 | G61: Lee&Ko 법무법인(유한) 광장 | I61: -3184000 | J61: -3184000
A62: =IF(C62="",A61,C62) -> 3113-00-001 | B62: =IF(D62="",B61,D62) -> 주식할인 발행차금 | C62: 3113-00-001 | I62: -26321000 | J62: -26321000
A63: =IF(C63="",A62,C63) -> 3304-00-000 | B63: =IF(D63="",B62,D63) -> 감자차손 | C63: 3304-00-000 | D63: 감자차손 | I63: -1345434787 | J63: -1345434787
A64: =IF(C64="",A63,C64) -> 3304-00-000 | B64: =IF(D64="",B63,D64) -> 감자차손 | E64: 2018112563 | G64: Lee&Ko 법무법인(유한) 광장 | I64: -2122960 | J64: -2122960
A65: =IF(C65="",A64,C65) -> 3304-00-000 | B65: =IF(D65="",B64,D65) -> 감자차손 | C65: 3304-00-000 | I65: -1347557747 | J65: -1347557747
A66: =IF(C66="",A65,C66) -> 3401-00-000 | B66: =IF(D66="",B65,D66) -> 이익 잉여금 | C66: 3401-00-000 | D66: 이익 잉여금 | I66: -839391686 | J66: -839391686
A67: =IF(C67="",A66,C67) -> 3401-00-000 | B67: =IF(D67="",B66,D67) -> 이익 잉여금 | C67: 3401-00-000 | I67: -839391686 | J67: -839391686
A68: =IF(C68="",A67,C68) -> 자본 | B68: =IF(D68="",B67,D68) -> Total | C68: 자본 | D68: Total | I68: 1791279567 | J68: 1791279567

Sheet Sheet1
G7: <2025년도 AIAPP 소득x, 간소화자료 제출하셔서 종전근무지 소득 확인필요자>
G8: 성함 | H8: 사원번호
G9: 유현민 | H9: 54683 | I9: 2025년도 종전근무지 소득없음(AIAPP 외 사업소득 없음)->연말정산 제외 된다고 말씀드림 (2/12일 오후 본인과 통화)
G10: 이정희 | H10: 54684 | I10: 부재중
G17: [제외자->대상자]
G18: 성함 | H18: 사원번호
G19: 51286 | H19: 김재성 | I19: 목요일 오후 5시 이후로 접속하여 진행하다고 하심(2/12 오후 본인과 통화)
G20: 54220 | H20: 김재영 | I20: 부재중
G21: 54338 | H21: 김미영 | I21: 상황 전달하였으며 추가로 다시 전화주신다고 하심 (2/12 오후 본인과 통화)
G28: 성함 | H28: 사원번호
G29: 김재영 | H29: 50981 | I29: 문자 발송 완료
G30: 최영옥 | H30: 53299 | I30: 문자 발송 완료

Sheet GL
A1: 계정별 원장
A4: 금명 유한회사
A7: 2026/01/01 ~ 2026/03/31
A10: Posting Date | B10: Document No. | C10: External Document No. | D10: Description | G10: VAT Amount | I10: Debit | L10: Credit | N10: Balance
A11: 1108-KR-001 Cash - USD (HANA) / 현금 - USD (HANA)
N13: 0
A14: 26-03-11 | B14: KM-JV26-0181 | D14: 263 EEKHPL_Unsecured Loan Agreement(USD 1,740,895) | G14: 0 | I14: 2610472053 | N14: 2610472053
A15: 26-03-11 | B15: KM-JV26-0181 | D15: 264 EEKHPL_Unsecured Loan Agreement(USD 323,000) | G15: 0 | I15: 484338500 | N15: 3094810553
A16: 26-03-11 | B16: KM-JV26-0182 | D16: 264 EEKHPL_Unsecured Loan Agreement(USD 323,000) | G16: 0 | L16: 484338500 | N16: 2610472053
A17: 26-03-11 | B17: KM-JV26-0183 | D17: 263 EEKHPL_Unsecured Loan Agreement(USD 1,740,895) | G17: 0 | L17: 2610472053 | N17: 0
A18: Cash - USD (HANA) / 현금 - USD (HANA) | G18: 0 | I18: 3094810553 | L18: 3094810553 | N18: 0
A19: 1112-KR-001 Cash - KRW (HANA) / 현금 - 원 (HANA)
N21: 1402060267
A22: 26-01-07 | B22: KM-PV26-0005 | D22: [KR Inv_202512] VLEHYUN01_Kummyung_Land Sale Down Payment for Bunmae-ri 684-1_KRW 60000000 | G22: 0 | L22: 60000000 | N22: 1342060267
A23: 26-01-08 | B23: KM-PV26-0006 | D23: [KR Inv_202601] VJMNGHI01_Kummyung_Land Purchase Balance Payment for Shinjang-ri 819-4_KRW 33500000 | G23: 0 | L23: 33500000 | N23: 1308560267
A24: 26-01-08 | B24: KM-PV26-0007 | D24: [KR Inv_202601] VLEHYUN01_Kummyung_Land Sale Down Payment for Bunmae-ri 685-6_KRW 15000000 | G24: 0 | L24: 15000000 | N24: 1293560267
A25: 26-01-08 | B25: KM-PV26-0008 | D25: [KR Inv_202601] VLEHYUN01_Kummyung_Land Sale Down Payment for Shinjang-ri 819-7_KRW 48000000 | G25: 0 | L25: 48000000 | N25: 1245560267
A26: 26-01-08 | B26: KM-PV26-0009 | D26: [KR Inv_202601] VLEHYUN01_Kummyung_Land Purchase Down Payment for Shinjang-ri 819-4_KRW 10000000 | G26: 0 | L26: 10000000 | N26: 1235560267
A27: 26-01-08 | B27: KM-PV26-0010 | D27: [KR Inv_202512] VLEHYUN01_Kummyung_Land Sale Down Payment for Bunmae-ri 697-10_KRW 45000000 | G27: 0 | L27: 45000000 | N27: 1190560267
A28: 26-01-08 | B28: KM-PV26-0011 | D28: [KR Inv_202601] VLEHYUN01_Kummyung_Land Sale Down Payment for Bunmae-ri 686-16 (Jin, Hyejeong)_KRW 7 | G28: 0 | L28: 7500000 | N28: 1183060267
A29: 26-01-08 | B29: KM-PV26-0012 | D29: [KR Inv_202601] VSEONGK01_Kummyung_Land Sale Balance Payment for Bunmae-ri 689-18_KRW 81000000 | G29: 0 | L29: 9000000 | N29: 1174060267
A30: 26-01-08 | B30: KM-PV26-0013 | D30: [KR Inv_202601] VSEONGK01_Kummyung_Land Sale Balance Payment for Bunmae-ri 689-18_KRW 81000000 | G30: 0 | L30: 67500000 | N30: 1106560267
A31: 26-01-08 | B31: KM-PV26-0014 | D31: [KR Inv_202601] VSEONGK01_Kummyung_Land Sale Balance Payment for Bunmae-ri 689-18_KRW 81000000 | G31: 0 | L31: 81000000 | N31: 1025560267
A32: 26-01-15 | B32: KM-PV26-0001 | D32: [KR Inv_202601] VSEJUNG01-2_Kummyung office maintenance fee inc. penalty fee _KRW 378,690 | G32: 0 | I32: 18030 | N32: 1025578297
A33: 26-01-15 | B33: KM-PV26-0015 | D33: [KR Inv_202601] VJUNGHO01_Kummyung_Land Sale Balance Payment for Bunmae-ri 696-1_KRW 47500000 | G33: 0 | L33: 47500000 | N33: 978078297
A34: 26-01-15 | B34: KM-PV26-0016 | D34: [KR Inv_202512] VLEHYUN01_Kummyung_Land Sale Down Payment for Bunmae-ri 689-19_KRW 7500000 | G34: 0 | L34: 7500000 | N34: 970578297
A35: 26-01-15 | B35: KM-PV26-0017 | D35: [KR Inv_202601] VLEHYUN01_Kummyung_Land Sale Down Payment for Bunmae-ri 686-16 (Oh, Seongyeol)_KRW 6 | G35: 0 | L35: 6500000 | N35: 964078297
A36: 26-01-15 | B36: KM-PV26-0018 | D36: [KR Inv_202601] VLEHYUN01_Kummyung_Land Purchase Down Payment for Shinjang-ri 819-8_KRW 48000000 | G36: 0 | L36: 48000000 | N36: 916078297
A37: 26-01-15 | B37: KM-PV26-0019 | D37: [KR Inv_202601] VLEHYUN01_Kummyung_Land Purchase Down Payment for Sinjang-ri 819-18_KRW 5000000 | G37: 0 | L37: 5000000 | N37: 911078297
A38: 26-01-15 | B38: KM-JV26-0069 | D38: 수정_[KR Inv_202601] VSEJUNG01-2_Kummyung office maintenance fee inc. penalty fee _KRW 378,690 | G38: 0 | L38: 396720 | N38: 910681577
A39: 26-01-22 | B39: KM-PV26-0003 | D39: OTT260100615 | G39: 0 | L39: 7290423 | N39: 903391154
A40: 26-01-22 | B40: KM-PV26-0004 | D40: 당발송금수수료(Ref No: 0201OTT260100615) | G40: 0 | L40: 51876 | N40: 903339278
A41: 26-01-22 | B41: KM-PV26-0020 | D41: [KR Inv_202601] VLINSUK01_Kummyung_Land Sale Balance Payment for Sinjang-ri 819-18_KRW 40000000 | G41: 0 | L41: 40000000 | N41: 863339278
A42: 26-01-22 | B42: KM-PV26-0021 | D42: [KR Inv_202601] VLEYHUI01_Kummyung_Land Sale Balance Payment for Bunmae-ri 685-3_KRW 40000000 | G42: 0 | L42: 40000000 | N42: 823339278
A43: 26-01-22 | B43: KM-PV26-0022 | D43: [KR Inv_202601] VJYONGH01_Kummyung_Land Sale Balance Payment for Bunmae-ri 685-2_KRW 27000000 | G43: 0 | L43: 27000000 | N43: 796339278
A44: 26-01-22 | B44: KM-PV26-0023 | D44: [KR Inv_202601] VLEHYUN01_Kummyung_Land Purchase Down Payment for Bunmae-ri 685-3_KRW 5000000 | G44: 0 | L44: 5000000 | N44: 791339278
... A66: 26-02-03 | B66: KM-PV26-0044 | D66: [KR Inv_202601] VTAENAM01_Kummyung_Land Sale Balance Payment for Bunmea-ri 718-65_KRW 20000000 | G66: 0 | L66: 20000000 | N66: 268507178
A67: 26-02-03 | B67: KM-JV26-0107 | D67: 수정_2026.02.03_Bank 시트_ KRW 20,000,000 출금 | G67: 0 | I67: 20000000 | N67: 288507178
A68: 26-02-03 | B68: KM-JV26-0108 | D68: Hana KRW -> Shiyunhup Bank KRW | G68: 0 | L68: 20000000 | N68: 268507178
A69: 26-02-05 | B69: KM-PV26-0045 | D69: [KR Inv_202601] VNEULSA01_Kummyung_Land Sale Down Payment for Bunmea-ri 718-65_KRW 10000000 | G69: 0 | L69: 10000000 | N69: 258507178
A70: 26-02-05 | B70: KM-PV26-0046 | D70: [KR Inv_202601] VNEULSA01_Kummyung_Land Sale Down Payment for Sinjang-ri 799-3_KRW 15000000 | G70: 0 | L70: 15000000 | N70: 243507178
A71: 26-02-05 | B71: KM-PV26-0047 | D71: [KR Inv_202602] VDREAME01_PJ Yangju_YH Power 1_Design Service Fee_KRW 11000000 | G71: 0 | L71: 11000000 | N71: 232507178
A72: 26-02-05 | B72: KM-PV26-0048 | D72: KR Inv_202601] VLEHYUN01_Kummyung_Land Purchase Down Payment for Sinjang-ri 797-6 (Choi, Okja)_KRW 3 | G72: 0 | L72: 3000000 | N72: 229507178
A73: 26-02-05 | B73: KM-PV26-0049 | D73: [KR Inv_202601] VLEHYUN01_Kummyung_Land Purchase Down Payment for Sinjang-ri 797-6_KRW 3000000 | G73: 0 | L73: 3000000 | N73: 226507178
A74: 26-02-05 | B74: KM-PV26-0050 | D74: [KR Inv_202601] VLEHYUN01_Kummyung_Land Purchase Down Payment for Sinjang-ri 797-6_KRW 33250000 | G74: 0 | L74: 33250000 | N74: 193257178
A75: 26-02-05 | B75: KM-PV26-0051 | D75: VLEHYUN01_Land Purchase Payment | G75: 0 | L75: 14000000 | N75: 179257178
A76: 26-02-06 | B76: KM-PV26-0052 | D76: 공인인증서(은행/보험용) | G76: 0 | L76: 4400 | N76: 179252778
A77: 26-02-12 | B77: KM-PV26-0053 | D77: [KR Inv_202602] VSAMHYO01_Kummyung_Yearly Rent Payment for Office Rental_KRW 13200000 | G77: 0 | L77: 13200000 | N77: 166052778
A78: 26-02-12 | B78: KM-PV26-0054 | D78: [KR Inv_202601] VTAXLOC01_Kummyung_Land Acquisition Tax for Sinjang-ri 718-65_KRW 1380000 | G78: 0 | L78: 1380000 | N78: 164672778
A79: 26-02-12 | B79: KM-PV26-0055 | D79: [KR Inv_202601] VTAXLOC01_Kummyung_Land Acquisition Tax for Sinjang-ri 819-18_KRW 2070000 | G79: 0 | L79: 2070000 | N79: 162602778
... A84: 26-02-19 | B84: KM-PV26-0060 | D84: [KR Inv_202602] VJUSANG01_Kummyung_Land Lease Down Payment for Bunmae-ri 693-3_KRW 2136000 | G84: 0 | L84: 2136000 | N84: 155972978
A85: 26-02-19 | B85: KM-JV26-0111 | D85: 제주북촌_Field trip for local residents of Project Phantom_기타미수금과 상계 | G85: 0 | I85: 25135000 | N85: 181107978
A86: 26-02-19 | B86: KM-JV26-0127 | D86: VAT Return for 2025.2H _ Naju Tax Office 나주세무서 | G86: 0 | I86: 124013160 | N86: 305121138
A87: 26-02-26 | B87: KM-PV26-0061 | D87: [KR Inv_202602] VWOOHYE01_Kummyung_Land Sale Balance Payment for Bunmae-ri 688-2_KRW 148000000 | G87: 0 | L87: 148000000 | N87: 157121138
A88: 26-02-26 | B88: KM-PV26-0062 | D88: [매입세금계산서] 용역비 | G88: 0 | L88: 35856700 | N88: 121264438
A89: 26-02-26 | B89: KM-PV26-0063 | D89: [KR Inv_202602] VNEULSA01_Kummyung_Land Sale Down Payment for Bunmae-ri 718-70_KRW 35000000 | G89: 0 | L89: 35000000 | N89: 86264438
A90: 26-02-26 | B90: KM-PV26-0064 | D90: [KR Inv_202602] VNEULSA01_Kummyung_Land Sale Down Payment for Bunmae-ri 688-2_KRW 17000000 | G90: 0 | L90: 17000000 | N90: 69264438
A91: 26-03-05 | B91: KM-PV26-0065 | D91: Hana Bank KRW | G91: 0 | L91: 390320 | N91: 68874118
A92: 26-03-05 | B92: KM-PV26-0068 | D92: [KR Inv_202601] VTAXLOC01_Kummyung_Land Acquisition Tax for Sinjang-ri 797-6 (4)_KRW 1223600 | G92: 0 | L92: 1223600 | N92: 67650518
A93: 26-03-05 | B93: KM-PV26-0069 | D93: [KR Inv_202601] VTAXLOC01_Kummyung_Land Acquisition Tax for Sinjang-ri 797-6 (3)_KRW 1223600 | G93: 0 | L93: 1223600 | N93: 66426918
A94: 26-03-05 | B94: KM-PV26-0070 | D94: [KR Inv_202601] VTAXLOC01_Kummyung_Land Acquisition Tax for Sinjang-ri 797-6 (1)_KRW 6118000 | G94: 0 | L94: 6118000 | N94: 60308918
A95: 26-03-05 | B95: KM-PV26-0071 | D95: [KR Inv_202602] VTAXLOC01_Kummyung_Land Acquisition Tax for Sinjang-ri 718-70_KRW 1610000 | G95: 0 | L95: 1610000 | N95: 58698918
A96: 26-03-05 | B96: KM-PV26-0072 | D96: [KR Inv_202601] VTAXLOC01_Kummyung_Land Acquisition Tax for Sinjang-ri 797-6 (2)_KRW 5139120 | G96: 0 | L96: 5139120 | N96: 53559798
A97: 26-03-06 | B97: KM-PV26-0073 | D97: [KR Inv_202601] VTAXLOC01_Kummyung_Land Acquisition Tax for Sinjang-ri 718-65_KRW 1380000 | G97: 0 | L97: 1380000 | N97: 52179798
A98: 26-03-06 | B98: KM-PV26-0074 | D98: [KR Inv_202601] VTAXLOC01_Kummyung_Land Acquisition Tax for Sinjang-ri 799-3_KRW 690000 | G98: 0 | L98: 6900000 | N98: 45279798
A99: 26-03-11 | B99: KM-PV26-0067 | D99: 공인인증수수료 | G99: 0 | L99: 4400 | N99: 45275398
A100: 26-03-11 | B100: KM-JV26-0182 | D100: 264 EEKHPL_Unsecured Loan Agreement(USD 323,000) | G100: 0 | I100: 473356500 | N100: 518631898
A101: 26-03-11 | B101: KM-JV26-0183 | D101: 263 EEKHPL_Unsecured Loan Agreement(USD 1,740,895) | G101: 0 | I101: 2551281622 | N101: 3069913520
A102: 26-03-12 | B102: KM-PV26-0075 | D102: [KR Inv_202603] VTAXLOC01_PJ Phantom_Land Acquisition Tax for Bunmae-ri 697-6_KRW 2070000 | G102: 0 | L102: 2070000 | N102: 3067843520
A103: 26-03-12 | B103: KM-PV26-0076 | D103: [KR Inv_202602] VTAXLOC01_Kummyung_Land Acquisition Tax for Bunmae-ri 688-2_KRW 7590000 | G103: 0 | L103: 7590000 | N103: 3060253520
A104: 26-03-12 | B104: KM-JV26-0161 | D104: FY2025 Q4 MSA Fee | G104: 0 | L104: 458577837 | N104: 2601675683
A105: 26-03-12 | B105: KM-PV26-0084 | D105: [KR Inv_202601] VLEHYUN01_PJ Phantom_Land Registration Service Fee for Bunmae-ri 685-6_KRW 387600 | G105: 0 | L105: 387600 | N105: 2601288083
A106: 26-03-12 | B106: KM-PV26-0085 | D106: [KR Inv_202601] VLEHYUN01_PJ Phantom_Land Registration Service Fee for Sinjang-ri 819-8_KRW 415450 | G106: 0 | L106: 415450 | N106: 2600872633
A107: 26-03-12 | B107: KM-PV26-0086 | D107: [KR Inv_202601] VLEHYUN01_PJ Phantom_Land Registration Service Fee for Sinjang-ri 795-10, 795-11_KRW | G107: 0 | L107: 804190 | N107: 2600068443
A108: 26-03-12 | B108: KM-PV26-0087 | D108: [KR Inv_202602] VLEHYUN01_Kummyung_Land Acquisition Tax for Bunmae-ri 688-2_Paid by Judicial Scriven | G108: 0 | L108: 3450000 | N108: 2596618443
A109: 26-03-12 | B109: KM-PV26-0088 | D109: [KR Inv_202601] VLEHYUN01_PJ Phantom_Land Registration Service Fee for Sinjang-ri 819-7_KRW 415490 | G109: 0 | L109: 415490 | N109: 2596202953
A110: 26-03-12 | B110: KM-PV26-0089 | D110: KR Inv_202602] VLEHYUN01_PJ Phantom_Land Registration Service Fee for Bunmae-ri 686-16_KRW 355000 | G110: 0 | L110: 355000 | N110: 2595847953
A111: 26-03-12 | B111: KM-PV26-0090 | D111: [KR Inv_202601] VLEHYUN01_PJ Phantom_Land Registration Service Fee for Bunmae-ri 689-19_KRW 485470 | G111: 0 | L111: 485470 | N111: 2595362483
A112: 26-03-12 | B112: KM-PV26-0091 | D112: [KR Inv_202602] VLEHYUN01_PJ Phantom_Land Registration Service Fee for Bunmae-ri 685-2_KRW 411220 | G112: 0 | L112: 411220 | N112: 2594951263
A113: 26-03-12 | B113: KM-PV26-0092 | D113: Hana Bank KRW | G113: 0 | L113: 413150 | N113: 2594538113
... A125: 26-03-19 | B125: KM-PV26-0100 | D125: [KR Inv_202602] VLEHYUN01_PJ Phantom_Land Registration Service Fee for Bunmae-ri 697-10_KRW 439730 | G125: 0 | L125: 439730 | N125: 2468061863
A126: 26-03-21 | B126: KM-JV26-0180 | D126: bank interest income(예금이자 219,071 소득세 30,660 지방소득세 3,060) | G126: 0 | I126: 185351 | N126: 2468247214
A127: 26-03-26 | B127: KM-PV26-0066 | D127: Hana Bank KRW | G127: 0 | L127: 373650 | N127: 2467873564
A128: 26-03-26 | B128: KM-PV26-0078 | D128: [KR Inv_202603] VTAXLOC01_Kummyung_Charge for exclusive use of road (Yeonsan-dong 1303)_KRW 813490 | G128: 0 | L128: 813490 | N128: 2467060074
A129: 26-03-26 | B129: KM-PV26-0079 | D129: KR Inv_202603] VTAXLOC01_Kummyung_Charge for exclusive use of road_KRW 27810 | G129: 0 | L129: 27810 | N129: 2467032264
A130: Cash - KRW (HANA) / 현금 - 원 (HANA) | G130: 0 | I130: 3193989663 | L130: 2129017666 | N130: 2467032264
A131: 1112-KR-005 Cash - KRW (SHINHYUP) / 현금 - 원 (신협)
N133: 3248905
A134: 26-02-02 | B134: KM-JV26-0109 | D134: 이자지급 (20억, 23.03.31-26.03.31, 변동금리) | G134: 0 | L134: 3211178 | N134: 37727
A135: 26-02-03 | B135: KM-JV26-0108 | D135: Hana KRW -> Shiyunhup Bank KRW | G135: 0 | I135: 20000000 | N135: 20037727
A136: 26-02-03 | B136: KM-JV26-0110 | D136: 이자지급 (20억, 23.03.31-26.03.31, 변동금리) | G136: 0 | L136: 4446246 | N136: 15591481
A137: 26-03-03 | B137: KM-JV26-0148 | D137: 이자지급 (최초원금20억, 23.03.31-27.03.31, 변동금리) | G137: 0 | L137: 6916383 | N137: 8675098
A138: 26-03-11 | B138: KM-PV26-0080 | D138: 공인인증수수료(신협은행)_세금계산서 발행x | G138: 0 | L138: 4400 | N138: 8670698
A139: 26-03-31 | B139: KM-JV26-0149 | D139: 이자지급 (최초원금20억, 23.03.31-27.03.31, 변동금리) | G139: 0 | L139: 7657424 | N139: 1013274
A140: Cash - KRW (SHINHYUP) / 현금 - 원 (신협) | G140: 0 | I140: 20000000 | L140: 22235631 | N140: 1013274
A141: 1211-00-000 Accounts receivables / 외상매출금
N143: 36539357
A144: 26-02-19 | B144: KM-JV26-0111 | D144: 제주북촌_Field trip for local residents of Project Phantom_기타미수금과 상계 | G144: 0 | L144: 25135000 | N144: 11404357
A145: Accounts receivables / 외상매출금 | G145: 0 | L145: 25135000 | N145: 11404357
A146: 1212-00-000 Income tax receivables / 선납세금
...

Sheet JE(2026)
A1: Posting Date2 | B1: Document No. | C1: G/L Account No. | D1: G/L Account Name | E1: Description | F1: Debit Amount (LCY) | G1: Credit Amount (LCY) | H1: Vendor Code
A2: 46023 | B2: KM-JV26-0056 | C2: 6402-00-002 | D2: FX - unrealized gains - others / 외화환산손실 | E2: EQUIS InterCo Billings_ECSSPL_IECSG001-INV25-0041 | F2: 0 | G2: 148911
A3: 46023 | B3: KM-JV26-0056 | C3: 2203-00-000 | D3: Intercompany Payable / 관계사미지급금 | E3: EQUIS InterCo Billings_ECSSPL_IECSG001-INV25-0041 | F3: 148911 | G3: 0
A4: 46023 | B4: KM-JV26-0057 | C4: 6402-00-002 | D4: FX - unrealized gains - others / 외화환산손실 | E4: EQUIS InterCo Billings_ECSS-SI25-0010 | F4: 0 | G4: 74396
A5: 46023 | B5: KM-JV26-0057 | C5: 2203-00-000 | D5: Intercompany Payable / 관계사미지급금 | E5: EQUIS InterCo Billings_ECSS-SI25-0010 | F5: 74396 | G5: 0
A6: 46023 | B6: KM-JV26-0058 | C6: 6402-00-002 | D6: FX - unrealized gains - others / 외화환산손실 | E6: EQUIS InterCo Billings_ECSS-SI25-0131 | F6: 0 | G6: 51661
A7: 46023 | B7: KM-JV26-0058 | C7: 2203-00-000 | D7: Intercompany Payable / 관계사미지급금 | E7: EQUIS InterCo Billings_ECSS-SI25-0131 | F7: 51661 | G7: 0
A8: 46023 | B8: KM-JV26-0059 | C8: 6402-00-002 | D8: FX - unrealized gains - others / 외화환산손실 | E8: EQUIS InterCo Billings_ECSS-SI25-0271 | F8: 0 | G8: 67537
A9: 46023 | B9: KM-JV26-0059 | C9: 2203-00-000 | D9: Intercompany Payable / 관계사미지급금 | E9: EQUIS InterCo Billings_ECSS-SI25-0271 | F9: 67537 | G9: 0
A10: 46023 | B10: KM-JV26-0060 | C10: 6402-00-002 | D10: FX - unrealized gains - others / 외화환산손실 | E10: 230 EEKHPL_Unsecured Loan Agreement(USD 1,500,000) | F10: 0 | G10: 29355000
A11: 46023 | B11: KM-JV26-0060 | C11: 2102-00-000 | D11: Intercompany loans - Long term / 관계사 대출 - 장기 | E11: 230 EEKHPL_Unsecured Loan Agreement(USD 1,500,000) | F11: 29355000 | G11: 0
A12: 46023 | B12: KM-JV26-0061 | C12: 6402-00-002 | D12: FX - unrealized gains - others / 외화환산손실 | E12: 231 EEKHPL_Unsecured Loan Agreement(USD 260,000) | F12: 0 | G12: 5088200
A13: 46023 | B13: KM-JV26-0061 | C13: 2102-00-000 | D13: Intercompany loans - Long term / 관계사 대출 - 장기 | E13: 231 EEKHPL_Unsecured Loan Agreement(USD 260,000) | F13: 5088200 | G13: 0
A14: 46028 | B14: KM-JV26-0010 | C14: 2407-00-000 | D14: GST/VAT receivable / 부가세대급금 | E14: 압해도 154kV 송전선로 2회선 설치공사(지중 1.1km, ELP 10공, 맨홀 3조) 감리용역 | F14: 1800000 | G14: 0
A15: 46028 | B15: KM-JV26-0010 | C15: 2202-00-001 | D15: Other payable / 기타미지급금 | E15: 압해도 154kV 송전선로 2회선 설치공사(지중 1.1km, ELP 10공, 맨홀 3조) 감리용역 | F15: 0 | G15: 19800000 | H15: VHWARIM01
A16: 46028 | B16: KM-JV26-0010 | C16: 1760-00-028 | D16: Construction work in progress / 건설중인 자산 | E16: 압해도 154kV 송전선로 2회선 설치공사(지중 1.1km, ELP 10공, 맨홀 3조) 감리용역 | F16: 18000000 | G16: 0
A17: 46029 | B17: KM-JV26-0011 | C17: 2202-00-001 | D17: Other payable / 기타미지급금 | E17: Land Sale Down Payment for Bunmae-ri 684-1_KRW 60000000 | F17: 0 | G17: 60000000 | H17: VLEHYUN01
A18: 46029 | B18: KM-JV26-0011 | C18: 1713-00-000 | D18: Land | E18: Land Sale Down Payment for Bunmae-ri 684-1_KRW 60000000 | F18: 60000000 | G18: 0
A19: 46029 | B19: KM-PV26-0005 | C19: 2202-00-001 | D19: Other payable / 기타미지급금 | E19: [KR Inv_202512] VLEHYUN01_Kummyung_Land Sale Down Payment for Bunmae-ri 684-1_KRW 60000000 | F19: 60000000 | G19: 0 | H19: VLEHYUN01
A20: 46029 | B20: KM-PV26-0005 | C20: 1112-KR-001 | D20: Cash - KRW (HANA) / 현금 - 원 (HANA) | E20: [KR Inv_202512] VLEHYUN01_Kummyung_Land Sale Down Payment for Bunmae-ri 684-1_KRW 60000000 | F20: 0 | G20: 60000000 | H20: HANA-KRW
A21: 46030 | B21: KM-JV26-0012 | C21: 2202-00-001 | D21: Other payable / 기타미지급금 | E21: Land Purchase Balance Payment for Shinjang-ri 819-4_KRW 33500000 | F21: 0 | G21: 33500000 | H21: VJMNGHI01
A22: 46030 | B22: KM-JV26-0012 | C22: 1713-00-000 | D22: Land | E22: Land Purchase Balance Payment for Shinjang-ri 819-4_KRW 33500000 | F22: 33500000 | G22: 0
A23: 46030 | B23: KM-JV26-0016 | C23: 2202-00-001 | D23: Other payable / 기타미지급금 | E23: Land Sale Down Payment for Bunmae-ri 685-6_KRW 15000000 | F23: 0 | G23: 15000000 | H23: VLEHYUN01
A24: 46030 | B24: KM-JV26-0016 | C24: 1713-00-000 | D24: Land | E24: Land Sale Down Payment for Bunmae-ri 685-6_KRW 15000000 | F24: 15000000 | G24: 0
A25: 46030 | B25: KM-JV26-0017 | C25: 2202-00-001 | D25: Other payable / 기타미지급금 | E25: Land Sale Down Payment for Shinjang-ri 819-7_KRW 48000000 | F25: 0 | G25: 48000000 | H25: VLEHYUN01
A26: 46030 | B26: KM-JV26-0017 | C26: 1713-00-000 | D26: Land | E26: Land Sale Down Payment for Shinjang-ri 819-7_KRW 48000000 | F26: 48000000 | G26: 0
A27: 46030 | B27: KM-JV26-0018 | C27: 2202-00-001 | D27: Other payable / 기타미지급금 | E27: Land Purchase Down Payment for Shinjang-ri 819-4_KRW 10000000 | F27: 0 | G27: 10000000 | H27: VLEHYUN01
A28: 46030 | B28: KM-JV26-0018 | C28: 1713-00-000 | D28: Land | E28: Land Purchase Down Payment for Shinjang-ri 819-4_KRW 10000000 | F28: 10000000 | G28: 0
A29: 46030 | B29: KM-JV26-0019 | C29: 2202-00-001 | D29: Other payable / 기타미지급금 | E29: Land Sale Down Payment for Bunmae-ri 697-10_KRW 45000000 | F29: 0 | G29: 45000000 | H29: VLEHYUN01
A30: 46030 | B30: KM-JV26-0019 | C30: 1713-00-000 | D30: Land | E30: Land Sale Down Payment for Bunmae-ri 697-10_KRW 45000000 | F30: 45000000 | G30: 0
A31: 46030 | B31: KM-JV26-0020 | C31: 2202-00-001 | D31: Other payable / 기타미지급금 | E31: Land Sale Down Payment for Bunmae-ri 686-16 (Jin, Hyejeong)_KRW 7500000 | F31: 0 | G31: 7500000 | H31: VLEHYUN01
A32: 46030 | B32: KM-JV26-0020 | C32: 1713-00-000 | D32: Land | E32: Land Sale Down Payment for Bunmae-ri 686-16 (Jin, Hyejeong)_KRW 7500000 | F32: 7500000 | G32: 0
A33: 46030 | B33: KM-JV26-0021 | C33: 2202-00-001 | D33: Other payable / 기타미지급금 | E33: Land Sale Balance Payment for Bunmae-ri 689-18_KRW 81000000 | F33: 0 | G33: 9000000 | H33: VLEHYUN01
A34: 46030 | B34: KM-JV26-0021 | C34: 1713-00-000 | D34: Land | E34: Land Sale Balance Payment for Bunmae-ri 689-18_KRW 81000000 | F34: 9000000 | G34: 0
A35: 46030 | B35: KM-JV26-0022 | C35: 2202-00-001 | D35: Other payable / 기타미지급금 | E35: Land Sale Balance Payment for Bunmae-ri 689-18 | F35: 0 | G35: 67500000
A36: 46030 | B36: KM-JV26-0022 | C36: 1713-00-000 | D36: Land | E36: Land Sale Balance Payment for Bunmae-ri 689-18 | F36: 67500000 | G36: 0
A37: 46030 | B37: KM-JV26-0023 | C37: 2202-00-001 | D37: Other payable / 기타미지급금 | E37: Land Sale Balance Payment for Bunmae-ri 689-18_KRW 81000000 | F37: 0 | G37: 81000000
A38: 46030 | B38: KM-JV26-0023 | C38: 1713-00-000 | D38: Land | E38: Land Sale Balance Payment for Bunmae-ri 689-18_KRW 81000000 | F38: 81000000 | G38: 0
A39: 46030 | B39: KM-PV26-0006 | C39: 2202-00-001 | D39: Other payable / 기타미지급금 | E39: [KR Inv_202601] VJMNGHI01_Kummyung_Land Purchase Balance Payment for Shinjang-ri 819-4_KRW 33500000 | F39: 33500000 | G39: 0 | H39: VJMNGHI01
A40: 46030 | B40: KM-PV26-0006 | C40: 1112-KR-001 | D40: Cash - KRW (HANA) / 현금 - 원 (HANA) | E40: [KR Inv_202601] VJMNGHI01_Kummyung_Land Purchase Balance Payment for Shinjang-ri 819-4_KRW 33500000 | F40: 0 | G40: 33500000 | H40: HANA-KRW
A41: 46030 | B41: KM-PV26-0007 | C41: 2202-00-001 | D41: Other payable / 기타미지급금 | E41: [KR Inv_202601] VLEHYUN01_Kummyung_Land Sale Down Payment for Bunmae-ri 685-6_KRW 15000000 | F41: 15000000 | G41: 0 | H41: VLEHYUN01
A42: 46030 | B42: KM-PV26-0007 | C42: 1112-KR-001 | D42: Cash - KRW (HANA) / 현금 - 원 (HANA) | E42: [KR Inv_202601] VLEHYUN01_Kummyung_Land Sale Down Payment for Bunmae-ri 685-6_KRW 15000000 | F42: 0 | G42: 15000000 | H42: HANA-KRW
A43: 46030 | B43: KM-PV26-0008 | C43: 2202-00-001 | D43: Other payable / 기타미지급금 | E43: [KR Inv_202601] VLEHYUN01_Kummyung_Land Sale Down Payment for Shinjang-ri 819-7_KRW 48000000 | F43: 48000000 | G43: 0 | H43: VLEHYUN01
A44: 46030 | B44: KM-PV26-0008 | C44: 1112-KR-001 | D44: Cash - KRW (HANA) / 현금 - 원 (HANA) | E44: [KR Inv_202601] VLEHYUN01_Kummyung_Land Sale Down Payment for Shinjang-ri 819-7_KRW 48000000 | F44: 0 | G44: 48000000 | H44: HANA-KRW
A45: 46030 | B45: KM-PV26-0009 | C45: 2202-00-001 | D45: Other payable / 기타미지급금 | E45: [KR Inv_202601] VLEHYUN01_Kummyung_Land Purchase Down Payment for Shinjang-ri 819-4_KRW 10000000 | F45: 10000000 | G45: 0 | H45: VLEHYUN01
A46: 46030 | B46: KM-PV26-0009 | C46: 1112-KR-001 | D46: Cash - KRW (HANA) / 현금 - 원 (HANA) | E46: [KR Inv_202601] VLEHYUN01_Kummyung_Land Purchase Down Payment for Shinjang-ri 819-4_KRW 10000000 | F46: 0 | G46: 10000000 | H46: HANA-KRW
A47: 46030 | B47: KM-PV26-0010 | C47: 2202-00-001 | D47: Other payable / 기타미지급금 | E47: [KR Inv_202512] VLEHYUN01_Kummyung_Land Sale Down Payment for Bunmae-ri 697-10_KRW 45000000 | F47: 45000000 | G47: 0 | H47: VLEHYUN01
A48: 46030 | B48: KM-PV26-0010 | C48: 1112-KR-001 | D48: Cash - KRW (HANA) / 현금 - 원 (HANA) | E48: [KR Inv_202512] VLEHYUN01_Kummyung_Land Sale Down Payment for Bunmae-ri 697-10_KRW 45000000 | F48: 0 | G48: 45000000 | H48: HANA-KRW
A49: 46030 | B49: KM-PV26-0011 | C49: 2202-00-001 | D49: Other payable / 기타미지급금 | E49: [KR Inv_202601] VLEHYUN01_Kummyung_Land Sale Down Payment for Bunmae-ri 686-16 (Jin, Hyejeong)_KRW 7 | F49: 7500000 | G49: 0 | H49: VLEHYUN01
A50: 46030 | B50: KM-PV26-0011 | C50: 1112-KR-001 | D50: Cash - KRW (HANA) / 현금 - 원 (HANA) | E50: [KR Inv_202601] VLEHYUN01_Kummyung_Land Sale Down Payment for Bunmae-ri 686-16 (Jin, Hyejeong)_KRW 7 | F50: 0 | G50: 7500000 | H50: HANA-KRW
... A52: 46030 | B52: KM-PV26-0012 | C52: 1112-KR-001 | D52: Cash - KRW (HANA) / 현금 - 원 (HANA) | E52: [KR Inv_202601] VSEONGK01_Kummyung_Land Sale Balance Payment for Bunmae-ri 689-18_KRW 81000000 | F52: 0 | G52: 9000000 | H52: HANA-KRW
A53: 46030 | B53: KM-PV26-0013 | C53: 2202-00-001 | D53: Other payable / 기타미지급금 | E53: [KR Inv_202601] VSEONGK01_Kummyung_Land Sale Balance Payment for Bunmae-ri 689-18_KRW 81000000 | F53: 67500000 | G53: 0
A54: 46030 | B54: KM-PV26-0013 | C54: 1112-KR-001 | D54: Cash - KRW (HANA) / 현금 - 원 (HANA) | E54: [KR Inv_202601] VSEONGK01_Kummyung_Land Sale Balance Payment for Bunmae-ri 689-18_KRW 81000000 | F54: 0 | G54: 67500000 | H54: HANA-KRW
A55: 46030 | B55: KM-PV26-0014 | C55: 2202-00-001 | D55: Other payable / 기타미지급금 | E55: [KR Inv_202601] VSEONGK01_Kummyung_Land Sale Balance Payment for Bunmae-ri 689-18_KRW 81000000 | F55: 81000000 | G55: 0
A56: 46030 | B56: KM-PV26-0014 | C56: 1112-KR-001 | D56: Cash - KRW (HANA) / 현금 - 원 (HANA) | E56: [KR Inv_202601] VSEONGK01_Kummyung_Land Sale Balance Payment for Bunmae-ri 689-18_KRW 81000000 | F56: 0 | G56: 81000000 | H56: HANA-KRW
A57: 46031 | B57: KM-JV26-0009 | C57: 5101-00-000 | D57: Management fee expense / 관리 수수료 비용 | E57: 12월 관리비 | F57: 327870 | G57: 0
A58: 46031 | B58: KM-JV26-0009 | C58: 2407-00-000 | D58: GST/VAT receivable / 부가세대급금 | E58: 12월 관리비 | F58: 32790 | G58: 0
A59: 46031 | B59: KM-JV26-0009 | C59: 2202-00-001 | D59: Other payable / 기타미지급금 | E59: 12월 관리비 | F59: 0 | G59: 360660 | H59: VSEJUNG01-2
A60: 46037 | B60: KM-JV26-0024 | C60: 2202-00-001 | D60: Other payable / 기타미지급금 | E60: Land Sale Balance Payment for Bunmae-ri 696-1_KRW 47500000 | F60: 0 | G60: 47500000 | H60: VJUNGHO01
A61: 46037 | B61: KM-JV26-0024 | C61: 1713-00-000 | D61: Land | E61: Land Sale Balance Payment for Bunmae-ri 696-1_KRW 47500000 | F61: 47500000 | G61: 0
A62: 46037 | B62: KM-JV26-0025 | C62: 2202-00-001 | D62: Other payable / 기타미지급금 | E62: Land Sale Down Payment for Bunmae-ri 689-19_KRW 7500000 | F62: 0 | G62: 7500000 | H62: VLEHYUN01
A63: 46037 | B63: KM-JV26-0025 | C63: 1713-00-000 | D63: Land | E63: Land Sale Down Payment for Bunmae-ri 689-19_KRW 7500000 | F63: 7500000 | G63: 0
A64: 46037 | B64: KM-JV26-0026 | C64: 2202-00-001 | D64: Other payable / 기타미지급금 | E64: Land Sale Down Payment for Bunmae-ri 686-16 (Oh, Seongyeol)_KRW 6500000 | F64: 0 | G64: 6500000 | H64: VLEHYUN01
A65: 46037 | B65: KM-JV26-0026 | C65: 1713-00-000 | D65: Land | E65: Land Sale Down Payment for Bunmae-ri 686-16 (Oh, Seongyeol)_KRW 6500000 | F65: 6500000 | G65: 0
A66: 46037 | B66: KM-JV26-0027 | C66: 2202-00-001 | D66: Other payable / 기타미지급금 | E66: Land Purchase Down Payment for Shinjang-ri 819-8_KRW 48000000 | F66: 0 | G66: 48000000 | H66: VLEHYUN01
A67: 46037 | B67: KM-JV26-0027 | C67: 1713-00-000 | D67: Land | E67: Land Purchase Down Payment for Shinjang-ri 819-8_KRW 48000000 | F67: 48000000 | G67: 0
A68: 46037 | B68: KM-JV26-0028 | C68: 2202-00-001 | D68: Other payable / 기타미지급금 | E68: Land Purchase Down Payment for Sinjang-ri 819-18_KRW 5000000 | F68: 0 | G68: 5000000 | H68: VLEHYUN01
A69: 46037 | B69: KM-JV26-0028 | C69: 1713-00-000 | D69: Land | E69: Land Purchase Down Payment for Sinjang-ri 819-18_KRW 5000000 | F69: 5000000 | G69: 0
A70: 46037 | B70: KM-JV26-0069 | C70: 5601-00-000 | D70: Other expenses / 잡손실 | E70: 수정_[KR Inv_202601] VSEJUNG01-2_Kummyung office maintenance fee inc. penalty fee _KRW 378,690 | F70: 396720 | G70: 0
A71: 46037 | B71: KM-JV26-0069 | C71: 1112-KR-001 | D71: Cash - KRW (HANA) / 현금 - 원 (HANA) | E71: 수정_[KR Inv_202601] VSEJUNG01-2_Kummyung office maintenance fee inc. penalty fee _KRW 378,690 | F71: 0 | G71: 396720 | H71: HANA-KRW
A72: 46037 | B72: KM-PV26-0001 | C72: 5601-00-000 | D72: Other expenses / 잡손실 | E72: [KR Inv_202601] VSEJUNG01-2_Kummyung office maintenance fee inc. penalty fee _KRW 378,690 | F72: 0 | G72: 378690
A73: 46037 | B73: KM-PV26-0001 | C73: 2202-00-001 | D73: Other payable / 기타미지급금 | E73: [KR Inv_202601] VSEJUNG01-2_Kummyung office maintenance fee inc. penalty fee _KRW 378,690 | F73: 360660 | G73: 0 | H73: VSEJUNG01-2
A74: 46037 | B74: KM-PV26-0001 | C74: 1112-KR-001 | D74: Cash - KRW (HANA) / 현금 - 원 (HANA) | E74: [KR Inv_202601] VSEJUNG01-2_Kummyung office maintenance fee inc. penalty fee _KRW 378,690 | F74: 18030 | G74: 0 | H74: HANA-KRW
A75: 46037 | B75: KM-PV26-0015 | C75: 2202-00-001 | D75: Other payable / 기타미지급금 | E75: [KR Inv_202601] VJUNGHO01_Kummyung_Land Sale Balance Payment for Bunmae-ri 696-1_KRW 47500000 | F75: 47500000 | G75: 0 | H75: VJUNGHO01
A76: 46037 | B76: KM-PV26-0015 | C76: 1112-KR-001 | D76: Cash - KRW (HANA) / 현금 - 원 (HANA) | E76: [KR Inv_202601] VJUNGHO01_Kummyung_Land Sale Balance Payment for Bunmae-ri 696-1_KRW 47500000 | F76: 0 | G76: 47500000 | H76: HANA-KRW
A77: 46037 | B77: KM-PV26-0016 | C77: 2202-00-001 | D77: Other payable / 기타미지급금 | E77: [KR Inv_202512] VLEHYUN01_Kummyung_Land Sale Down Payment for Bunmae-ri 689-19_KRW 7500000 | F77: 7500000 | G77: 0 | H77: VLEHYUN01
A78: 46037 | B78: KM-PV26-0016 | C78: 1112-KR-001 | D78: Cash - KRW (HANA) / 현금 - 원 (HANA) | E78: [KR Inv_202512] VLEHYUN01_Kummyung_Land Sale Down Payment for Bunmae-ri 689-19_KRW 7500000 | F78: 0 | G78: 7500000 | H78: HANA-KRW
A79: 46037 | B79: KM-PV26-0017 | C79: 2202-00-001 | D79: Other payable / 기타미지급금 | E79: [KR Inv_202601] VLEHYUN01_Kummyung_Land Sale Down Payment for Bunmae-ri 686-16 (Oh, Seongyeol)_KRW 6 | F79: 6500000 | G79: 0 | H79: VLEHYUN01
A80: 46037 | B80: KM-PV26-0017 | C80: 1112-KR-001 | D80: Cash - KRW (HANA) / 현금 - 원 (HANA) | E80: [KR Inv_202601] VLEHYUN01_Kummyung_Land Sale Down Payment for Bunmae-ri 686-16 (Oh, Seongyeol)_KRW 6 | F80: 0 | G80: 6500000 | H80: HANA-KRW
A81: 46037 | B81: KM-PV26-0018 | C81: 2202-00-001 | D81: Other payable / 기타미지급금 | E81: [KR Inv_202601] VLEHYUN01_Kummyung_Land Purchase Down Payment for Shinjang-ri 819-8_KRW 48000000 | F81: 48000000 | G81: 0 | H81: VLEHYUN01
A82: 46037 | B82: KM-PV26-0018 | C82: 1112-KR-001 | D82: Cash - KRW (HANA) / 현금 - 원 (HANA) | E82: [KR Inv_202601] VLEHYUN01_Kummyung_Land Purchase Down Payment for Shinjang-ri 819-8_KRW 48000000 | F82: 0 | G82: 48000000 | H82: HANA-KRW
A83: 46037 | B83: KM-PV26-0019 | C83: 2202-00-001 | D83: Other payable / 기타미지급금 | E83: [KR Inv_202601] VLEHYUN01_Kummyung_Land Purchase Down Payment for Sinjang-ri 819-18_KRW 5000000 | F83: 5000000 | G83: 0 | H83: VLEHYUN01
A84: 46037 | B84: KM-PV26-0019 | C84: 1112-KR-001 | D84: Cash - KRW (HANA) / 현금 - 원 (HANA) | E84: [KR Inv_202601] VLEHYUN01_Kummyung_Land Purchase Down Payment for Sinjang-ri 819-18_KRW 5000000 | F84: 0 | G84: 5000000 | H84: HANA-KRW
A85: 46044 | B85: KM-JV26-0029 | C85: 2202-00-001 | D85: Other payable / 기타미지급금 | E85: Land Sale Balance Payment for Sinjang-ri 819-18_KRW 40000000 | F85: 0 | G85: 40000000 | H85: VLINSUK01
A86: 46044 | B86: KM-JV26-0029 | C86: 1713-00-000 | D86: Land | E86: Land Sale Balance Payment for Sinjang-ri 819-18_KRW 40000000 | F86: 40000000 | G86: 0
A87: 46044 | B87: KM-JV26-0030 | C87: 2202-00-001 | D87: Other payable / 기타미지급금 | E87: Land Sale Balance Payment for Bunmae-ri 685-3_KRW 40000000 | F87: 0 | G87: 40000000
A88: 46044 | B88: KM-JV26-0030 | C88: 1713-00-000 | D88: Land | E88: Land Sale Balance Payment for Bunmae-ri 685-3_KRW 40000000 | F88: 40000000 | G88: 0
A89: 46044 | B89: KM-JV26-0031 | C89: 2202-00-001 | D89: Other payable / 기타미지급금 | E89: Land Sale Balance Payment for Bunmae-ri 685-2_KRW 27000000 | F89: 0 | G89: 27000000
A90: 46044 | B90: KM-JV26-0031 | C90: 1713-00-000 | D90: Land | E90: Land Sale Balance Payment for Bunmae-ri 685-2_KRW 27000000 | F90: 27000000 | G90: 0
A91: 46044 | B91: KM-JV26-0032 | C91: 2202-00-001 | D91: Other payable / 기타미지급금 | E91: Land Purchase Down Payment for Bunmae-ri 685-3_KRW 5000000 | F91: 0 | G91: 5000000 | H91: VLEHYUN01
A92: 46044 | B92: KM-JV26-0032 | C92: 1713-00-000 | D92: Land | E92: Land Purchase Down Payment for Bunmae-ri 685-3_KRW 5000000 | F92: 5000000 | G92: 0
A93: 46044 | B93: KM-JV26-0033 | C93: 2202-00-001 | D93: Other payable / 기타미지급금 | E93: Land Sale Down Payment for Bunmae-ri 696-1_KRW 5000000 | F93: 0 | G93: 5000000 | H93: VLEHYUN01
A94: 46044 | B94: KM-JV26-0033 | C94: 1713-00-000 | D94: Land | E94: Land Sale Down Payment for Bunmae-ri 696-1_KRW 5000000 | F94: 5000000 | G94: 0
A95: 46044 | B95: KM-JV26-0034 | C95: 2202-00-001 | D95: Other payable / 기타미지급금 | E95: Land Acquisition Tax for Bunmae-ri 689-19_KRW 3450000 | F95: 0 | G95: 3000000 | H95: VLEHYUN01
A96: 46044 | B96: KM-JV26-0034 | C96: 1713-00-000 | D96: Land | E96: Land Acquisition Tax for Bunmae-ri 689-19_KRW 3450000 | F96: 3000000 | G96: 0
A97: 46044 | B97: KM-JV26-0071 | C97: 5342-00-000 | D97: FX - realized loss - others / 외환차손 | E97: 수정_OTT260100615_EQUIS CENTRAL SERVICES (SINGAPORE) PTE LTD | F97: 67501 | G97: 0
A98: 46044 | B98: KM-JV26-0071 | C98: 5341-00-000 | D98: FX - realized gains - others / 외환차익 | E98: 수정_OTT260100615_EQUIS CENTRAL SERVICES (SINGAPORE) PTE LTD | F98: 0 | G98: 61520
A99: 46044 | B99: KM-JV26-0071 | C99: 2203-00-000 | D99: Intercompany Payable / 관계사미지급금 | E99: 수정_OTT260100615_EQUIS CENTRAL SERVICES (SINGAPORE) PTE LTD | F99: 0 | G99: 5981
A100: 46044 | B100: KM-JV26-0073 | C100: 5342-00-000 | D100: FX - realized loss - others / 외환차손 | E100: 최종수정_OTT260100615_EQUIS CENTRAL SERVICES (SINGAPORE) PTE LTD | F100: 410005 | G100: 0
A101: 46044 | B101: KM-JV26-0073 | C101: 5342-00-000 | D101: FX - realized loss - others / 외환차손 | E101: 최종수정_OTT260100615_EQUIS CENTRAL SERVICES (SINGAPORE) PTE LTD | F101: 0 | G101: 67501
...

Sheet Review→
G10: ='대출금,미지급이자,'!Q21 -> 0

Sheet 현금
B1: Balance Sheet Reconciliation
B2: Periode | C2: =CONTENTS!C2 -> 46112
B3: GL A/C | C3: 1112-KR-003
B4: A/C Name | C4: =VLOOKUP(C3, COA!$A$2:$C$187,3,0) -> Cash - KRW (Petty cash)
B6: Acc Number | C6: 명칭 | D6: 기준일 | E6: Amount | F6: Remark
B7: 1112-KR-003 | C7: 현금잔액 | D7: =C2 -> 46112 | E7: 0
E14: =SUM(E7:E13) -> 0 | F14: =VLOOKUP(C3,#REF!,6,0)=E14 -> #REF!

Sheet 은행
B1: Balance Sheet Reconciliation
B2: Periode | C2: =CONTENTS!C2 -> 46112
B3: GL A/C | C3: 1112-00-000 | D3: 1108-KR-001
B4: A/C Name | C4: =VLOOKUP(C3, COA!$A$2:$C$187,3,0) -> Cash - KRW | D4: =VLOOKUP(D3, COA!$A$2:$C$187,3,0) -> Cash - USD (HANA)
B6: Acc Number | C6: Acc Name | D6: Bank Number | E6: Amount | F6: Remark
B7: 1112-00-000 | C7: HANA BANK (주)하나은행 원화 (76804) | D7: 20191003076804 | E7: =#REF! -> #REF!
B8: 1108-KR-001 | C8: HANA BANK (주)하나은행 외화 (31538) | D8: 20191001531538 | E8: =외화!M72 -> 0 | F8: 매월 환산
E11: =SUM(E7:E10) -> #REF! | F11: =VLOOKUP("1112-00-000",#REF!,6,0)+VLOOKUP("1108-KR-001",#REF!,6,0)=E11 -> #REF!

Sheet 외상매출금
B1: Balance Sheet Reconciliation
B2: Periode | C2: =CONTENTS!C2 -> 46112
B3: GL A/C | C3: 1211-00-000
B4: A/C Name | C4: =VLOOKUP(C3, COA!$A$2:$C$187,3,0) -> Accounts receivables
B6: 거래처코드(사업자번호) | C6: 거래처명 | D6: 적요 | E6: 금액 | F6: Remark
E14: =SUM(E7:E12) -> 0 | F14: =VLOOKUP("1211-00-000",#REF!,6,0)=E14 -> #REF!

Sheet 선급금.
B1: Balance Sheet Reconciliation
B2: Periode | C2: =CONTENTS!C2 -> 46112
B3: GL A/C | C3: 1233-00-000 | D3: 1241-00-000 | E3: 1242-00-000
B4: A/C Name | C4: =VLOOKUP(C3, COA!$A$2:$C$187,3,0) -> Other prepaid and advances | D4: =VLOOKUP(D3, COA!$A$2:$C$187,3,0) -> Allowance for doubtful accounts - gen (non-tax) | E4: =VLOOKUP(E3, COA!$A$2:$C$187,3,0) -> Allowance for doubtful accounts - specific (tax)
B6: [토지 매매 대금]
B7: 거래처코드(사업자번호) | C7: 토지명(거래처명) | D7: 예금주 | E7: 계약금 지급일 | F7: 적요 | G7: 매매대금 | H7: 계약금 (선급금) | I7: 잔금 | J7: Remark
I19: =SUM(I8:I18) -> 0 | J19: =IFERROR(VLOOKUP("1233-00-000",#REF!,6,0),0)=I19 -> TRUE

Sheet BS(2025)
A2: 재 무 상 태 표
A3: 2025-12-31
A4: 회 사 명 : 금명 유한회사
B5: 과목 | C5: 2025/01/31 | D5: 2025/02/28 | E5: 2025/03/31수정 | F5: 2025/04/30 | G5: 2025/05/31 | H5: 2025/06/30 | I5: 2025/07/31 | J5: 2025/08/31 | K5: 2025/09/30 | L5: 2025/10/31 | M5: 45991 | N5: 46022
B6: 자산
B7: 유동자산 | C7: 437560895 | D7: 2187735445 | E7: 2160201863 | F7: =F8 -> 2131022540 | G7: =G8 -> 2116562144 | H7: =H8 -> 1700482255 | I7: =I8 -> 1596475959 | J7: =J8 -> 1560390759 | K7: 1430090367 | L7: 1153341825 | M7: 1113501315 | N7: 1569336905
B8: 당좌자산 | C8: 437560895 | D8: 2187735445 | E8: 2160201863 | F8: =F9+SUM(F12:F16) -> 2131022540 | G8: =G9+SUM(G12:G16) -> 2116562144 | H8: =H9+SUM(H12:H16) -> 1700482255 | I8: =I9+SUM(I12:I16) -> 1596475959 | J8: =J9+SUM(J12:J16) -> 1560390759 | K8: 1430090367 | L8: 1153341825 | M8: 1113501315 | N8: 1569336905
B9: 보통예금 | C9: 353722162 | D9: 2126887381 | E9: 2100199039 | F9: =F10+F11 -> 2069585036 | G9: =G10+G11 -> 2040685246 | H9: =H10+H11 -> 1622715967 | I9: =I10+I11 -> 1502337730 | J9: =J10+J11 -> 1501033910 | K9: 1322773116 | L9: 1027189242 | M9: 988195702 | N9: 1405309172
B10: 현금 - 원 (HANA) | C10: 325492654 | D10: 2106438696 | E10: 2088413367 | F10: 2015361007 | G10: 1986461217 | H10: 1622544607 | I10: 1461307727 | J10: 1460003907 | K10: 1296810947 | L10: 1008884497 | M10: 969890957 | N10: 1402060267
B11: 현금 - 원 (신협) | C11: 28229508 | D11: 20448685 | E11: 11785672 | F11: 54224029 | G11: 54224029 | H11: 171360 | I11: 41030003 | J11: 41030003 | K11: 25962169 | L11: 18304745 | M11: 18304745 | N11: 3248905
B12: 선납세금 | C12: 237430 | D12: 237430 | E12: 268490 | F12: 162890 | G12: 152350 | H12: 239010 | I12: 239010 | J12: 239010 | K12: 296840 | L12: 296840 | M12: 296840 | N12: 340300
B13: 기타미수금 | C13: 58586042 | D13: 36539357 | E13: 36539357 | F13: 36539357 | G13: 36539357 | H13: 36539357 | I13: 36539357 | J13: 36539357 | K13: 36539357 | L13: 36539357 | M13: 36539357 | N13: 36539357
B14: 선급비용 | C14: 10000000 | D14: 9000000 | E14: 8000000 | F14: 7000000 | G14: 6000000 | H14: 5000000 | I14: 4000000 | J14: 3000000 | K14: 2000000 | L14: 1000000
B15: 선급금 (유동) | C15: 43834 | D15: 0 | E15: 0 | F15: 0 | G15: 0 | H15: 0 | I15: 0 | J15: 0
B16: 부가세대급금 | C16: 14971427 | D16: 15071277 | E16: 15194977 | F16: 17735257 | G16: 33185191 | H16: 35987921 | I16: 53359862 | J16: 19578482 | K16: =53287182+15193872 -> 68481054 | L16: 88316386 | M16: 88469416 | N16: 127148076
B17: 재고자산 | C17: 0 | D17: 0 | E17: 0 | F17: 0 | G17: 0 | H17: 0 | I17: 0 | J17: 0
B18: 비유동자산 | C18: =C20+C24 -> 6803649004 | D18: =D20+D24 -> 7055649004 | E18: =E20+E24 -> 7067571004 | F18: =F20+F24 -> 7087971834 | G18: =G20+G24 -> 7107971834 | H18: =H20+H24 -> 7477401834 | I18: =I20+I24 -> 7574943234 | J18: =J20+J24 -> 7611176534 | K18: 7948686044 | L18: 7992186044 | M18: 7992186044 | N18: 8577016044
B19: 투자자산 | C19: 0 | D19: 0 | E19: 0 | F19: 0 | H19: 0 | I19: 0
B20: 유형자산 | C20: 6782669004 | D20: 7034669004 | E20: 7046591004 | F20: 7066991834 | G20: 7086991834 | H20: 7456421834 | I20: 7553963234 | J20: =J21+J22 -> 7590196534 | K20: 7927706044 | L20: 7971206044 | M20: 7971206044 | N20: 8556036044
B21: 토지 | C21: 6782669004 | D21: 7034669004 | E21: 7046591004 | F21: 7046991834 | G21: 7046991834 | H21: 7390421834 | I21: 7467963234 | J21: 7484196534 | K21: 7485994044 | L21: 7485994044 | M21: 7485994044 | N21: 7684424044
B22: 건설중인자산 | F22: 20000000 | G22: 40000000 | H22: 66000000 | I22: 86000000 | J22: 106000000 | K22: 441712000 | L22: 485212000 | M22: 485212000 | N22: 871612000
B23: 무형자산 | C23: 0 | D23: 0 | H23: 0 | I23: 0
B24: 기타비유동자산 | C24: 20980000 | D24: 20980000 | E24: 20980000 | F24: 20980000 | G24: 20980000 | H24: 20980000 | I24: 20980000 | J24: 20980000 | K24: 20980000 | L24: 20980000 | M24: 20980000 | N24: 20980000
B25: 임차보증금 - 비유동 | C25: 20980000 | D25: 20980000 | E25: 20980000 | F25: 20980000 | G25: 20980000 | H25: 20980000 | I25: 20980000 | J25: 20980000 | K25: 20980000 | L25: 20980000 | M25: 20980000 | N25: 20980000
B26: 자산 총 계 | C26: =C7+C18 -> 7241209899 | D26: =D7+D18 -> 9243384449 | E26: =E7+E18 -> 9227772867 | F26: =F7+F18 -> 9218994374 | G26: =G7+G18 -> 9224533978 | H26: =H7+H18 -> 9177884089 | I26: =I7+I18 -> 9171419193 | J26: =J7+J18 -> 9171567293 | K26: 9378776411 | L26: 9145527869 | M26: 9105687359 | N26: 10146352949
B27: 부채 | K27: 8210031197 | L27: 8210608130 | M27: 8257356272 | N27: 9317747503
B28: 유동부채 | C28: =SUM(C29:C32) -> 528342217 | D28: =SUM(D29:D32) -> 10290632 | E28: =SUM(E29:E32) -> 9324016 | F28: =SUM(F29:F32) -> 14501977 | G28: =SUM(G29:G32) -> 164632033 | H28: =SUM(H29:H32) -> 168146351 | I28: =SUM(I29:I32) -> 325445602 | J28: =SUM(J29:J32) -> 336942537 | K28: 705516623 | L28: 637898272 | M28: 608615571 | N28: 16535838
B29: 계약부채 | E29: 0 | F29: 0 | G29: 0 | H29: 0 | I29: 0
B30: 기타미지급금 | C30: 8414960 | D30: 7699960 | E30: 6691670 | F30: 11877570 | G30: 5366720 | H30: 15248720 | I30: 5931720 | J30: 9748720 | K30: 218831250 | L30: 43381250 | M30: 6091250 | N30: 7091250
B31: 관계사미지급금 | C31: 519927257 | D31: 2590672 | E31: 2632346 | F31: 2624407 | G31: 151451615 | H31: 151415549 | I31: 319515733 | J31: 319538244 | K31: =319554631+167132593 -> 486687224 | L31: 594518873 | M31: 595115762 | N31: 9446439
B32: 미지급이자비용 - 일반 대출 -단기 | G32: 7813698 | H32: 1482082 | I32: -1851 | J32: 7655573 | K32: -1851 | L32: -1851 | M32: 7408559 | N32: -1851
B33: 비유동부채 | C33: =SUM(C34:C36) -> 4968700549 | D33: =SUM(D34:D36) -> 7527834509 | E33: =SUM(E34:E36) -> 7565423393 | F33: =SUM(F34:F36) -> 7547100636 | G33: =SUM(G34:G36) -> 7477364720 | H33: =SUM(H34:H36) -> 7409379563 | I33: =SUM(I34:I36) -> 7446053247 | J33: =SUM(J34:J36) -> 7480826131 | K33: 7504514574 | L33: 7572709858 | M33: 7648740701 | N33: 9301211665
B34: 은행 대출 | C34: 2000000000 | D34: 2000000000 | E34: 2000000000 | F34: 2000000000 | G34: 2000000000 | H34: 1960000000 | I34: 1960000000 | J34: 1960000000 | K34: 1960000000 | L34: 1960000000 | M34: 1960000000 | N34: 1960000000
B35: 관계사 대출 - 장기 | C35: 1321408000 | D35: 3866350400 | E35: 3888227200 | F35: 3854699200 | G35: 3769251200 | H35: 3726060800 | I35: 3747022400 | J35: 3766083200 | K35: 3774566400 | L35: 3827049600 | M35: 3887875200 | N35: 5524634080
B36: 미지급이자비용 - 관계사 대출 - 장기 | C36: 1647292549 | D36: 1661484109 | E36: 1677196193 | F36: 1692401436 | G36: 1708113520 | H36: 1723318763 | I36: 1739030847 | J36: 1754742931 | K36: 1769948174 | L36: 1785660258 | M36: 1800865501 | N36: 1816577585
B37: 부채 총 계 | C37: =C33+C28 -> 5497042766 | D37: =D33+D28 -> 7538125141 | E37: =E33+E28 -> 7574747409 | F37: =F33+F28 -> 7561602613 | G37: =G33+G28 -> 7641996753 | H37: =H33+H28 -> 7577525914 | I37: =I33+I28 -> 7771498849 | J37: =J33+J28 -> 7817768668 | K37: 8210031197 | L37: 8210608130 | M37: 8257356272 | N37: 9317747503
B38: 자본 | K38: 1168745214 | L38: 934919739 | M38: 848331087 | N38: 828605446
B39: 자본금 | C39: 4004550000 | D39: 4004550000 | E39: 4004550000 | F39: 4004550000 | G39: 4004550000 | H39: 4004550000 | I39: 4004550000 | J39: 4004550000 | K39: 4004550000 | L39: 4004550000 | M39: 4004550000 | N39: 4004550000
B40: 보통주 | C40: 4004550000 | D40: 4004550000 | E40: 4004550000 | F40: 4004550000 | G40: 4004550000 | H40: 4004550000 | I40: 4004550000 | J40: 4004550000 | K40: 4004550000 | L40: 4004550000 | M40: 4004550000 | N40: 4004550000
B41: 자본잉여금 | C41: 0 | D41: 0 | E41: 0
B42: 자본 조정 | C42: -1373878747 | D42: -1373878747 | E42: -1373878747 | F42: -1373878747 | G42: -1373878747 | H42: -1373878747 | I42: -1373878747 | J42: -1373878747 | K42: -1373878747 | L42: -1373878747 | M42: -1373878747 | N42: -1373878747
B43: 감자차손 | C43: -1347557747 | D43: -1347557747 | E43: -1347557747 | F43: -1347557747 | G43: -1347557747 | H43: -1347557747 | I43: -1347557747 | J43: -1347557747 | K43: -1347557747 | L43: -1347557747 | M43: -1347557747 | N43: -1347557747
B44: 주식할인 발행차금 | C44: -26321000 | D44: -26321000 | E44: -26321000 | F44: -26321000 | G44: -26321000 | H44: -26321000 | I44: -26321000 | J44: -26321000 | K44: -26321000 | L44: -26321000 | M44: -26321000 | N44: -26321000
B45: 기타포괄손익 | C45: 0 | D45: 0 | E45: 0
B46: 이익잉여금 | C46: -886504120 | D46: -925411945 | E46: -977645795 | F46: -973279492 | G46: -1048134028 | H46: -1030313078 | I46: -1230750909 | J46: -1276872628 | K46: -1461926039 | L46: -1695751514 | M46: -1782340166 | N46: -1802065807
B47: 이익 잉여금 | C47: -839391686 | D47: -839391686 | E47: -839391686 | F47: -839391686 | G47: -839391686 | H47: -839391686 | I47: -839391686 | J47: -839391686 | K47: -839391686 | L47: -839391686 | M47: -839391686 | N47: -839391686
B48: 당기순이익 | C48: -47112434 | D48: -86020259 | E48: -138254109 | F48: -133887806 | G48: -208742342 | H48: -190921392 | I48: -391359223 | J48: -437480942 | K48: -606319113 | L48: -735178188 | M48: -743165240 | N48: -802545873
B49: 자본 총 계 | C49: 1744167133 | D49: 1705259308 | E49: 1653025458 | F49: 1657391761 | G49: 1582537225 | H49: 1600358175 | I49: 1399920344 | J49: 1353798625 | K49: 1168745214 | L49: 934919739 | M49: 848331087 | N49: 828605446
B50: 자본 및 부채 총 계 | C50: 7241209899 | D50: 9243384449 | E50: 9227772867 | F50: 9218994374 | G50: 9224533978 | H50: 9177884089 | I50: 9171419193 | J50: 9171567293 | K50: 9378776411 | L50: 9145527869 | M50: 9105687359 | N50: 10146352949
B55: 24년도 당기순이익 ->이잉
B56: 계약부채 결산 분개 미적용으로 인한 당기손익 영향 | C56: 58318120
B57: 외상매출금 -> 기타미수금으로 reclass | C57: 36539357
B58: 임대토지 -> 토지로 reclass | C58: 6782669004

Sheet IS(2025)
A2: 손 익 계 산 서
A3: 2025/01/01~2025/12/31
A4: 회 사 명 : 금명 유한회사 | O4: (단위:원)
B5: 과목 | C5: 2025/01/31 | D5: 2025/02/28 | E5: 2025/03/31 | F5: 2025/04/30 | G5: 2025/05/31 | H5: 2025/06/30 | I5: 2025/07/31 | J5: 2025/08/31 | K5: 2025/09/30 | L5: 2025/10/31 | M5: 2025/11/30 | N5: 2025/12/31 | O5: 2025/01/01~2025/12/31
B6: 매출 | C6: 0 | D6: 0 | I6: 0 | O6: 0
B7: 매출원가 | C7: 0 | D7: 0 | O7: 0
B8: 매출총이익 | C8: 0 | D8: 0 | O8: 0
B9: 판매비와 관리비 | C9: =SUM(C10:C20) -> 22738100 | D9: =SUM(D10:D20) -> 4589202 | E9: =SUM(E10:E20) -> 6142020 | F9: =SUM(F10:F20) -> 6402750 | G9: =SUM(G10:G20) -> 136808848 | H9: =SUM(H10:H20) -> 3027270 | I9: =SUM(I10:I20) -> 156055923 | J9: =SUM(J10:J20) -> 3649350 | K9: 154313751 | L9: 157907802 | M9: 2532340 | N9: 3610290 | O9: =SUM(C9:N9) -> 657777646
B10: 관리 수수료 비용 | C10: 333100 | D10: 332530 | E10: 383020 | F10: 347750 | G10: 359160 | H10: 327270 | I10: 340670 | J10: 355350 | K10: 375030 | L10: 326220 | M10: 330340 | N10: 378570 | O10: =SUM(C10:N10) -> 4189010
B11: 공유 서비스 비용 | C11: 0 | D11: 2590672 | F11: 0 | G11: 1309547 | I11: 925532 | L11: 2054463 | O11: =SUM(C11:N11) -> 6880214
B12: 기타 법률 및 전문 수수료 | C12: 1400000 | D12: 650000 | E12: 850000 | F12: 5051000 | G12: 0 | H12: 1700000 | I12: 1250000 | J12: 2200000 | K12: 1000000 | L12: 2100000 | O12: =SUM(C12:N12) -> 16201000
B13: 관리운용비용 | G13: 134136141 | H13: 0 | I13: 151938721 | K13: 151938721 | L13: 96102019 | M13: 248040740 | N13: 2223720 | O13: =SUM(C13:N13) -> 784380062
B14: 지급임차료 | C14: 1000000 | D14: 1000000 | E14: 1000000 | F14: 1000000 | G14: 1000000 | H14: 1000000 | I14: 1000000 | J14: 1000000 | K14: 1000000 | L14: 1000000 | M14: 1000000 | N14: 1000000 | O14: =SUM(C14:N14) -> 12000000
B15: 광고비용 | E15: =3550000+355000 -> 3905000 | F15: 0 | G15: 0 | H15: 0 | I15: 600000 | O15: =SUM(C15:N15) -> 4505000
B16: 은행 수수료 | C16: 5000 | D16: 16000 | E16: 4000 | F16: 4000 | G16: 4000 | H16: 0 | I16: 1000 | L16: 4000 | M16: 2000 | N16: 8000 | O16: =SUM(C16:N16) -> 48000
B17: 기부금 | C17: 20000000 | I17: 0 | O17: =SUM(C17:N17) -> 20000000
B18: 기타 운영 비용 | L18: 600000 | M18: 1200000 | O18: =SUM(C18:N18) -> 1800000
B19: 여비교통비 | J19: 39000 | O19: =SUM(C19:N19) -> 39000
B20: 세금과 공과 | J20: 55000 | L20: 55721100 | O20: =SUM(C20:N20) -> 55776100
B21: 영업이익 | C21: =-C9 -> -22738100 | D21: =-D9 -> -4589202 | E21: =-E9 -> -6142020 | F21: =-F9 -> -6402750 | G21: =-G9 -> -136808848 | H21: =-H9 -> -3027270 | I21: =-I9 -> -156055923 | J21: =-J9 -> -3649350 | K21: -154313751 | L21: -157907802 | M21: -2532340 | N21: -3610290 | O21: =SUM(C21:N21) -> -657777646
B22: 영업외수익 | C22: =SUM(C23:C25) -> 0 | D22: =SUM(D23:D25) -> 0 | E22: =SUM(E23:E25) -> 201741 | F22: =SUM(F23:F25) -> 11651200 | G22: =SUM(G23:G25) -> 85448000 | H22: =SUM(H23:H25) -> 43787598 | I22: =SUM(I23:I25) -> -20986026 | J22: =SUM(J23:J25) -> -19060800 | K22: 8107620 | L22: 52483200 | M22: 39300800 | N22: -19827496 | O22: =SUM(C22:N22) -> 181105837
B23: 이자수익 - 은행 | E23: 201741 | F23: =_xlfn.XLOOKUP(B23,[1]IS!$B:$B,[1]IS!$D:$D) -> 0 | H23: 562773 | K23: 375580 | N23: 282376 | O23: =SUM(C23:N23) -> 1422470
B24: 외화환산이익 | F24: 11651200 | G24: 85448000 | H24: 43224825 | I24: -20996025 | J24: -19060800 | K24: 8483200 | L24: 52483200 | M24: 39300800 | O24: =SUM(C24:N24) -> 200534400
B25: 잡이익 | I25: 9999 | O25: =SUM(C25:N25) -> 9999
B26: 외환차익 | N26: -19545120 | O26: =SUM(C26:N26) -> -19545120
B27: 영업외비용 | C27: =SUM(C28:C33) -> 24374334 | D27: =SUM(D28:D33) -> 34318623 | E27: =SUM(E28:E33) -> 46293571 | F27: =SUM(F28:F33) -> 882147 | G27: =SUM(G28:G33) -> 23493688 | H27: =SUM(H28:H33) -> 22939378 | I27: =SUM(I28:I33) -> 23395882 | J27: =SUM(J28:J33) -> 23411569 | K27: 22632040 | L27: 23434473 | M27: 44755512 | N27: 35942847 | O27: =SUM(C27:N27) -> 325874064
B28: 외환차손 | C28: 0 | D28: 12302400 | E28: 0 | F28: =_xlfn.XLOOKUP(B28,[1]IS!$B:$B,[1]IS!$D:$D) -> 0 | G28: =_xlfn.XLOOKUP(B28,[1]IS!$B:$B,[1]IS!$C:$C) -> 0 | H28: 0 | O28: =SUM(C28:N28) -> 12302400
B29: 잡손실 | C29: 0 | D29: 6 | E29: 0 | F29: =_xlfn.XLOOKUP(B29,[1]IS!$B:$B,[1]IS!$D:$D) -> 0 | G29: =_xlfn.XLOOKUP(B29,[1]IS!$B:$B,[1]IS!$C:$C) -> 0 | H29: 0 | I29: 18740 | J29: 19550 | M29: 18170 | N29: 20820 | O29: =SUM(C29:N29) -> 77286
B30: 이자비용 - 회사 간 대출 | C30: 15712084 | D30: 14191560 | E30: 15712084 | F30: 15205243 | G30: 15712084 | H30: 15205243 | I30: 15712084 | J30: 15712084 | K30: 15205243 | L30: 15712084 | M30: 15205243 | N30: 15712084 | O30: =SUM(C30:N30) -> 184997120
B31: 이자비용 - 일반 | C31: 8662250 | D31: 7824657 | E31: 8663013 | F31: 7561643 | G31: 7813698 | H31: 7531397 | I31: 7657424 | J31: 7657424 | K31: 7410410 | L31: 7657424 | M31: 7410410 | N31: 7657424 | O31: =SUM(C31:N31) -> 93507174
B32: 외화환산손실 | E32: 21918474 | F32: -21884739 | G32: -32094 | H32: -1641 | I32: 7634 | J32: 22511 | K32: 16387 | L32: 64965 | M32: 22121689 | N32: 12552519 | O32: =SUM(C32:N32) -> 34785705
B33: 기타 금융 비용 | H33: 204379 | O33: =SUM(C33:N33) -> 204379
B34: 법인세 비용 차감전 순이익 | C34: =C21+C22-C27 -> -47112434 | D34: =D21+D22-D27 -> -38907825 | E34: =E21+E22-E27 -> -52233850 | F34: =F21+F22-F27 -> 4366303 | G34: =G21+G22-G27 -> -74854536 | H34: =H21+H22-H27 -> 17820950 | I34: =I21+I22-I27 -> -200437831 | J34: =J21+J22-J27 -> -46121719 | K34: -168838171 | L34: -128859075 | M34: -7987052 | N34: -59380633 | O34: =SUM(C34:N34) -> -802545873
B35: 소득세와 법인세 | C35: 0 | D35: 0 | O35: =SUM(C35:N35) -> 0
B36: 당기순이익 | C36: -47112434 | D36: =D34 -> -38907825 | E36: =E34 -> -52233850 | F36: =F34 -> 4366303 | G36: =G34 -> -74854536 | H36: =H34 -> 17820950 | I36: =I34 -> -200437831 | J36: =J34 -> -46121719 | K36: -168838171 | L36: -128859075 | M36: -7987052 | N36: -59380633 | O36: =SUM(C36:N36) -> -802545873
K38: =SUM(C36:K36) -> -606319113 | L38: =SUM(C36:L36) -> -735178188 | M38: =SUM(D36:M36) -> -696052806 | N38: =SUM(E36:N36) -> -716525614
C39: =C21-C27 -> -47112434 | D39: =D21-D27 -> -38907825 | E39: =E21-E27+E22 -> -52233850 | F39: =F21-F27+F22 -> 4366303 | G39: =G21-G27+G22 -> -74854536 | H39: =H21-H27+H22 -> 17820950 | I39: =I21-I27+I22 -> -200437831 | J39: =J21-J27+J22 -> -46121719 | K39: =K21-K27+K22 -> -168838171 | L39: =L21-L27+L22 -> -128859075 | ... N39: =N21-N27+N22 -> -59380633
C40: =C36=C39 -> TRUE | D40: =D36=D39 -> TRUE | E40: =E36=E39 -> TRUE | F40: =F36=F39 -> TRUE | G40: =G36=G39 -> TRUE | H40: =H36=H39 -> TRUE | I40: =I36=I39 -> TRUE | J40: =J36=J39 -> TRUE | ... N40: =N36=N39 -> TRUE

Sheet JE(2025)
A1: Posting Date2 | B1: Document No. | C1: G/L Account No. | D1: G/L Account Name | E1: Description | F1: Debit Amount (LCY) | G1: Credit Amount (LCY) | H1: Vendor Code
A2: 2025-01-02 | B2: GJ25-0001 | C2: 5301-00-000 | D2: Bank charges / 은행 수수료 | E2: (HTX)_공인인증서(은행/보험용) / 은행 수수료 | F2: 4000 | G2: 0
A3: 2025-01-02 | B3: GJ25-0001 | C3: 2407-00-000 | D3: GST/VAT receivable / 부가세대급금 | E3: (HTX)_공인인증서(은행/보험용) / 부가세대급금 | F3: 400 | G3: 0
A4: 2025-01-02 | B4: GJ25-0001 | C4: 2202-00-001 | D4: Other payable / 기타미지급금 | E4: (HTX)_공인인증서(은행/보험용) / 기타미지급금 | F4: 0 | G4: 4400
A5: 2025-01-02 | B5: GJ25-0002 | C5: 5301-00-000 | D5: Bank charges / 은행 수수료 | E5: [KR Inv_202412] VJIPYON02_Kummyung_Registration fee for debt to equity_KRW 23487000 _ 은행 수수료 | F5: 500 | G5: 0
A6: 2025-01-02 | B6: GJ25-0002 | C6: 2202-00-001 | D6: Other payable / 기타미지급금 | E6: [KR Inv_202412] VJIPYON02_Kummyung_Registration fee for debt to equity_KRW 23487000 _ 기타미지급금 | F6: 23487000 | G6: 0
A7: 2025-01-02 | B7: GJ25-0002 | C7: 1112-KR-001 | D7: Cash - KRW (HANA) / 현금 - 원 (HANA) | E7: [KR Inv_202412] VJIPYON02_Kummyung_Registration fee for debt to equity_KRW 23487000 _ 현금 - 원 (HANA) | F7: 0 | G7: 23487500
A8: 2025-01-02 | B8: GJ25-0003 | C8: 5301-00-000 | D8: Bank charges / 은행 수수료 | E8: [KR Inv_202411] VNEULSA01_Kummyung_Real estate transaction amount_KRW 12000000 _ 은행 수수료 | F8: 500 | G8: 0
A9: 2025-01-02 | B9: GJ25-0003 | C9: 2202-00-001 | D9: Other payable / 기타미지급금 | E9: [KR Inv_202411] VNEULSA01_Kummyung_Real estate transaction amount_KRW 12000000 _ 기타미지급금 | F9: 12000000 | G9: 0
A10: 2025-01-02 | B10: GJ25-0003 | C10: 1112-KR-001 | D10: Cash - KRW (HANA) / 현금 - 원 (HANA) | E10: [KR Inv_202411] VNEULSA01_Kummyung_Real estate transaction amount_KRW 12000000 _ 현금 - 원 (HANA) | F10: 0 | G10: 12000500
A11: 2025-01-02 | B11: GJ25-0004 | C11: 2202-00-001 | D11: Other payable / 기타미지급금 | E11: Issuance Fee payment _ 기타미지급금 | F11: 4400 | G11: 0
A12: 2025-01-02 | B12: GJ25-0004 | C12: 1112-KR-001 | D12: Cash - KRW (HANA) / 현금 - 원 (HANA) | E12: Issuance Fee payment _ 기타미지급금 | F12: 0 | G12: 4400
A13: 2025-01-08 | B13: GJ25-0005 | C13: 5319-00-000 | D13: Donations / 기부금 | E13: [KR Inv_202501] VCOMNAM01_Project Phantom - Jeju Air Passenger Plane Crash Victim Charity_KRW 200000 | F13: 20000000 | G13: 0
... A58: 2025-01-31 | B58: GJ25-0075 | C58: 2203-00-000 | D58: Intercompany Payable / 관계사미지급금 | E58: Intercompany Payable / 관계사미지급금 | F58: 147977175 | G58: 0
A59: 2025-02-03 | B59: GJ25-0019 | C59: 5106-00-000 | D59: Shared service charges / 공유 서비스 비용 | E59: IECSG001-INV25-0041(SGD 2413.07*@ 1,073.60)_ECSS PL Equis Central Service Singapore Pte. Ltd. | F59: 2767811966 | G59: 0 | H59: IECSG001
A60: 2025-02-03 | B60: GJ25-0019 | C60: 2203-00-000 | D60: Intercompany Payable / 관계사미지급금 | E60: IECSG001-INV25-0041(SGD 2413.07*@ 1,073.60)_ECSS PL Equis Central Service Singapore Pte. Ltd. | F60: 0 | G60: 2767811966 | H60: IECSG001
A61: 2025-02-03 | B61: GJ25-0047 | C61: 5106-00-000 | D61: Shared service charges / 공유 서비스 비용 | E61: IECSG001-INV25-0041(SGD 2413.07*@ 1,073.60)_ECSS PL Equis Central Service Singapore Pte. Ltd. | F61: 0 | G61: 2767811966 | H61: IECSG001
A62: 2025-02-03 | B62: GJ25-0047 | C62: 2203-00-000 | D62: Intercompany Payable / 관계사미지급금 | E62: IECSG001-INV25-0041(SGD 2413.07*@ 1,073.60)_ECSS PL Equis Central Service Singapore Pte. Ltd. | F62: 2767811966 | G62: 0 | H62: IECSG001
A63: 2025-02-03 | B63: GJ25-0048 | C63: 5106-00-000 | D63: Shared service charges / 공유 서비스 비용 | E63: Mgmt & Shared Service Fee Q4 2024-Keummyeong Co. Ltd_ECSS PL Equis Central Service Singapore Pte. Lt | F63: 2590672 | G63: 0 | H63: IECSG001
A64: 2025-02-03 | B64: GJ25-0048 | C64: 2203-00-000 | D64: Intercompany Payable / 관계사미지급금 | E64: IECSG001-INV25-0041(SGD 2413.07*@ 1,073.60)_ECSS PL Equis Central Service Singapore Pte. Ltd. | F64: 0 | G64: 2590672 | H64: IECSG001
A65: 2025-02-06 | B65: GJ25-0020 | C65: 5301-00-000 | D65: Bank charges / 은행 수수료 | E65: 공인인증서(은행/보험용)_HANA BANK (주)하나은행_HANA BANK (주)하나은행 | F65: 4000 | G65: 0 | H65: VHANABA01
A66: 2025-02-06 | B66: GJ25-0020 | C66: 2407-00-000 | D66: GST/VAT receivable / 부가세대급금 | E66: 공인인증서(은행/보험용)_HANA BANK (주)하나은행_HANA BANK (주)하나은행 | F66: 400 | G66: 0 | H66: VHANABA01
A67: 2025-02-06 | B67: GJ25-0020 | C67: 2202-00-001 | D67: Other payable / 기타미지급금 | E67: 공인인증서(은행/보험용)_HANA BANK (주)하나은행_HANA BANK (주)하나은행 | F67: 0 | G67: 4400 | H67: VHANABA01
A68: 2025-02-06 | B68: GJ25-0021 | C68: 2202-00-001 | D68: Other payable / 기타미지급금 | E68: Issuance Fee payment_HANA BANK (주)하나은행 | F68: 4400 | G68: 0 | H68: VHANABA01
A69: 2025-02-06 | B69: GJ25-0021 | C69: 1112-KR-001 | D69: Cash - KRW (HANA) / 현금 - 원 (HANA) | E69: Issuance Fee payment_HANA BANK (주)하나은행 | F69: 0 | G69: 4400 | H69: VHANABA01
A70: 2025-02-10 | B70: GJ25-0022 | C70: 5101-00-000 | D70: Management fee expense / 관리 수수료 비용 | E70: 관리비_세정아울렛 관리단_세정아울렛 관리단 | F70: 332530 | G70: 0 | H70: VSEJUNG01
... A128: 2025-02-28 | B128: GJ25-0046 | C128: 1232-00-000 | D128: Prepaid expenses / 선급비용 | E128: Office rent_유한회사 삼형 | F128: 0 | G128: 1000000 | H128: VSAMHYO01
A129: 2025-03-06 | B129: GJ25-0049 | C129: 5301-00-000 | D129: Bank charges / 은행 수수료 | E129: 공인인증서(은행/보험용)_HANA BANK (주)하나은행 | F129: 4000 | G129: 0
A130: 2025-03-06 | B130: GJ25-0049 | C130: 2407-00-000 | D130: GST/VAT receivable / 부가세대급금 | E130: 공인인증서(은행/보험용)_HANA BANK (주)하나은행 | F130: 400 | G130: 0
A131: 2025-03-06 | B131: GJ25-0049 | C131: 2202-00-001 | D131: Other payable / 기타미지급금 | E131: 공인인증서(은행/보험용)_HANA BANK (주)하나은행 | F131: 0 | G131: 4400
A132: 2025-03-06 | B132: GJ25-0055 | C132: 2202-00-001 | D132: Other payable / 기타미지급금 | E132: Issuance Fee payment | F132: 4400 | G132: 0 | H132: VHANABA01
A133: 2025-03-06 | B133: GJ25-0055 | C133: 1112-KR-001 | D133: Cash - KRW (HANA) / 현금 - 원 (HANA) | E133: Issuance Fee payment | F133: 0 | G133: 4400 | H133: VHANABA01
A134: 2025-03-10 | B134: GJ25-0050 | C134: 5101-00-000 | D134: Management fee expense / 관리 수수료 비용 | E134: 관리비_세정아울렛 관리단 | F134: 383018 | G134: 0
A135: 2025-03-10 | B135: GJ25-0050 | C135: 2407-00-000 | D135: GST/VAT receivable / 부가세대급금 | E135: 관리비_세정아울렛 관리단 | F135: 38302 | G135: 0
A136: 2025-03-10 | B136: GJ25-0050 | C136: 2202-00-001 | D136: Other payable / 기타미지급금 | E136: 관리비_세정아울렛 관리단 | F136: 0 | G136: 421320
A137: 2025-03-10 | B137: GJ25-0069 | C137: 5101-00-000 | D137: Management fee expense / 관리 수수료 비용 | E137: 수정분개 | F137: 0 | G137: 383018 | H137: VSEJUNG01
A138: 2025-03-10 | B138: GJ25-0069 | C138: 2407-00-000 | D138: GST/VAT receivable / 부가세대급금 | E138: 수정분개 | F138: 0 | G138: 38302 | H138: VSEJUNG01
A139: 2025-03-10 | B139: GJ25-0069 | C139: 2202-00-001 | D139: Other payable / 기타미지급금 | E139: 수정분개 | F139: 421320 | G139: 0 | H139: VSEJUNG01
A140: 2025-03-10 | B140: GJ25-0070 | C140: 5101-00-000 | D140: Management fee expense / 관리 수수료 비용 | E140: 관리비_세정아울렛 관리단 | F140: 383020 | G140: 0 | H140: VSEJUNG01
A141: 2025-03-10 | B141: GJ25-0070 | C141: 2407-00-000 | D141: GST/VAT receivable / 부가세대급금 | E141: 관리비_세정아울렛 관리단 | F141: 38300 | G141: 0 | H141: VSEJUNG01
A142: 2025-03-10 | B142: GJ25-0070 | C142: 2202-00-001 | D142: Other payable / 기타미지급금 | E142: 관리비_세정아울렛 관리단 | F142: 0 | G142: 421320 | H142: VSEJUNG01
A143: 2025-03-13 | B143: GJ25-0051 | C143: 5263-00-000 | D143: Advertising / 광고비용 | E143: 신안군기념품(타올)구입_유한회사 파란디 | F143: 2727273 | G143: 0 | H143: VPRDLTD01
A144: 2025-03-13 | B144: GJ25-0051 | C144: 2407-00-000 | D144: GST/VAT receivable / 부가세대급금 | E144: 신안군기념품(타올)구입_유한회사 파란디 | F144: 272727 | G144: 0 | H144: VPRDLTD01
A145: 2025-03-13 | B145: GJ25-0051 | C145: 2202-00-001 | D145: Other payable / 기타미지급금 | E145: 신안군기념품(타올)구입_유한회사 파란디 | F145: 0 | G145: 3000000 | H145: VPRDLTD01
A146: 2025-03-15 | B146: GJ25-0056 | C146: 5612-00-000 | D146: Interest income - bank / 이자수익 - 은행 | E146: bank interest income(예금이자 201,741 소득세 28,240 지방소득세 2,820) | F146: 0 | G146: 201741 | H146: VHANABA01
A147: 2025-03-15 | B147: GJ25-0056 | C147: 1212-00-000 | D147: Income tax receivables / 선납세금 | E147: bank interest income(예금이자 201,741 소득세 28,240 지방소득세 2,820) | F147: 2820 | G147: 0
A148: 2025-03-15 | B148: GJ25-0056 | C148: 1212-00-000 | D148: Income tax receivables / 선납세금 | E148: bank interest income(예금이자 201,741 소득세 28,240 지방소득세 2,820) | F148: 28240 | G148: 0
A149: 2025-03-15 | B149: GJ25-0056 | C149: 1112-KR-001 | D149: Cash - KRW (HANA) / 현금 - 원 (HANA) | E149: bank interest income(예금이자 201,741 소득세 28,240 지방소득세 2,820) | F149: 170681 | G149: 0 | H149: VHANABA01
A150: 2025-03-17 | B150: GJ25-0052 | C150: 5263-00-000 | D150: Advertising / 광고비용 | E150: 떡류_현창떡집 | F150: 822727 | G150: 0 | H150: VHYCHNG01
A151: 2025-03-17 | B151: GJ25-0052 | C151: 2407-00-000 | D151: GST/VAT receivable / 부가세대급금 | E151: 떡류_현창떡집 | F151: 82273 | G151: 0 | H151: VHYCHNG01
A152: 2025-03-17 | B152: GJ25-0052 | C152: 2202-00-001 | D152: Other payable / 기타미지급금 | E152: 떡류_현창떡집 | F152: 0 | G152: 905000 | H152: VHYCHNG01
A153: 2025-03-20 | B153: GJ25-0057 | C153: 2202-00-001 | D153: Other payable / 기타미지급금 | E153: [KR Inv_202501] VKPMCOR01_KPMG Acct Service for Dec'24_KRW 31141000 | F153: 715000 | G153: 0 | H153: VKPMCOR01
A154: 2025-03-20 | B154: GJ25-0057 | C154: 1112-KR-001 | D154: Cash - KRW (HANA) / 현금 - 원 (HANA) | E154: [KR Inv_202501] VKPMCOR01_KPMG Acct Service for Dec'24_KRW 31141000 | F154: 0 | G154: 715000 | H154: VKPMCOR01
A155: 2025-03-20 | B155: GJ25-0058 | C155: 2202-00-001 | D155: Other payable / 기타미지급금 | E155: [KR Inv_202503] VKPMCOR01_KPMG Acct Service for Jan'24_KRW 73372750 | F155: 1540000 | G155: 0 | H155: VKPMCOR01
A156: 2025-03-20 | B156: GJ25-0058 | C156: 1112-KR-001 | D156: Cash - KRW (HANA) / 현금 - 원 (HANA) | E156: [KR Inv_202503] VKPMCOR01_KPMG Acct Service for Jan'24_KRW 73372750 | F156: 0 | G156: 1540000 | H156: VKPMCOR01
A157: 2025-03-20 | B157: GJ25-0059 | C157: 2202-00-001 | D157: Other payable / 기타미지급금 | E157: [KR Inv_202503] VSEJUNG01_Kummyung office maintenance fee_KRW 439,610 | F157: 439610 | G157: 0 | H157: VSEJUNG01
A158: 2025-03-20 | B158: GJ25-0059 | C158: 1112-KR-001 | D158: Cash - KRW (HANA) / 현금 - 원 (HANA) | E158: [KR Inv_202503] VSEJUNG01_Kummyung office maintenance fee_KRW 439,610 | F158: 0 | G158: 439610 | H158: VSEJUNG01
A159: 2025-03-21 | B159: GJ25-0053 | C159: 2202-00-001 | D159: Other payable / 기타미지급금 | E159: 소유권이전 (분매리134-249외 4필지, 총 2100평)_김윤석 법무사 | F159: 0 | G159: 330000 | H159: VKIMYUN01
A160: 2025-03-21 | B160: GJ25-0053 | C160: 1712-00-000 | D160: Leasehold land / 토지 | E160: VAT_소유권이전 (분매리134-249외 4필지, 총 2100평)_김윤석 법무사 | F160: 30000 | G160: 0 | H160: VKIMYUN01
... A196: 2025-04-09 | B196: 4 | C196: 5101-00-000 | D196: Management fee expense / 관리 수수료 비용 | E196: 관리비_세정아울렛 관리단 | F196: 0 | G196: 383018 | H196: VSEJUNG01
A197: 2025-04-09 | B197: 4 | C197: 5101-00-000 | D197: Management fee expense / 관리 수수료 비용 | E197: 관리비_세정아울렛 관리단 | F197: 383018 | G197: 0
A198: 2025-04-09 | B198: 4 | C198: 2407-00-000 | D198: GST/VAT receivable / 부가세대급금 | E198: 관리비_세정아울렛 관리단 | F198: 34775 | G198: 0 | H198: VSEJUNG01
A199: 2025-04-09 | B199: 4 | C199: 2407-00-000 | D199: GST/VAT receivable / 부가세대급금 | E199: 관리비_세정아울렛 관리단 | F199: 0 | G199: 38302 | H199: VSEJUNG01
A200: 2025-04-09 | B200: 4 | C200: 2407-00-000 | D200: GST/VAT receivable / 부가세대급금 | E200: 관리비_세정아울렛 관리단 | F200: 38302 | G200: 0
A201: 2025-04-09 | B201: 4 | C201: 2202-00-001 | D201: Other payable / 기타미지급금 | E201: 관리비_세정아울렛 관리단 | F201: 0 | G201: 382530 | H201: VSEJUNG01
A202: 2025-04-09 | B202: 4 | C202: 2202-00-001 | D202: Other payable / 기타미지급금 | E202: 관리비_세정아울렛 관리단 | F202: 421320 | G202: 0 | H202: VSEJUNG01
A203: 2025-04-09 | B203: 4 | C203: 2202-00-001 | D203: Other payable / 기타미지급금 | E203: 관리비_세정아울렛 관리단 | F203: 0 | G203: 421320
A204: 2025-04-09 | B204: 29 | C204: 5101-00-000 | D204: Management fee expense / 관리 수수료 비용 | E204: 관리비_세정아울렛 관리단 | F204: 0 | G204: 347755 | H204: VSEJUNG01
A205: 2025-04-09 | B205: 29 | C205: 2407-00-000 | D205: GST/VAT receivable / 부가세대급금 | E205: 관리비_세정아울렛 관리단 | F205: 0 | G205: 34775 | H205: VSEJUNG01
A206: 2025-04-09 | B206: 29 | C206: 2202-00-001 | D206: Other payable / 기타미지급금 | E206: 관리비_세정아울렛 관리단 | F206: 382530 | G206: 0 | H206: VSEJUNG01
A207: 2025-04-09 | B207: 31 | C207: 5101-00-000 | D207: Management fee expense / 관리 수수료 비용 | E207: 관리비_세정아울렛 관리단 | F207: 347750 | G207: 0 | H207: VSEJUNG01
A208: 2025-04-09 | B208: 31 | C208: 2407-00-000 | D208: GST/VAT receivable / 부가세대급금 | E208: GST/VAT receivable / 부가세대급금 | F208: 34780 | G208: 0 | H208: VSEJUNG01
A209: 2025-04-09 | B209: 31 | C209: 2202-00-001 | D209: Other payable / 기타미지급금 | E209: Sejung Outlet Management | F209: 0 | G209: 382530 | H209: VSEJUNG01
A210: 2025-04-10 | B210: 5 | C210: 5301-00-000 | D210: Bank charges / 은행 수수료 | E210: (HTX)_공인인증서(은행/보험용) | F210: 4000 | G210: 0 | H210: VHANABA01
A211: 2025-04-10 | B211: 5 | C211: 2407-00-000 | D211: GST/VAT receivable / 부가세대급금 | E211: (HTX)_공인인증서(은행/보험용) | F211: 400 | G211: 0 | H211: VHANABA01
A212: 2025-04-10 | B212: 5 | C212: 2202-00-001 | D212: Other payable / 기타미지급금 | E212: (HTX)_공인인증서(은행/보험용) | F212: 0 | G212: 4400 | H212: VHANABA01
A213: 2025-04-10 | B213: 6 | C213: 2202-00-001 | D213: Other payable / 기타미지급금 | E213: Issuance Fee payment | F213: 4400 | G213: 0 | H213: VHANABA01
A214: 2025-04-10 | B214: 6 | C214: 1112-KR-001 | D214: Cash - KRW (HANA) / 현금 - 원 (HANA) | E214: Issuance Fee payment | F214: 0 | G214: 4400 | H214: VHANABA01
A215: 2025-04-10 | B215: 7 | C215: 2202-00-001 | D215: Other payable / 기타미지급금 | E215: (HTX)_소유권이전 (분매리134-249외 4필지, 총 2100평)_김윤석 법무사 | F215: 330000 | G215: 0 | H215: VKIMYUN01
... A217: 2025-04-10 | B217: 7 | C217: 1112-KR-001 | D217: Cash - KRW (HANA) / 현금 - 원 (HANA) | E217: [KR Inv_202503] VKIMYUN01_PJ Phantom_Kummyung Land Registration Transfer Legal Fee_KRW 730830 | F217: 0 | G217: 730830 | H217: VHANABA01
A218: 2025-04-11 | B218: 22 | C218: 5108-00-000 | D218: Other operating expense / 기타 운영 비용 | E218: 압해도 태양광 발전사업 개발용역 6-1_늘샘그린에너지 주식회사 | F218: 20000000 | G218: 0
A219: 2025-04-11 | B219: 22 | C219: 2407-00-000 | D219: GST/VAT receivable / 부가세대급금 | E219: 압해도 태양광 발전사업 개발용역 6-1_늘샘그린에너지 주식회사 | F219: 2000000 | G219: 0
A220: 2025-04-11 | B220: 22 | C220: 1112-KR-001 | D220: Cash - KRW (HANA) / 현금 - 원 (HANA) | E220: 압해도 태양광 발전사업 개발용역 6-1_늘샘그린에너지 주식회사 | F220: 0 | G220: 22000000
A221: 2025-04-11 | B221: 39 | C221: 5108-00-000 | D221: Other operating expense / 기타 운영 비용 | E221: 압해도 태양광 발전사업 개발용역 6-1_늘샘그린에너지 주식회사 | F221: 0 | G221: 20000000 | H221: VNSMGRE01
A222: 2025-04-11 | B222: 39 | C222: 2407-00-000 | D222: GST/VAT receivable / 부가세대급금 | E222: 압해도 태양광 발전사업 개발용역 6-1_늘샘그린에너지 주식회사 | F222: 0 | G222: 2000000 | H222: VNSMGRE01
A223: 2025-04-11 | B223: 39 | C223: 1112-KR-001 | D223: Cash - KRW (HANA) / 현금 - 원 (HANA) | E223: 압해도 태양광 발전사업 개발용역 6-1_늘샘그린에너지 주식회사 | F223: 22000000 | G223: 0 | H223: VNSMGRE01
A224: 2025-04-11 | B224: 40 | C224: 2407-00-000 | D224: GST/VAT receivable / 부가세대급금 | E224: 압해도 태양광 발전사업 개발용역 6-1_늘샘그린에너지 주식회사 | F224: 2000000 | G224: 0 | H224: VNSMGRE01
A225: 2025-04-11 | B225: 40 | C225: 1760-00-028 | D225: Construction work in progress / 건설중인 자산 | E225: 압해도 태양광 발전사업 개발용역 6-1_늘샘그린에너지 주식회사 | F225: 20000000 | G225: 0 | H225: VNSMGRE01
A226: 2025-04-11 | B226: 40 | C226: 1112-KR-001 | D226: Cash - KRW (HANA) / 현금 - 원 (HANA) | E226: 압해도 태양광 발전사업 개발용역 6-1_늘샘그린에너지 주식회사 | F226: 0 | G226: 22000000 | H226: VNSMGRE01
A227: 2025-04-15 | B227: 8 | C227: 5249-00-000 | D227: Other legal and professional fees / 기타 법률 및 전문 수수료 | E227: (HTX)_용역보수 | F227: 0 | G227: 850000 | H227: VKPMCOR01
A228: 2025-04-15 | B228: 8 | C228: 5249-00-000 | D228: Other legal and professional fees / 기타 법률 및 전문 수수료 | E228: (HTX)_용역보수 | F228: 850000 | G228: 0 | H228: VKPMCOR01
A229: 2025-04-15 | B229: 8 | C229: 2407-00-000 | D229: GST/VAT receivable / 부가세대급금 | E229: (HTX)_용역보수 | F229: 0 | G229: 85000 | H229: VKPMCOR01
A230: 2025-04-15 | B230: 8 | C230: 2407-00-000 | D230: GST/VAT receivable / 부가세대급금 | E230: (HTX)_용역보수 | F230: 85000 | G230: 0 | H230: VKPMCOR01
A231: 2025-04-15 | B231: 8 | C231: 2202-00-001 | D231: Other payable / 기타미지급금 | E231: (HTX)_용역보수 | F231: 935000 | G231: 0 | H231: VKPMCOR01
A232: 2025-04-15 | B232: 8 | C232: 2202-00-001 | D232: Other payable / 기타미지급금 | E232: (HTX)_용역보수 | F232: 0 | G232: 935000 | H232: VKPMCOR01
... A240: 2025-04-15 | B240: 38 | C240: 2202-00-001 | D240: Other payable / 기타미지급금 | E240: (HTX)_용역보수 | F240: 0 | G240: 935000 | H240: VKPMCOR01
A241: 2025-04-15 | B241: 41 | C241: 5249-00-000 | D241: Other legal and professional fees / 기타 법률 및 전문 수수료 | E241: (HTX)_용역보수-수정 | F241: 0 | G241: 935000
A242: 2025-04-15 | B242: 41 | C242: 2407-00-000 | D242: GST/VAT receivable / 부가세대급금 | E242: (HTX)_용역보수-수정 | F242: 85000 | G242: 0
A243: 2025-04-15 | B243: 41 | C243: 2202-00-001 | D243: Other payable / 기타미지급금 | E243: (HTX)_용역보수-수정 | F243: 850000 | G243: 0
A244: 2025-04-15 | B244: 42 | C244: 5249-00-000 | D244: Other legal and professional fees / 기타 법률 및 전문 수수료 | E244: (HTX)_용역보수-수정-최종 | F244: 85000 | G244: 0
...

Sheet 외화
B1: FX - realized & FX - unrealized Amount Reconciliation
B2: Periode | C2: =CONTENTS!C2 -> 46112
B3: GL A/C | C3: 6402-00-001 | D3: 6402-00-002 | E3: 5341-00-000 | F3: 5342-00-000
B4: A/C Name | C4: =VLOOKUP(C3, COA!$A$2:$D$587,3,0) -> FX - unrealized gains - others | D4: =VLOOKUP(D3, COA!$A$2:$D$587,3,0) -> FX - unrealized losses - others | E4: =VLOOKUP(E3, COA!$A$2:$D$587,3,0) -> FX - realized gains - others | F4: =VLOOKUP(F3, COA!$A$2:$D$587,3,0) -> FX - realized loss - others
B7: DATE (F-X Rate) | C7: [SGD] | D7: [USD] | E7: [AUD] | F7: [EUR] | G7: [GBP] | I7: GL A/C | J7: A/C Name | K7: TB 잔액 | L7: 검증
B8: 44926 | C8: 956.96 | D8: 1293.84 | E8: 873.38 | G8: 1573.6252
B9: 44957 | C9: 938.16091 | D9: 1243.4094 | E9: 864.27989 | F9: 1338.8838 | G9: 1519.4553 | N9: AUD : 905.133
B10: 44985 | C10: 959.52505 | D10: 1278.7571 | E10: 881.11297 | F10: 1367.3227 | G10: 1542.1755
B11: 45016 | C11: 973.30839 | D11: 1305.2846 | E11: 871.58256 | F11: 1495.7622 | G11: 1582.7628 | N11: EUR : 1617.34
B12: 45046 | C12: 992.11773 | D12: 1321.5501 | E12: 833.43177 | F12: 1447.0834 | G12: 1642.9648
B13: 45077 | C13: 991.06352 | D13: 1327.8019 | E13: 882.18051 | F13: 1441.7189 | G13: 1655.6469 | N13: SGD : 1087.58
B14: 45107 | C14: 962.76 | D14: 1296.1 | E14: 870.324 | F14: 1403.38 | G14: 1635.95
B15: 45138 | C15: 962.599 | D15: 1285.17 | E15: 864.8 | F15: 1419.49 | G15: 1653.52
B16: 45169 | C16: 979.576 | D16: 1323.19 | E16: 857.708 | F16: 1442.29 | G16: 1679.42
B17: 45199 | C17: 978.233 | D17: 1333.39 | E17: 856.569 | F17: 1424.07 | G17: 1652.8
B18: 45230 | C18: 986.913 | D18: 1351.09 | E18: 857.7 | F18: 1427.18 | G18: 1644.41
B19: 45260 | C19: 969.066 | D19: 1307.13 | E19: 848.93 | F19: 1413.05 | G19: 1623.16
B20: 45291 | C20: 978.618 | D20: 1302.98 | E20: 873.089 | F20: 1422.26 | G20: 1649.96
B21: 45322 | C21: 992.112 | D21: 1324.83 | E21: 880.753 | F21: 1445.49 | G21: 1683.53
B22: 45351 | C22: 990.87 | D22: 1332.44 | E22: 868.788 | F22: 1437.98 | G22: 1682.91
B23: 45382 | C23: 993.737 | D23: 1332.85 | E23: 873.48 | F23: 1448.1 | G23: 1693.36
B24: 45412 | C24: 1009.16 | D24: 1369.62 | E24: 891.062 | F24: 1468.41 | G24: 1713.68
B25: 45443 | C25: 1009.94 | D25: 1364.39 | E25: 903.906 | F25: 1474.71 | G25: 1723.45
... B32: 45657 | C32: 1066.32 | D32: 1440.2 | E32: 911.542 | F32: 1508.63 | G32: 1820.29
B33: 45688 | C33: 1067.93 | D33: 1454.62 | E33: 905.409 | F33: 1505.2 | G33: 1795.98 | I33: 6402-00-001 | J33: 외화환산이익 | K33: =IFERROR(VLOOKUP(I33,TB!$A:$F,6,0),0) -> 0 | L33: =K33=-O100 -> TRUE
B34: 45716 | C34: 1073.6 | D34: 1445.99 | E34: 910.908 | F34: 1505.61 | G34: 1811.34 | I34: 6402-00-002 | J34: 외화환산손실 | K34: =IFERROR(VLOOKUP(I34,TB!$A:$F,6,0),0)+34785705 -> 131843129 | L34: =K34=-P100 -> TRUE
B35: 45747 | C35: 1090.87 | D35: 1458.42 | E35: 917.843 | I35: 5341-00-000 | J35: 외환차익 | K35: =-TB!F41+19545120 -> 19545120 | L35: =K35=AA100 -> TRUE
B36: 45777 | C36: 1087.58 | D36: 1439.37 | E36: 905.133 | F36: 1617.34 | I36: 5342-00-000 | J36: 외환차손 | K36: =IFERROR(VLOOKUP(I36,TB!$A:$F,6,0),0)+12302400 -> 82884836 | L36: =K36=-AB100 -> TRUE
B37: 45808 | C37: 1074.28 | D37: 1390.82 | E37: 895.318 | F37: 1568.77 | G37: 1858.58
B38: 45838 | C38: 1064.35 | D38: 1366.28 | E38: 887.427 | F38: 1574.24 | G38: 1852.26
B39: 45869 | C39: 1075.93 | D39: 1378.19 | E39: 901.535 | F39: 1610.82 | G39: 1860.6
B40: 45900 | C40: 1080.93 | D40: 1389.02 | E40: 902.409 | F40: 1618.01 | G40: 1868.49
B41: 45930 | C41: 1084.57 | D41: 1393.84 | E41: 918.748 | F41: 1635.24
