Workbook

Sheet CFS Template_2026
B1: Liquidity Item | C1: January | D1: February | E1: March | F1: April | G1: May | H1: June | I1: July | J1: August | K1: September | L1: October | M1: November | N1: December | O1: Accumulated
R2: Please, only include figures in green cells
A3: Operating Activities | O3: =SUM(C3:N3) -> 0
A4: Cash receipts from customers | B4: OA_BLACK_TP | O4: =SUM(C4:N4) -> 0
A5: Cash paid to suppliers | D5: =SUM(D6:D8) -> 0 | O5: =SUM(C5:N5) -> 0
A6: Cash paid for O&M (Operation & maintenace costs) | B6: OA_OM_TP | O6: =SUM(C6:N6) -> 0
A7: Cash paid for leases and Rents | B7: OA_LEASES | D7: =+'2월'!D10 -> 0 | O7: =SUM(C7:N7) -> 0
A8: Cash paid to other suppliers | B8: OA_OTHER_SS_TP | D8: =+'2월'!B2 -> 0 | O8: =SUM(C8:N8) -> 0
A9: Cash paid to personnel | B9: OA_PERSONNEL | D9: ='2월'!B3 -> 0 | O9: =SUM(C9:N9) -> 0 | R9: Include counterparty information in payments / collections with related parties
A10: Other receipts / (payments) relating to operating activities | D10: =D15+D16+D14+D11 -> 644123235 | O10: =SUM(C10:N10) -> 644123235
A11: State and Other Public Entities | D11: =SUM(D12:D13) -> 0 | O11: =SUM(C11:N11) -> 0
A12: VAT | B12: OA_VAT_OUT | O12: =SUM(C12:N12) -> 0
A13: Other Taxes | B13: OA_OTHERTAX_OUT | O13: =SUM(C13:N13) -> 0
A14: Guarantees received / (paid) | B14: OA_GUARANTEES | O14: =SUM(C14:N14) -> 0
A15: Other Municipal and tax Payments | B15: OA_CONCESSIONS | D15: =+'2월'!B4+C14+C16+C11 -> 660324915 | O15: =SUM(C15:N15) -> 660324915
A16: Other receipts / (payments) | B16: OA_OTHERS_OTHERS | D16: =+'2월'!B5 -> -16201680 | O16: =SUM(C16:N16) -> -16201680
A17: Net cash flows from operations | D17: =D4+D5+D9+D10 -> 644123235 | O17: =SUM(C17:N17) -> 644123235
A18: Income tax received (CASH-IN) | B18: OA_INCOMETAX_IN | O18: =SUM(C18:N18) -> 0 | R18: Please include receipts with a positive sign and payments with a negative sign.
A19: Income tax paid (CASH-OUT) | B19: OA_INCOMETAX_OUT | O19: =SUM(C19:N19) -> 0
A20: Net cash flows from operating activities | D20: =D17+D18+D19 -> 644123235 | O20: =SUM(C20:N20) -> 644123235
A21: Investing Activities
A22: Cash receipts relating to: | D22: =SUM(D23:D30) -> 0 | O22: =SUM(C22:N22) -> 0
A23: Changes in cash resulting from perimeter variations (CASH-IN | B23: IA_CHANGESPER_IN | O23: =SUM(C23:N23) -> 0
A24: Financial assets (CASH-IN) / Sale of assets - subsidiaries | B24: IA_FINASSETS_IN | O24: =SUM(C24:N24) -> 0 | R24: Payments related to capitalized costs as fixed assets should be reflected in investment flows (Property, plant and equipment (CASH-OUT).
A25: Property, plant and equipment (CASH-IN) | B25: IA_TANGIBLE_IN | O25: =SUM(C25:N25) -> 0
A26: Intangible assets (CASH-IN) | B26: IA_INTANGIB_IN | O26: =SUM(C26:N26) -> 0
A27: Loans to related parties (CASH-IN) | B27: IA_GRLOANS_IN | O27: =SUM(C27:N27) -> 0
A28: Subsidies for investment | B28: IA_SUBSIDIES | O28: =SUM(C28:N28) -> 0
A29: Interest and similar income | B29: IA_INTEREST_SIM | O29: =SUM(C29:N29) -> 0
A30: Dividends received | B30: IA_DIVIDENDS | O30: =SUM(C30:N30) -> 0
A31: Cash payments relating to: | D31: =SUM(D32:D36) -> 0 | O31: =SUM(C31:N31) -> 0
A32: Financial assets (CASH-OUT) / Acquisition of assets – subsid | B32: IA_FINASSETS_OUT | O32: =SUM(C32:N32) -> 0
A33: Changes in cash resulting from perimeter variations | B33: IA_CHANGES_PERIM | O33: =SUM(C33:N33) -> 0
A34: Property, plant and equipment (CASH-OUT) | B34: IA_TANGIBLE_OUT | O34: =SUM(C34:N34) -> 0
A35: Intangible assets (CASH-OUT) | B35: IA_INTANGIB_OUT | O35: =SUM(C35:N35) -> 0
A36: Loans to related parties (CASH-OUT) | B36: IA_GRLOANS_OUT | O36: =SUM(C36:N36) -> 0
A37: Net cash flows from investing activities | D37: =D31+D22 -> 0 | O37: =SUM(C37:N37) -> 0
A38: Financing Activities
A39: Cash receipts relating to: | D39: =D40+D43+D46+D47+D48+D49+D50 -> 0 | O39: =SUM(C39:N39) -> 0
A40: Receipts of loans | D40: =SUM(D41:D42) -> 0 | O40: =SUM(O41:O42) -> 0
A41: Loans with the Group (CASH-IN) | B41: FA_GRLOANS_IN | O41: =SUM(C41:N41) -> 0
A42: Loans with third parties(CASH-IN) | B42: FA_TPLOANS_IN | O42: =SUM(C42:N42) -> 0
A43: Interest and similar income including hedge derivatives | D43: =SUM(D44:D45) -> 0 | O43: =SUM(O44:O45) -> 0
A44: Interest with the Group(CASH-IN) | B44: FA_GRINTERES_IN | O44: =SUM(C44:N44) -> 0
A45: Interest with third parties(CASH-IN) | B45: FA_TPINTERES_IN | O45: =SUM(C45:N45) -> 0
A46: Share capital increases (CASH-IN) | B46: FA_CAPITAL_IN | O46: =SUM(C46:N46) -> 0
A47: Subsidies and donations | B47: FA_SUBSIDIES | O47: =SUM(C47:N47) -> 0
A48: Share capital increases by non-controlling interests (CASH-I | B48: FA_CAPIT_NCI_IN | O48: =SUM(C48:N48) -> 0
A49: Receipts of derivative financial instruments | B49: FA_DERIV_IN | O49: =SUM(C49:N49) -> 0
A50: Receipts from wind activity institutional partnership - USA | B50: FA_TAXEQ_IN | O50: =SUM(C50:N50) -> 0
A51: Cash payments relating to: | D51: =D52+D55+D58+D59+D60+D61+D62+D63 -> 0 | O51: =O52+O55+O58+O59+O60+O61+O62+O63 -> 0
A52: Payments of loans | D52: =SUM(D53:D54) -> 0 | O52: =SUM(O53:O54) -> 0
A53: Loans with the Group (CASH-OUT) | B53: FA_GRLOANS_OUT | O53: =SUM(C53:N53) -> 0
A54: Loans with third parties(CASH-OUT) | B54: FA_TPLOANS_OUT | O54: =SUM(C54:N54) -> 0
A55: Interest and similar expenses including hedge derivatives | D55: =SUM(D56:D57) -> 0 | O55: =SUM(O56:O57) -> 0
A56: Interest with the Group(CASH-OUT) | B56: FA_GRINTERES_OUT | O56: =SUM(C56:N56) -> 0
A57: Interest with third parties(CASH-OUT) | B57: FA_TPINTERES_OUT | O57: =SUM(C57:N57) -> 0
A58: Share capital decreases (CASH-OUT) | B58: FA_CAPITAL_OUT | O58: =SUM(C58:N58) -> 0
A59: Share capital decreases by non-controlling interests (CASH-O | B59: FA_CAPIT_NCI_OUT | O59: =SUM(C59:N59) -> 0
A60: Payment of lease liabilities | B60: FA_PAYMENTLEASE | O60: =SUM(C60:N60) -> 0
A61: Payments of derivative financial instruments | B61: FA_DERIV_OUT | O61: =SUM(C61:N61) -> 0
A62: Dividends paid | B62: FA_DIVIDENDS_TP | O62: =SUM(C62:N62) -> 0
A63: Payments from wind activity institutional partnership - USA | B63: FA_TAXEQ_OUT | O63: =SUM(C63:N63) -> 0
A64: Net cash flows from financing activities | D64: =D51+D39 -> 0 | O64: =O51+O39 -> 0
A65: Net cash and cash equivalents | D65: =-(D20+D37+D64) -> -644123235 | O65: =SUM(C65:N65) -> -644123235
A66: Effect of exchange rate fluctuations on cash held | B66: EXCHANGE_RATES
A67: Cash and cash equivalents at the beginning of the period | B67: BALANCE_INI | D67: 644123235 | O67: =C67 -> 0
A68: Cash and cash equivalents at the end of the period | B68: SF | D68: =D65+D66+D67 -> 0 | O68: =N68 -> 0
A69: Company | B69: LPSK | D69: =+D68='2월'!I17 -> TRUE
A70: Currency | B70: KRW
D72: =D67-D68 -> 644123235
D73: =D69-D71 -> 1
D75: =D72-D73 -> 644123234

Sheet 2월
C1: (KRW)
A2: Cash paid to other suppliers | C2: 2024 Cash paid for leases and Rents | F2: Being return of deposit from landlord | G2: 10000000 | I2: 654121727
A3: Cash paid to personnel | C3: Details | D3: December | F3: transfer (Shinhan -> HSBC) | G3: 6202688 | I3: 660324415
A4: Other Municipal and tax Payments | B4: =+H4+H5+H6+H7+H22-G3 -> 660324915 | C4: Monthly room rental fee | F4: Being payment to Green Cross I-Med for healthcare screening fee | H4: 1800000 | I4: 658524415
A5: Other receipts / (payments) | B5: =-G21-G2 -> -16201680 | C5: CAR RENTAL (BMW 520i Iux Lci60)-Deposit (30%) | F5: Monthly IT Maintenance Service fee | H5: 330000 | I5: 658194415
C6: CAR RENTAL FEE | D6: 0 | F6: Being payment of office reinstatement fee to M2 Design | H6: 500000 | I6: 657694415
A7: Loans with the Group (CASH-OUT) | C7: EDPR KR-Office sublease-Deposit | F7: Being payment of management fees to SSG | H7: 657694415
A8: Interest with the Group(CASH-OUT) | C8: EDPR KR-Office sublease-Monthly lease | D8: =+H12 -> 0
C9: Office rent/management fee_March, April, May
A10: Loans with the Group (CASH-IN) | C10: Total | D10: =SUM(D4:D9) -> 0
A12: Interest and similar income
G14: 4656329 | H14: 80031670
G15: 1921204931 | H15: 1277083204
H17: =I13+I22 -> 0 | I17: =+I7+J22 -> 0
G20: 1508 | I20: 1508
F21: VAT refund | G21: 6201680 | I21: 6203188
F22: transfer (Shinhan -> HSBC) | H22: 6203188
G23: 6201680 | H23: 6203188
G24: 6203188 | H24: 6203188

Sheet Leases,Rents
B1: (KRW)
B2: 2023 Cash paid for leases and Rents
B3: Details | C3: January | D3: February | E3: March | F3: April | G3: May | H3: June | I3: July | J3: August | K3: September | L3: October | M3: November | N3: December
B4: Monthly room rental fee
B5: CAR RENTAL (BMW 520i Iux Lci60)-Deposit (30%)
B6: CAR RENTAL FEE | C6: 1430000 | D6: 1430000 | E6: 1430000 | F6: 1430000 | G6: 1430000
B7: EDPR KR-Office sublease-Deposit
B8: EDPR KR-Office sublease-Monthly lease | D8: 15002526 | F8: 12259206 | G8: =#REF!*2 -> #REF!
B9: Office rent/management fee_March, April, May
B10: Total | C10: =SUM(C4:C9) -> 1430000 | D10: =SUM(D4:D9) -> 16432526 | E10: =SUM(E4:E9) -> 1430000 | F10: =SUM(F4:F9) -> 13689206 | G10: =SUM(G4:G9) -> #REF! | H10: =SUM(H4:H9) -> 0 | I10: =SUM(I4:I9) -> 0 | J10: =SUM(J4:J9) -> 0 | ... N10: =SUM(N4:N9) -> 0
C11: =-C10='CFS Template_2026'!C7 -> FALSE

Sheet CFS Template_2022
B1: Liquidity Item | C1: January | D1: February | E1: March | F1: April | G1: May | H1: June | I1: July | J1: August | K1: September | L1: October | M1: November | N1: December | O1: Accumulated
R2: Please, only include figures in green cells
A3: Operating Activities | O3: =SUM(C3:N3) -> 0
A4: Cash receipts from customers | B4: OA_BLACK_TP | O4: =SUM(C4:N4) -> 0
A5: Cash paid to suppliers | C5: =SUM(C6:C8) -> 0 | D5: =SUM(D6:D8) -> -5082500 | E5: =SUM(E6:E8) -> -147782000 | F5: =SUM(F6:F8) -> -5082000 | G5: =SUM(G6:G8) -> -8030000 | H5: =SUM(H6:H8) -> -274436088 | I5: =SUM(I6:I8) -> -51898720 | J5: =SUM(J6:J8) -> -33672065 | ... N5: =SUM(N6:N8) -> -94068796 | O5: =SUM(C5:N5) -> -1136251576
A6: Cash paid for O&M (Operation & maintenace costs) | B6: OA_OM_TP | E6: =-(83600000+38500000) -> -122100000 | G6: -6600000 | H6: -111650000 | I6: =-1650000-20900000 -> -22550000 | K6: -22012066 | O6: =SUM(C6:N6) -> -284912066
A7: Cash paid for leases and Rents | B7: OA_LEASES | D7: -5082500 | E7: =-(19170000+5082000+1430000) -> -25682000 | F7: -5082000 | G7: -1430000 | H7: -162786088 | I7: =-15002526-1430000 -> -16432526 | J7: =-1430000-15002526 -> -16432526 | K7: =-1430000-15002526 -> -16432526 | L7: =-1430000-15002526 -> -16432526 | M7: -1430000 | N7: -46437578 | O7: =SUM(C7:N7) -> -313660270
A8: Cash paid to other suppliers | B8: OA_OTHER_SS_TP | I8: =-5318500-5318500-2279194 -> -12916194 | J8: =-8281799-5318500-1650000-1989240 -> -17239539 | K8: =-15500000+-2178000+-238000+-1039500+-346500+-390884769+-1100000+-13132878+-1650000+-418000+-5318500 -> -431806147 | L8: -30000 | M8: -28056142 | N8: =-(1650000+9500705+5733280+6820280+1650000+1136300+44000+2761000+1697270+1305240+1149223+618220+303910+280000+410790+5318500+7252500) -> -47631218 | O8: =SUM(C8:N8) -> -537679240
A9: Cash paid to personnel | B9: OA_PERSONNEL | J9: =-9363023-78410 -> -9441433 | K9: =-94900 -> -94900 | L9: =-26170920+-43528748 -> -69699668 | M9: -62434194 | N9: =-56257038-10000 -> -56267038 | O9: =SUM(C9:N9) -> -197937233 | R9: Include counterparty information in payments / collections with related parties
A10: Other receipts / (payments) relating to operating activities | C10: =C11+C14+C15+C16 -> 0 | D10: =D11+D14+D15+D16 -> 0 | E10: =E11+E14+E15+E16 -> 0 | F10: =F11+F14+F15+F16 -> 0 | G10: =G11+G14+G15+G16 -> 0 | H10: =H11+H14+H15+H16 -> 0 | I10: =I11+I14+I15+I16 -> -181500 | J10: =J11+J14+J15+J16 -> -2167480 | ... N10: =N11+N14+N15+N16 -> -17420 | O10: =SUM(C10:N10) -> 25353110
A11: State and Other Public Entities | C11: =SUM(C12:C13) -> 0 | D11: =SUM(D12:D13) -> 0 | E11: =SUM(E12:E13) -> 0 | F11: =SUM(F12:F13) -> 0 | G11: =SUM(G12:G13) -> 0 | H11: =SUM(H12:H13) -> 0 | I11: =SUM(I12:I13) -> 0 | J11: =SUM(J12:J13) -> -1071170 | ... N11: =SUM(N12:N13) -> -17420 | O11: =SUM(C11:N11) -> -1088590
A12: VAT | B12: OA_VAT_OUT | O12: =SUM(C12:N12) -> 0
A13: Other Taxes | B13: OA_OTHERTAX_OUT | J13: =-889670-181500 -> -1071170 | N13: -17420 | O13: =SUM(C13:N13) -> -1088590
A14: Guarantees received / (paid) | B14: OA_GUARANTEES | O14: =SUM(C14:N14) -> 0
A15: Other Municipal and tax Payments | B15: OA_CONCESSIONS | I15: -181500 | J15: -1096310 | L15: =-62500 -> -62500 | O15: =SUM(C15:N15) -> -1340310
A16: Other receipts / (payments) | B16: OA_OTHERS_OTHERS | K16: 27812600 | M16: -30590 | O16: =SUM(C16:N16) -> 27782010
A17: Net cash flows from operations | C17: =C10+C9+C5+C4 -> 0 | D17: =D10+D9+D5+D4 -> -5082500 | E17: =E10+E9+E5+E4 -> -147782000 | F17: =F10+F9+F5+F4 -> -5082000 | G17: =G10+G9+G5+G4 -> -8030000 | H17: =H10+H9+H5+H4 -> -274436088 | I17: =I10+I9+I5+I4 -> -52080220 | J17: =J10+J9+J5+J4 -> -45280978 | ... N17: =N10+N9+N5+N4 -> -150353254 | O17: =SUM(C17:N17) -> -1308835699
A18: Income tax received (CASH-IN) | B18: OA_INCOMETAX_IN | O18: =SUM(C18:N18) -> 0 | R18: Please include receipts with a positive sign and payments with a negative sign.
A19: Income tax paid (CASH-OUT) | B19: OA_INCOMETAX_OUT | H19: -1490 | K19: =-16500+-170020+-2608680+-260860 -> -3056060 | L19: =-187050+-5323660+-532350 -> -6043060 | M19: -6633280 | N19: =-(39000+390000+7930340+793000) -> -9152340 | O19: =SUM(C19:N19) -> -24886230
A20: Net cash flows from operating activities | C20: =C17+C18+C19 -> 0 | D20: =D17+D18+D19 -> -5082500 | E20: =E17+E18+E19 -> -147782000 | F20: =F17+F18+F19 -> -5082000 | G20: =G17+G18+G19 -> -8030000 | H20: =H17+H18+H19 -> -274437578 | I20: =I17+I18+I19 -> -52080220 | J20: =J17+J18+J19 -> -45280978 | ... N20: =N17+N18+N19 -> -159505594 | O20: =SUM(C20:N20) -> -1333721929
A21: Investing Activities
A22: Cash receipts relating to: | C22: =SUM(C23:C30) -> 0 | D22: =SUM(D23:D30) -> 0 | E22: =SUM(E23:E30) -> 0 | F22: =SUM(F23:F30) -> 0 | G22: =SUM(G23:G30) -> 0 | H22: =SUM(H23:H30) -> 9676 | I22: =SUM(I23:I30) -> 0 | J22: =SUM(J23:J30) -> 0 | ... N22: =SUM(N23:N30) -> 113166 | O22: =SUM(C22:N22) -> 122842
A23: Changes in cash resulting from perimeter variations (CASH-IN | B23: IA_CHANGESPER_IN | O23: =SUM(C23:N23) -> 0
A24: Financial assets (CASH-IN) / Sale of assets - subsidiaries | B24: IA_FINASSETS_IN | O24: =SUM(C24:N24) -> 0 | R24: Payments related to capitalized costs as fixed assets should be reflected in investment flows (Property, plant and equipment (CASH-OUT).
A25: Property, plant and equipment (CASH-IN) | B25: IA_TANGIBLE_IN | O25: =SUM(C25:N25) -> 0
A26: Intangible assets (CASH-IN) | B26: IA_INTANGIB_IN | O26: =SUM(C26:N26) -> 0
A27: Loans to related parties (CASH-IN) | B27: IA_GRLOANS_IN | O27: =SUM(C27:N27) -> 0
A28: Subsidies for investment | B28: IA_SUBSIDIES | O28: =SUM(C28:N28) -> 0
A29: Interest and similar income | B29: IA_INTEREST_SIM | H29: 9676 | N29: 113166 | O29: =SUM(C29:N29) -> 122842
A30: Dividends received | B30: IA_DIVIDENDS | O30: =SUM(C30:N30) -> 0
A31: Cash payments relating to: | C31: =SUM(C32:C36) -> 0 | D31: =SUM(D32:D36) -> 0 | E31: =SUM(E32:E36) -> 0 | F31: =SUM(F32:F36) -> 0 | G31: =SUM(G32:G36) -> 0 | H31: =SUM(H32:H36) -> 0 | I31: =SUM(I32:I36) -> 0 | J31: =SUM(J32:J36) -> 0 | ... N31: =SUM(N32:N36) -> 0 | O31: =SUM(C31:N31) -> -12359896
A32: Financial assets (CASH-OUT) / Acquisition of assets – subsid | B32: IA_FINASSETS_OUT | K32: =-5794740+-4020156 -> -9814896 | O32: =SUM(C32:N32) -> -9814896
A33: Changes in cash resulting from perimeter variations | B33: IA_CHANGES_PERIM | O33: =SUM(C33:N33) -> 0
A34: Property, plant and equipment (CASH-OUT) | B34: IA_TANGIBLE_OUT | K34: -1500000 | L34: -1045000 | O34: =SUM(C34:N34) -> -2545000
A35: Intangible assets (CASH-OUT) | B35: IA_INTANGIB_OUT | O35: =SUM(C35:N35) -> 0
A36: Loans to related parties (CASH-OUT) | B36: IA_GRLOANS_OUT | O36: =SUM(C36:N36) -> 0
A37: Net cash flows from investing activities | C37: =C31+C22 -> 0 | D37: =D31+D22 -> 0 | E37: =E31+E22 -> 0 | F37: =F31+F22 -> 0 | G37: =G31+G22 -> 0 | H37: =H31+H22 -> 9676 | I37: =I31+I22 -> 0 | J37: =J31+J22 -> 0 | ... N37: =N31+N22 -> 113166 | O37: =SUM(C37:N37) -> -12237054
A38: Financing Activities
A39: Cash receipts relating to: | C39: =C40+C43+C46+C47+C48+C49+C50 -> 100000000 | D39: =D40+D43+D46+D47+D48+D49+D50 -> 0 | E39: =E40+E43+E46+E47+E48+E49+E50 -> 200000000 | F39: =F40+F43+F46+F47+F48+F49+F50 -> 0 | G39: =G40+G43+G46+G47+G48+G49+G50 -> 0 | H39: =H40+H43+H46+H47+H48+H49+H50 -> 423000000 | I39: =I40+I43+I46+I47+I48+I49+I50 -> 0 | J39: =J40+J43+J46+J47+J48+J49+J50 -> 0 | ... N39: =N40+N43+N46+N47+N48+N49+N50 -> -10231350 | O39: =SUM(C39:N39) -> 1621374180
A40: Receipts of loans | C40: =SUM(C41:C42) -> 0 | D40: =SUM(D41:D42) -> 0 | E40: =SUM(E41:E42) -> 200000000 | F40: =SUM(F41:F42) -> 0 | G40: =SUM(G41:G42) -> 0 | H40: =SUM(H41:H42) -> 423000000 | I40: =SUM(I41:I42) -> 0 | J40: =SUM(J41:J42) -> 0 | ... O40: =SUM(O41:O42) -> 1533000000
A41: Loans with the Group (CASH-IN) | B41: FA_GRLOANS_IN | E41: 200000000 | H41: 423000000 | K41: 410000000 | M41: 500000000 | O41: =SUM(C41:N41) -> 1533000000
A42: Loans with third parties(CASH-IN) | B42: FA_TPLOANS_IN | O42: =SUM(C42:N42) -> 0
A43: Interest and similar income including hedge derivatives | C43: =SUM(C44:C45) -> 0 | D43: =SUM(D44:D45) -> 0 | E43: =SUM(E44:E45) -> 0 | F43: =SUM(F44:F45) -> 0 | G43: =SUM(G44:G45) -> 0 | H43: =SUM(H44:H45) -> 0 | I43: =SUM(I44:I45) -> 0 | J43: =SUM(J44:J45) -> 0 | ... O43: =SUM(O44:O45) -> 0
A44: Interest with the Group(CASH-IN) | B44: FA_GRINTERES_IN | O44: =SUM(C44:N44) -> 0
A45: Interest with third parties(CASH-IN) | B45: FA_TPINTERES_IN | O45: =SUM(C45:N45) -> 0
A46: Share capital increases (CASH-IN) | B46: FA_CAPITAL_IN | C46: 100000000 | O46: =SUM(C46:N46) -> 100000000
A47: Subsidies and donations | B47: FA_SUBSIDIES | L47: -1394470 | N47: -10231350 | O47: =SUM(C47:N47) -> -11625820
A48: Share capital increases by non-controlling interests (CASH-I | B48: FA_CAPIT_NCI_IN | O48: =SUM(C48:N48) -> 0
A49: Receipts of derivative financial instruments | B49: FA_DERIV_IN | O49: =SUM(C49:N49) -> 0
A50: Receipts from wind activity institutional partnership - USA | B50: FA_TAXEQ_IN | O50: =SUM(C50:N50) -> 0
A51: Cash payments relating to: | C51: =C52+C55+C58+C59+C60+C61+C62+C63 -> 0 | D51: =D52+D55+D58+D59+D60+D61+D62+D63 -> 0 | E51: =E52+E55+E58+E59+E60+E61+E62+E63 -> 0 | F51: =F52+F55+F58+F59+F60+F61+F62+F63 -> 0 | G51: =G52+G55+G58+G59+G60+G61+G62+G63 -> 0 | H51: =H52+H55+H58+H59+H60+H61+H62+H63 -> 0 | I51: =I52+I55+I58+I59+I60+I61+I62+I63 -> 0 | J51: =J52+J55+J58+J59+J60+J61+J62+J63 -> 0 | ... O51: =O52+O55+O58+O59+O60+O61+O62+O63 -> 0
A52: Payments of loans | C52: =SUM(C53:C54) -> 0 | D52: =SUM(D53:D54) -> 0 | E52: =SUM(E53:E54) -> 0 | F52: =SUM(F53:F54) -> 0 | G52: =SUM(G53:G54) -> 0 | H52: =SUM(H53:H54) -> 0 | I52: =SUM(I53:I54) -> 0 | J52: =SUM(J53:J54) -> 0 | ... O52: =SUM(O53:O54) -> 0
A53: Loans with the Group (CASH-OUT) | B53: FA_GRLOANS_OUT | O53: =SUM(C53:N53) -> 0
A54: Loans with third parties(CASH-OUT) | B54: FA_TPLOANS_OUT | O54: =SUM(C54:N54) -> 0
A55: Interest and similar expenses including hedge derivatives | C55: =SUM(C56:C57) -> 0 | D55: =SUM(D56:D57) -> 0 | E55: =SUM(E56:E57) -> 0 | F55: =SUM(F56:F57) -> 0 | G55: =SUM(G56:G57) -> 0 | H55: =SUM(H56:H57) -> 0 | I55: =SUM(I56:I57) -> 0 | J55: =SUM(J56:J57) -> 0 | ... O55: =SUM(O56:O57) -> 0
A56: Interest with the Group(CASH-OUT) | B56: FA_GRINTERES_OUT | O56: =SUM(C56:N56) -> 0
A57: Interest with third parties(CASH-OUT) | B57: FA_TPINTERES_OUT | O57: =SUM(C57:N57) -> 0
A58: Share capital decreases (CASH-OUT) | B58: FA_CAPITAL_OUT | O58: =SUM(C58:N58) -> 0
A59: Share capital decreases by non-controlling interests (CASH-O | B59: FA_CAPIT_NCI_OUT | O59: =SUM(C59:N59) -> 0
A60: Payment of lease liabilities | B60: FA_PAYMENTLEASE | O60: =SUM(C60:N60) -> 0
A61: Payments of derivative financial instruments | B61: FA_DERIV_OUT | O61: =SUM(C61:N61) -> 0
A62: Dividends paid | B62: FA_DIVIDENDS_TP | O62: =SUM(C62:N62) -> 0
A63: Payments from wind activity institutional partnership - USA | B63: FA_TAXEQ_OUT | O63: =SUM(C63:N63) -> 0
A64: Net cash flows from financing activities | C64: =C51+C39 -> 100000000 | D64: =D51+D39 -> 0 | E64: =E51+E39 -> 200000000 | F64: =F51+F39 -> 0 | G64: =G51+G39 -> 0 | H64: =H51+H39 -> 423000000 | I64: =I51+I39 -> 0 | J64: =J51+J39 -> 0 | ... O64: =O51+O39 -> 1621374180
A65: Net cash and cash equivalents | C65: =C64+C37+C20 -> 100000000 | D65: =D64+D37+D20 -> -5082500 | E65: =E64+E37+E20 -> 52218000 | F65: =F64+F37+F20 -> -5082000 | G65: =G64+G37+G20 -> -8030000 | H65: =H64+H37+H20 -> 148572098 | I65: =I64+I37+I20 -> -52080220 | J65: =J64+J37+J20 -> -45280978 | ... N65: =N64+N37+N20 -> -169623778 | O65: =SUM(C65:N65) -> 275415197
A66: Effect of exchange rate fluctuations on cash held | B66: EXCHANGE_RATES
A67: Cash and cash equivalents at the beginning of the period | B67: BALANCE_INI | D67: =C68 -> 100000000 | E67: =D68 -> 94917500 | F67: =E68 -> 147135500 | G67: =F68 -> 142053500 | H67: =G68 -> 134023500 | I67: =H68 -> 282595598 | J67: =I68 -> 230515378 | K67: =J68 -> 185234400 | ... N67: =M68 -> 445038975 | O67: =C67 -> 0
A68: Cash and cash equivalents at the end of the period | B68: SF | C68: =C65+C66+C67 -> 100000000 | D68: =D65+D66+D67 -> 94917500 | E68: =E65+E66+E67 -> 147135500 | F68: =F65+F66+F67 -> 142053500 | G68: =G65+G66+G67 -> 134023500 | H68: =H65+H66+H67 -> 282595598 | I68: =I65+I66+I67 -> 230515378 | J68: =J65+J66+J67 -> 185234400 | ... N68: =N65+N66+N67 -> 275415197 | O68: =N68 -> 275415197
A69: Company | B69: LPSK
A70: Currency | B70: KRW

Sheet Leases,Rents_2022
B1: (KRW)
B2: Cash paid for leases and Rents
B3: Details | C3: January | D3: February | E3: March | F3: April | G3: May | H3: June | I3: July | J3: August | K3: September | L3: October | M3: November | N3: December
B4: Monthly room rental fee | D4: 5082500 | E4: 5082000 | F4: 5082000 | H4: 0
B5: CAR RENTAL (BMW 520i Iux Lci60)-Deposit (30%) | E5: 19170000
B6: CAR RENTAL FEE | E6: 1430000 | G6: 1430000 | H6: 1430000 | I6: 1430000 | J6: 1430000 | K6: 1430000 | L6: 1430000 | M6: 1430000 | N6: =1430000+40630 -> 1470630
B7: EDPR KR-Office sublease-Deposit | H7: 111013400
B8: EDPR KR-Office sublease-Monthly lease | H8: 15002526 | I8: 15002526 | J8: 15002526 | K8: 15002526 | L8: 15002526 | N8: =15002526*3 -> 45007578
B9: Office rent/management fee_March, April, May | H9: 35340162
B10: Total | D10: =SUM(D4:D9) -> 5082500 | E10: =SUM(E4:E9) -> 25682000 | F10: =SUM(F4:F9) -> 5082000 | G10: =SUM(G4:G9) -> 1430000 | H10: =SUM(H4:H9) -> 162786088 | I10: =SUM(I4:I9) -> 16432526 | J10: =SUM(J4:J9) -> 16432526 | K10: =SUM(K4:K9) -> 16432526 | ... N10: =SUM(N4:N9) -> 46478208
D11: =-D10='CFS Template_2026'!D7 -> FALSE | E11: =-E10='CFS Template_2026'!E7 -> FALSE | F11: =-F10='CFS Template_2026'!F7 -> FALSE | G11: =-G10='CFS Template_2026'!G7 -> FALSE | H11: =-H10='CFS Template_2026'!H7 -> FALSE | I11: =-I10='CFS Template_2026'!I7 -> FALSE | J11: =-J10='CFS Template_2026'!J7 -> FALSE | K11: =-K10='CFS Template_2026'!K7 -> FALSE | L11: =-L10='CFS Template_2026'!L7 -> FALSE | M11: =M10=-'CFS Template_2026'!M7 -> FALSE | N11: =N10=-'CFS Template_2026'!N7 -> FALSE
